Workbook

Sheet Mapa de emendas
A1: Ano | C1: Região | D1: Endereço | E1: Beneficiário | F1: CNPJ Beneficiário | G1: Instituição | H1: Nº da Emenda | I1: Área de alocação | J1: Área | K1: Modalidade | L1: Valores destinados | M1: Observação | N1: Tipo da emenda | O1: Situação | P1: Informações adicionais | Q1: Andamento
A2: 2024 | B2: Gramado | C2: =IFERROR(VLOOKUP(B2,'Regiões'!A:B,2,0),"") -> Turismo da Serra | D2: Avenida das Hortênsias, 2029 - Centro, Gramado - RS, CEP 95670-000, Brasil | E2: =G2&" de "&B2 -> Prefeitura Municipal de Gramado | G2: Prefeitura Municipal | H2: 41160005 | I2: Defesa Civil | J2: Defesa Civil | K2: Custeio | L2: 0 | N2: Emenda Individual
A3: 2023 | B3: Rio Grande | D3: Marinha, Rio Grande,RS | E3: Fundo Naval | G3: Fundo Naval | H3: 41160009 | I3: Segurança Pública | J3: Segurança Pública | K3: Custeio | L3: 1200 | N3: Emenda Individual | O3: Recurso pago
A4: 2020 | B4: Bagé | C4: =IFERROR(VLOOKUP(B4,'Regiões'!A:B,2,0),"") -> Sudoeste do Estado | D4: 9ª Delegacia de Polícia Regional – Bagé, Bagé, RS | E4: Polícia Civil | G4: 9ª Delegacia de Polícia Regional – Bagé | H4: 41160010 | I4: Segurança pública | J4: Segurança Pública | K4: Investimento | L4: 12142.85 | N4: Emenda individual | O4: Recurso empenhado. Inexigibilidade de licitação aceita pelo Ministério. Recurso pago em 25/04/2022. De acordo com consulta feita no Transferegov, em 03/04/2024, não é possível afirmar que foi pago. Há dois convênio com o MS vinculados a essa emenda, um deles vigente até 04/2025. Será necessário consultar o órgão para verificar se o valor referente à Polícia Civil de Bagé foi recebido. | P4: Aquisição de Ferramenta Forense para extração, processamento e apoio na análise de dados e informações a partir de plataformas eletrônicas portáteis para estruturar a 9ª Delegacia de Polícia Regional do Interior - Bagé.
A5: 2022 | B5: Barão de Cotegipe | C5: =IFERROR(VLOOKUP(B5,'Regiões'!A:B,2,0),"") -> Alto Uruguai | D5: Prefeitura Municipal, Barão de Cotegipe, RS | E5: Município | G5: Prefeitura Municipal | H5: 41160002 | I5: Saúde (Custeio - PAB) | J5: Saúde | K5: Custeio | L5: 20000 | N5: Emenda Individual | O5: Recurso pago
A6: 2022 | B6: Barão de Cotegipe | C6: =IFERROR(VLOOKUP(B6,'Regiões'!A:B,2,0),"") -> Alto Uruguai | D6: Prefeitura Municipal, Barão de Cotegipe, RS | E6: Prefeitura | G6: Prefeitura Municipal | H6: 41160002 | I6: Saúde (Custeio - PAB) | J6: Saúde | K6: Custeio | L6: 20000 | N6: Emenda individual (processo seletivo 2021) | O6: Recurso pago | P6: Câmara para conservação de vacinas, medicamentos e termolábeis de 420L para a UBS do município.
A7: 2021 | B7: Novo Hamburgo | C7: =IFERROR(VLOOKUP(B7,'Regiões'!A:B,2,0),"") -> Metropolitana de Porto Alegre | D7: 2ª Delegacia de Polícia de Novo Hamburgo , Novo Hamburgo, RS | E7: Polícia Civil | G7: 2ª Delegacia de Polícia de Novo Hamburgo | H7: 41160001 | I7: Segurança pública | J7: Segurança Pública | K7: Investimento | L7: 26383.34 | N7: Emenda individual | O7: Empenhado | P7: Viatura caracterizada tipo SUV.
A8: 2020 | B8: Porto Alegre | C8: =IFERROR(VLOOKUP(B8,'Regiões'!A:B,2,0),"") -> Metropolitana de Porto Alegre | D8: Instituto Geral de Perícias , Porto Alegre, RS | E8: Instituto Geral de Perícias | G8: Instituto Geral de Perícias | H8: 41160008 | I8: Segurança pública | J8: Segurança Pública | K8: Investimento | L8: 26706.33 | N8: Emenda individual | O8: Pregão eletrônio concluído. | P8: Equipamentos e insumos para o IGP: Vials 20 ml com tampa, lacre e septo (50 caixas com 100 unidades).
A9: 2024 | B9: Cerro Branco | C9: =IFERROR(VLOOKUP(B9,'Regiões'!A:B,2,0),"") -> Centro Serra | D9: Avenida Doze de Maio, 520 - Centro, Cerro Branco - RS, CEP 96535-000 | E9: =G9&" de "&B9 -> Prefeitura Municipal de Cerro Branco | G9: Prefeitura Municipal | H9: 41160001 | I9: Custeio - PAB | J9: Saúde | K9: Custeio | L9: 30000 | N9: Emenda Individual
A10: 2023 | B10: Santa Vitória do Palmar | C10: =IFERROR(VLOOKUP(B10,'Regiões'!A:B,2,0),"") -> Zona Sul | D10: Rua Dom Diogo de Souza, 1761, Centro - Santa Vitória do Palmar - RS | E10: APAE | G10: APAE de Santa Vitória do Palmar | I10: Saúde (Custeio) | J10: =LEFT(I10,FIND(" (",I10) - 1) -> Saúde | K10: Custeio | L10: 30514.31 | N10: Emenda de Bancada | O10: Recurso pago | P10: Aquisição de eletrônicos para fins pedagógicos
A11: 2020 | B11: Porto Alegre | C11: =IFERROR(VLOOKUP(B11,'Regiões'!A:B,2,0),"") -> Metropolitana de Porto Alegre | D11: Divisão Estadual de Combate à Corrupção e à Lavagem de Dinheiro, Porto Alegre, RS | E11: Polícia Civil | G11: Divisão Estadual de Combate à Corrupção e à Lavagem de Dinheiro | H11: 41160010 | I11: Segurança pública | J11: Segurança Pública | K11: Investimento | L11: 31428.6 | N11: Emenda individual | O11: Recurso empenhado. Inexigibilidade de licitação aceita pelo Ministério. | P11: Aquisição de Ferramenta Forense de extração e processamento de dados provenientes da navegação na Internet para a estruturação da Divisão Estadual de Combate à Corrupção e à Lavagem de Dinheiro.
A12: 2020 | B12: Porto Alegre | C12: =IFERROR(VLOOKUP(B12,'Regiões'!A:B,2,0),"") -> Metropolitana de Porto Alegre | D12: Instituto Geral de Perícias , Porto Alegre, RS | E12: Instituto Geral de Perícias | G12: Instituto Geral de Perícias | H12: 41160008 | I12: Segurança pública | J12: Segurança Pública | K12: Investimento | L12: 31616.04 | N12: Emenda individual | O12: Pregão eletrônio concluído. | P12: Equipamentos e insumos para o IGP: 2 colunas LC/MS.
A13: 2022 | B13: Campos Borges | C13: =IFERROR(VLOOKUP(B13,'Regiões'!A:B,2,0),"") -> Alta da Serra do Botucarai | D13: Prefeitura Municipal, Campos Borges, RS | E13: Prefeitura | G13: Prefeitura Municipal | H13: 41160002 | I13: Saúde (Custeio - PAB) | J13: Saúde | K13: Custeio | L13: 35000 | N13: Emenda individual (processo seletivo 2021) | O13: Recurso pago | P13: Equipamentos de fisioterapia (barra, eletroestimulador, bicicleta ergométrica, maca hidráulica) para ampliar a rede de atendimento e a oferta de serviços fisioterápicos na UBS do município.
A14: 2023 | B14: Espumoso | C14: =IFERROR(VLOOKUP(B14,'Regiões'!A:B,2,0),"") -> Alta da Serra do Botucarai | D14: R. Vasco da Gama, 277 - Jardim, Espumoso - RS, 99400-000 | E14: APAE | G14: APAE de Espumoso | I14: Saúde (Custeio) | J14: Saúde | K14: Custeio | L14: 35000 | N14: Emenda de Bancada | O14: Recursos pago. | P14: Aquisição e instalação de uma casa de brinquedos para PCD
A15: 2023 | B15: Aratiba | C15: =IFERROR(VLOOKUP(B15,'Regiões'!A:B,2,0),"") -> Alto Uruguai | D15: Aratiba, RS | E15: APAE | G15: APAE de Aratiba | I15: Saúde (Custeio) | J15: Saúde | K15: Custeio | L15: 37480 | N15: Emenda de Bancada | O15: Recurso pago | P15: Instalação de painéis solares
A16: 2021 | B16: Santa Maria | C16: =IFERROR(VLOOKUP(B16,'Regiões'!A:B,2,0),"") -> Centro do Estado | D16: 2ª Delegacia Penitenciária Regional - Santa Maria, Santa Maria, RS | E16: Secretaria de Administração Penitenciária | G16: 2ª Delegacia Penitenciária Regional - Santa Maria | H16: 41160005 | I16: Segurança pública | J16: Segurança Pública | K16: Investimento | L16: 38354.48 | N16: Emenda individual | O16: Recurso pago | P16: Aparelhamento do Grupo de Intervenção Regional (GIR):1 Escudo Balístico, 10 Espingarda PUMP Calibre 12.
A17: 2023 | B17: Bossoroca | C17: =IFERROR(VLOOKUP(B17,'Regiões'!A:B,2,0),"") -> Missões | D17: Rua João Pedro Furtado Fabrício, 068 - Bonfim, Bossoroca - RS, 97850-000 | E17: APAE | G17: APAE de Bossoroca | I17: Saúde (Custeio) | J17: Saúde | K17: Custeio | L17: 39600 | N17: Emenda de Bancada | O17: Recurso pago | P17: Contratação de empresa para realização de aulas de canto e dança
A18: 2020 | B18: Porto Alegre | C18: =IFERROR(VLOOKUP(B18,'Regiões'!A:B,2,0),"") -> Metropolitana de Porto Alegre | D18: Rede de Saúde Div. Prov.- Hosp. Independência, Porto Alegre, RS | E18: Hospital | G18: Rede de Saúde Div. Prov.- Hosp. Independência | H18: 41160005 | I18: Saúde (Custeio - MAC) | J18: Saúde | K18: Custeio | L18: 40000 | N18: Emenda Individual (processo seletivo) | O18: Recurso pago | P18: Recurso para custeio dos serviços de saúde (Média e Alta Complexidade) | Q18: O recurso foi utilizado na aquisição de materiais e medicamentos para o cuidado e tratamento de pacientes com COVID-19, atendidos no Hospital Independência. Itens como EPIS(Itens de Proteção Individual), equipos e insumos hospitalares.
A19: 2023 | B19: Santo Augusto | C19: =IFERROR(VLOOKUP(B19,'Regiões'!A:B,2,0),"") -> Celeiro do Rio Grande | D19: R. José Gutkowski, 490 - São João, Santo Augusto - RS, 98590-000 | E19: APAE | G19: APAE de Santo Augusto | I19: Saúde (Custeio) | J19: =LEFT(I19,FIND(" (",I19) - 1) -> Saúde | K19: Custeio | L19: 40200 | N19: Emenda de Bancada | O19: Recurso pago | P19: Instalação de uma oficina de embelezamento, com duração de 10 meses
A20: 2025 | B20: Campestre da Serra | C20: =IFERROR(VLOOKUP(B20,'Regiões'!A:B,2,0),"") -> Campos de cima da Serra | D20: Secretaria Municipal da Saúde (SMS) – Fundo Municipal da Saúde, Rua Bardini, 215 - Centro, Campestre da Serra - RS, CEP 95255-000 | E20: Fundo Municipal De Saude De Campestre Da Serra - Rs Campestre Da Serra - Rs | F20: 12452816000135 | G20: Prefeitura Municipal | H20: 41160001 | I20: Custeio dos Serviços de Atenção Primária à Saúde | J20: Saúde | K20: Custeio | L20: 40925 | N20: Emenda Individual | P20: Recurso de custeio para apoio aos serviços de atenção básica da saúde do Município
A21: 2020 | B21: Porto Alegre | C21: =IFERROR(VLOOKUP(B21,'Regiões'!A:B,2,0),"") -> Metropolitana de Porto Alegre | D21: Instituto Geral de Perícias , Porto Alegre, RS | E21: Instituto Geral de Perícias | G21: Instituto Geral de Perícias | H21: 41160008 | I21: Segurança pública | J21: Segurança Pública | K21: Investimento | L21: 41388.5 | M21: (na licitação ficou em 27999,00) | N21: Emenda individual | O21: Pregão eletrônio concluído. Pagamento no valor de 27.999,00 realizado em 25/10/2021. O valor unitário das mesas ginecológicas da proposta vencedora ficou em 1.866,00, economizando recursos públicos, já que o valor empenhado era de 2,759,23 por mesa (total de 41.388,50 conforme o Plano de Trabalho) | P21: Equipamentos e insumos para o IGP: 15 mesas ginecológicas.
A22: 2020 | B22: Porto Alegre | C22: =IFERROR(VLOOKUP(B22,'Regiões'!A:B,2,0),"") -> Metropolitana de Porto Alegre | D22: Instituto Geral de Perícias , Porto Alegre, RS | E22: Instituto Geral de Perícias | G22: Instituto Geral de Perícias | H22: 41160008 | I22: Segurança pública | J22: Segurança Pública | K22: Investimento | L22: 41565.73 | N22: Emenda individual | O22: Pregão eletrônio concluído. | P22: Equipamentos e insumos para o IGP: Vials 1,5 -2 ml com tampa e septo (287 caixas com 100 unidades).
A23: 2023 | B23: Rosário do Sul | C23: =IFERROR(VLOOKUP(B23,'Regiões'!A:B,2,0),"") -> Fronteira Oeste | D23: Analvina Severo Coelho, Rosário do Sul - RS, 97590-000 | E23: APAE | G23: APAE de Rosário do Sul | I23: Saúde (Custeio) | J23: =LEFT(I23,FIND(" (",I23) - 1) -> Saúde | K23: Custeio | L23: 44950 | N23: Emenda de Bancada | O23: Recurso pago | P23: Energia solar
A24: 2023 | B24: Bom Retiro do Sul | C24: =IFERROR(VLOOKUP(B24,'Regiões'!A:B,2,0),"") -> Vale do Taquari | D24: Rua Pedro Carneiro Pereira, 204, Centro - Bom Retiro do Sul - RS | E24: APAE | G24: APAE de Bom Retiro do Sul | I24: Saúde (Custeio) | J24: Saúde | K24: Custeio | L24: 49379.28 | N24: Emenda de Bancada | O24: Recurso pago | P24: Placa fotovoltaica
A25: 2023 | B25: Campo Novo | C25: =IFERROR(VLOOKUP(B25,'Regiões'!A:B,2,0),"") -> Celeiro do Rio Grande | D25: Rua Teodomiro Luciano Souza, s/n - Cel. Bicaco, RS, 98580-000 | E25: APAE | G25: APAE de Campo Novo | I25: Saúde (Custeio) | J25: Saúde | K25: Custeio | L25: 49379.28 | N25: Emenda de Bancada | O25: Recurso pago | P25: Usina solar
A26: 2019 | B26: Guaporé | C26: =IFERROR(VLOOKUP(B26,'Regiões'!A:B,2,0),"") -> Encosta Superior do Nordeste | D26: Escola Estadual Técnica Agrícola Guaporé, Guaporé, RS | E26: Escola Agrotécnica | G26: Escola Estadual Técnica Agrícola Guaporé | H26: 71220005 | I26: Educação (escola estadual agrotécnica) | J26: Educação | K26: Investimento | L26: 50000 | N26: Emenda de Bancada (processo seletivo) | O26: Recurso pago | P26: Recurso para a aquisição de implementos agrícolas | Q26: Implementos agrícolas entregues a partir de abril de 2021.
A27: 2020 | B27: Araricá | C27: =IFERROR(VLOOKUP(B27,'Regiões'!A:B,2,0),"") -> Vale dos Sinos | D27: Prefeitura/Hospital Sapiranga, Araricá, RS | E27: Município/hospital mais próximo | G27: Prefeitura/Hospital Sapiranga | I27: Saúde (Custeio - MAC) | J27: Saúde | K27: Custeio | L27: 50000 | N27: Emenda de bancada | O27: Recurso pago | P27: Recursos para custeio do combate à COVID-19 (Média e Alta Complexidade). Como o município não possuía hospital para atender pacientes de COVID-19, e como o recurso era destinado a hospitais, a emenda foi alocada no hospital de referência do município. Prefeitos e hospitais foram comunicados.
A28: 2020 | B28: Canela | C28: =IFERROR(VLOOKUP(B28,'Regiões'!A:B,2,0),"") -> Turismo da Serra | D28: Hospital de Caridade de Canela, Canela, RS | E28: Hospital | G28: Hospital de Caridade de Canela | H28: 7122 0006 | I28: Saúde (Custeio - MAC) | J28: Saúde | K28: Custeio | L28: 50000 | N28: Emenda de Bancada | O28: Recurso pago | P28: Recursos para custeio do combate à COVID-19 (Média e Alta Complexidade)
A29: 2020 | B29: Carazinho | C29: =IFERROR(VLOOKUP(B29,'Regiões'!A:B,2,0),"") -> Alto Jacuí | D29: Hospital Comunitário de Carazinho, Carazinho, RS | E29: Hospital | G29: Hospital Comunitário de Carazinho | H29: 7122 0006 | I29: Saúde (Custeio - MAC) | J29: Saúde | K29: Custeio | L29: 50000 | N29: Emenda de Bancada | O29: Recurso pago | P29: Recursos para custeio do combate à COVID-19 (Média e Alta Complexidade)
A30: 2020 | B30: Gramado | C30: =IFERROR(VLOOKUP(B30,'Regiões'!A:B,2,0),"") -> Turismo da Serra | D30: Hospital Arcanjo São Miguel, Gramado, RS | E30: Hospital | G30: Hospital Arcanjo São Miguel | H30: 7122 0006 | I30: Saúde (Custeio - MAC) | J30: Saúde | K30: Custeio | L30: 50000 | N30: Emenda de Bancada | O30: Recurso pago | P30: Recursos para custeio do combate à COVID-19 (Média e Alta Complexidade)
A31: 2020 | B31: Igrejinha | C31: =IFERROR(VLOOKUP(B31,'Regiões'!A:B,2,0),"") -> Vale do Paranhana | D31: Hospital Bom Pastor, Igrejinha, RS | E31: Hospital | G31: Hospital Bom Pastor | H31: 7122 0006 | I31: Saúde (Custeio - MAC) | J31: Saúde | K31: Custeio | L31: 50000 | N31: Emenda de Bancada | O31: Recurso pago | P31: Recursos para custeio do combate à COVID-19 (Média e Alta Complexidade)
A32: 2020 | B32: Ivoti | C32: =IFERROR(VLOOKUP(B32,'Regiões'!A:B,2,0),"") -> Vale dos Sinos | D32: Hospital São José de Ivoti, Ivoti, RS | E32: Hospital | G32: Hospital São José de Ivoti | H32: 7122 0006 | I32: Saúde (Custeio - MAC) | J32: Saúde | K32: Custeio | L32: 50000 | N32: Emenda de Bancada | O32: Recurso pago | P32: Recursos para custeio do combate à COVID-19 (Média e Alta Complexidade)
A33: 2020 | B33: Marau | C33: =IFERROR(VLOOKUP(B33,'Regiões'!A:B,2,0),"") -> Planalto | D33: Hospital Cristo Redentor Marau, Marau, RS | E33: Hospital | G33: Hospital Cristo Redentor Marau | H33: 7122 0006 | I33: Saúde (Custeio - MAC) | J33: Saúde | K33: Custeio | L33: 50000 | N33: Emenda de Bancada | O33: Recurso pago | P33: Recursos para custeio do combate à COVID-19 (Média e Alta Complexidade)
A34: 2020 | B34: Nova Petrópolis | C34: =IFERROR(VLOOKUP(B34,'Regiões'!A:B,2,0),"") -> Turismo da Serra | D34: Hospital Nova Petrópolis, Nova Petrópolis, RS | E34: Hospital | G34: Hospital Nova Petrópolis | H34: 7122 0006 | I34: Saúde (Custeio - MAC) | J34: Saúde | K34: Custeio | L34: 50000 | N34: Emenda de Bancada | O34: Recurso pago | P34: Recursos para custeio do combate à COVID-19 (Média e Alta Complexidade)
A35: 2020 | B35: Portão | C35: =IFERROR(VLOOKUP(B35,'Regiões'!A:B,2,0),"") -> Vale do Rio Caí | D35: Hospital de Portão, Portão, RS | E35: Hospital | G35: Hospital de Portão | H35: 7122 0006 | I35: Saúde (Custeio - MAC) | J35: Saúde | K35: Custeio | L35: 50000 | N35: Emenda de Bancada | O35: Recurso pago | P35: Recursos para custeio do combate à COVID-19 (Média e Alta Complexidade)
A36: 2020 | B36: Riozinho | C36: =IFERROR(VLOOKUP(B36,'Regiões'!A:B,2,0),"") -> Vale do Paranhana | D36: Hospital Nossa Senhora do Rosário de Riozinho, Riozinho, RS | E36: Hospital | G36: Hospital Nossa Senhora do Rosário de Riozinho | H36: 7122 0006 | I36: Saúde (Custeio - MAC) | J36: Saúde | K36: Custeio | L36: 50000 | N36: Emenda de Bancada | O36: Recurso pago | P36: Recursos para custeio do combate à COVID-19 (Média e Alta Complexidade)
A37: 2020 | B37: Rolante | C37: =IFERROR(VLOOKUP(B37,'Regiões'!A:B,2,0),"") -> Vale do Paranhana | D37: Fundação Hospitalar de Rolante, Rolante, RS | E37: Hospital | G37: Fundação Hospitalar de Rolante | H37: 7122 0006 | I37: Saúde (Custeio - MAC) | J37: Saúde | K37: Custeio | L37: 50000 | N37: Emenda de Bancada | O37: Recurso pago | P37: Recursos para custeio do combate à COVID-19 (Média e Alta Complexidade)
A38: 2020 | B38: Canoas | C38: =IFERROR(VLOOKUP(B38,'Regiões'!A:B,2,0),"") -> Metropolitana de Porto Alegre | D38: Hospital Nossa Senhora das Graças, Canoas, RS | E38: Hospital | G38: Hospital Nossa Senhora das Graças | H38: 41160005 | I38: Saúde (Custeio - MAC) | J38: Saúde | K38: Custeio | L38: 50000 | N38: Emenda Individual | O38: Recurso pago | P38: Recurso para Implemento Mac | Q38: Após cumprimentá-lo, vimos através desta, em resposta ao ofício de n. 137/2020, prestar informações atualizadas sobre o recurso financeiro destinado ao HNSG, em razão de emenda parlamentar impositiva individual de nº 41160005, na área da saúde (custeio) no Orçamento Geral da União 2020, no valor de 50.000,00 (cinqüenta mil reais). Primeiramente, insta apontar que o recurso em questão restou aplicado no Fundo Municipal de Saúde do Município de Canoas/RS, porém, com o não atingimento das metas do Plano Operativo do ano corrente, tais verbas não foram repassadas ao Hospital. A instituição destinatária da emenda parlamentar esteve, durante todo o ano de 2020, em estado crítico financeiro e assistencial, de forma tão grave que desencadeou a declaração de Requisição Administrativa pela Prefeitura Municipal de Canoas, através do Decreto nº 263, de 23 de outubro de 2020, como forma de tentativa de reversão deste quadro. Por isso, apesar de não ter observado o Plano Operativo de 2020 em sua integralidade, tem chances reais e concretas de fazê-lo em 2021, em razão do advento da nova diretoria nomeada pelo Poder Público Municipal, bem como por conta da ampliação de previsão de procedimentos e serviços à população Canoense no novo Plano Operativo. Com isso, haverá, então, o repasse dos recursos financeiros do Fundo Municipal da Saúde ao nosocômio, e a efetiva aplicação destes, possibilitando a prestação de contas requerida.
A39: 2020 | B39: Capão Bonito do Sul | C39: =IFERROR(VLOOKUP(B39,'Regiões'!A:B,2,0),"") -> Nordeste Riograndense | D39: Prefeitura/Hospital São Paulo de Lagoa Vermelha, Capão Bonito do Sul, RS | E39: Município/hospital mais próximo | G39: Prefeitura/Hospital São Paulo de Lagoa Vermelha | H39: 7122 0006 | I39: Saúde (Custeio - MAC) | J39: Saúde | K39: Custeio | L39: 50000 | N39: Emenda de bancada OGU 2020 | O39: Recurso pago | P39: Recursos para custeio do combate à COVID-19 (Média e Alta Complexidade). Como o município não possuía hospital para atender pacientes de COVID-19, e como o recurso era destinado a hospitais, a emenda foi alocada no hospital de referência do município. Prefeitos e hospitais foram comunicados.
A40: 2020 | B40: Lindolfo Collor | C40: =IFERROR(VLOOKUP(B40,'Regiões'!A:B,2,0),"") -> Vale dos Sinos | D40: Prefeitura/Hospital São José Ivoti, Lindolfo Collor, RS | E40: Município/hospital mais próximo | G40: Prefeitura/Hospital São José Ivoti | H40: 7122 0006 | I40: Saúde (Custeio - MAC) | J40: Saúde | K40: Custeio | L40: 50000 | N40: Emenda de bancada OGU 2020 | O40: Recurso pago | P40: Recursos para custeio do combate à COVID-19 (Média e Alta Complexidade). Como o município não possuía hospital para atender pacientes de COVID-19, e como o recurso era destinado a hospitais, a emenda foi alocada no hospital de referência do município. Prefeitos e hospitais foram comunicados.
A41: 2020 | B41: Morro Reuter | C41: =IFERROR(VLOOKUP(B41,'Regiões'!A:B,2,0),"") -> Vale dos Sinos | D41: Prefeitura/Hospital São José de Dois Irmãos, Morro Reuter, RS | E41: Município/hospital mais próximo | G41: Prefeitura/Hospital São José de Dois Irmãos | H41: 7122 0006 | I41: Saúde (Custeio - MAC) | J41: Saúde | K41: Custeio | L41: 50000 | N41: Emenda de bancada OGU 2020 | O41: Recurso pago | P41: Recursos para custeio do combate à COVID-19 (Média e Alta Complexidade). Como o município não possuía hospital para atender pacientes de COVID-19, e como o recurso era destinado a hospitais, a emenda foi alocada no hospital de referência do município. Prefeitos e hospitais foram comunicados. | Q41: Recurso utilizado para auxiliar no financiamento da nova ala COVID-19 do Hospital São José de Dois Irmãos.
A42: 2020 | B42: São Francisco de Paula | C42: =IFERROR(VLOOKUP(B42,'Regiões'!A:B,2,0),"") -> Turismo da Serra | D42: Hospital São Francisco de Paula, São Francisco de Paula, RS | E42: Hospital | G42: Hospital São Francisco de Paula | H42: 7122 0006 | I42: Saúde (Custeio - MAC) | J42: Saúde | K42: Custeio | L42: 50000 | N42: Emenda de Bancada | O42: Recurso pago | P42: Recursos para custeio do combate à COVID-19 (Média e Alta Complexidade)
A43: 2020 | B43: Nova Hartz | C43: =IFERROR(VLOOKUP(B43,'Regiões'!A:B,2,0),"") -> Vale dos Sinos | D43: Prefeitura/Hospital Sapiranga, Nova Hartz, RS | E43: Município/hospital mais próximo | G43: Prefeitura/Hospital Sapiranga | H43: 7122 0006 | I43: Saúde (Custeio - MAC) | J43: Saúde | K43: Custeio | L43: 50000 | N43: Emenda de bancada OGU 2020 | O43: Recurso pago | P43: Recursos para custeio do combate à COVID-19 (Média e Alta Complexidade). Como o município não possuía hospital para atender pacientes de COVID-19, e como o recurso era destinado a hospitais, a emenda foi alocada no hospital de referência do município. Prefeitos e hospitais foram comunicados.
A44: 2020 | B44: São Luiz Gonzaga | C44: =IFERROR(VLOOKUP(B44,'Regiões'!A:B,2,0),"") -> Missões | D44: Hospital São Luiz Gonzaga, São Luiz Gonzaga, RS | E44: Hospital | G44: Hospital São Luiz Gonzaga | H44: 7122 0006 | I44: Saúde (Custeio - MAC) | J44: Saúde | K44: Custeio | L44: 50000 | N44: Emenda de Bancada | O44: Recurso pago | P44: Recursos para custeio do combate à COVID-19 (Média e Alta Complexidade)
A45: 2020 | B45: Picada Café | C45: =IFERROR(VLOOKUP(B45,'Regiões'!A:B,2,0),"") -> Turismo da Serra | D45: Prefeitura/Hospital Nova Petrópolis, Picada Café, RS | E45: Município/hospital mais próximo | G45: Prefeitura/Hospital Nova Petrópolis | H45: 7122 0006 | I45: Saúde (Custeio - MAC) | J45: Saúde | K45: Custeio | L45: 50000 | N45: Emenda de bancada OGU 2020 | O45: Recurso pago | P45: Recursos para custeio do combate à COVID-19 (Média e Alta Complexidade). Como o município não possuía hospital para atender pacientes de COVID-19, e como o recurso era destinado a hospitais, a emenda foi alocada no hospital de referência do município. Prefeitos e hospitais foram comunicados.
A46: 2020 | B46: Presidente Lucena | C46: =IFERROR(VLOOKUP(B46,'Regiões'!A:B,2,0),"") -> Vale dos Sinos | D46: Prefeitura/Hospital São José Ivoti, Presidente Lucena, RS | E46: Município/hospital mais próximo | G46: Prefeitura/Hospital São José Ivoti | H46: 7122 0006 | I46: Saúde (Custeio - MAC) | J46: Saúde | K46: Custeio | L46: 50000 | N46: Emenda de bancada OGU 2020 | O46: Recurso pago | P46: Recursos para custeio do combate à COVID-19 (Média e Alta Complexidade). Como o município não possuía hospital para atender pacientes de COVID-19, e como o recurso era destinado a hospitais, a emenda foi alocada no hospital de referência do município. Prefeitos e hospitais foram comunicados.
A47: 2020 | B47: Santa Maria do Herval | C47: =IFERROR(VLOOKUP(B47,'Regiões'!A:B,2,0),"") -> Turismo da Serra | D47: Prefeitura/Hospital São José de Dois Irmãos, Santa Maria do Herval, RS | E47: Município/hospital mais próximo | G47: Prefeitura/Hospital São José de Dois Irmãos | H47: 7122 0006 | I47: Saúde (Custeio - MAC) | J47: Saúde | K47: Custeio | L47: 50000 | N47: Emenda de bancada OGU 2020 | O47: Recurso pago | P47: Recursos para custeio do combate à COVID-19 (Média e Alta Complexidade). Como o município não possuía hospital para atender pacientes de COVID-19, e como o recurso era destinado a hospitais, a emenda foi alocada no hospital de referência do município. Prefeitos e hospitais foram comunicados. | Q47: Recurso utilizado para auxiliar no financiamento da nova ala COVID-19 do Hospital São José de Dois Irmãos.
A48: 2020 | B48: Três Coroas | C48: =IFERROR(VLOOKUP(B48,'Regiões'!A:B,2,0),"") -> Vale do Paranhana | D48: Hospital Dr Oswaldo Diesel, Três Coroas, RS | E48: Hospital | G48: Hospital Dr Oswaldo Diesel | H48: 7122 0006 | I48: Saúde (Custeio - MAC) | J48: Saúde | K48: Custeio | L48: 50000 | N48: Emenda de Bancada | O48: Recurso pago | P48: Recursos para custeio do combate à COVID-19 (Média e Alta Complexidade)
A49: 2021 | B49: Tapera | C49: =IFERROR(VLOOKUP(B49,'Regiões'!A:B,2,0),"") -> Alto Jacuí | D49: Prefeitura Municipal, Tapera, RS | E49: Prefeitura | G49: Prefeitura Municipal | H49: 41160002 | I49: Saúde (Custeio - PAB) | J49: Saúde | K49: Custeio | L49: 50000 | N49: Emenda individual (processo seletivo 2021) | O49: Prefeitura submeteu proposta ao Ministério da Saúde (Em 02/05/2024 consultei o SIOP, para verificar a situação da emenda e não localizei o beneficiário FMS-Tapera. A emenda 41160002, referenciada na planilha, não é de Custeio-PAB; é de Investimento-MAC. Em 2021 não foram indicados recursos de emendas individuais para custeio-PAB. Também não localizei o beneficiário na emenda de Custeio-MAC. | P49: Monitor multiparâmetros e cardiversor para equipar a ambulância do município e reduzir custos com a contratação de veículos com esses equipamentos e que a Prefeitura não possui.
A50: 2022 | B50: Tapera | C50: =IFERROR(VLOOKUP(B50,'Regiões'!A:B,2,0),"") -> Alto Jacuí | D50: Prefeitura Municipal, Tapera, RS | E50: Município | G50: Prefeitura Municipal | H50: 41160002 | I50: Saúde (Custeio - PAB) | J50: Saúde | K50: Custeio | L50: 50000 | N50: Emenda Individual | O50: Recurso pago
A51: 2023 | B51: Boa Vista do Buricá | C51: =IFERROR(VLOOKUP(B51,'Regiões'!A:B,2,0),"") -> Fronteira Noroeste | D51: R. Santa Clara, 49, Boa Vista do Buricá - RS, 98918-000 | E51: APAE | G51: APAE de Boa Vista do Buricá | I51: Saúde (Custeio) | J51: Saúde | K51: Custeio | L51: 50000 | N51: Emenda de Bancada | O51: Recurso pago | P51: Aquisição de equipamentos e adequação do espaço
A52: 2023 | B52: Feliz | C52: =IFERROR(VLOOKUP(B52,'Regiões'!A:B,2,0),"") -> Vale do Rio Caí | D52: Av. Dóris José Schlatter, 30, Feliz - RS, 95770-000 | E52: APAE | G52: APAE de Feliz | I52: Saúde (Custeio) | J52: Saúde | K52: Custeio | L52: 50000 | N52: Emenda de Bancada | O52: Recurso pago | P52: Aquisição de 2 conteiners que se tornarão espaços para o bazar da instituição e área de preparação para o mercado de trabalho
A53: 2023 | B53: São Martinho | C53: =IFERROR(VLOOKUP(B53,'Regiões'!A:B,2,0),"") -> Celeiro do Rio Grande | D53: Rua Jacob Hermindo Hartmann, 62. Centro - São Martinho - RS | E53: APAE | G53: APAE de São Martinho | I53: Saúde (Custeio) | J53: =LEFT(I53,FIND(" (",I53) - 1) -> Saúde | K53: Custeio | L53: 50000 | N53: Emenda de Bancada | O53: Recurso pago | P53: Placas solares
A54: 2024 | B54: Forquetinha | C54: =IFERROR(VLOOKUP(B54,'Regiões'!A:B,2,0),"") -> Vale do Taquari | D54: Rua Johann Kremer, 1.316 (1316), Centro, Forquetinha - RS, CEP 95937-000 | E54: =G54&" de "&B54 -> Prefeitura Municipal de Forquetinha | G54: Prefeitura Municipal | H54: 41160002 | I54: Custeio - MAC | J54: Saúde | K54: Custeio | L54: 50000 | N54: Emenda Individual
A55: 2024 | B55: Imigrante | C55: =IFERROR(VLOOKUP(B55,'Regiões'!A:B,2,0),"") -> Vale do Taquari | D55: Rua Castelo Branco, 15 - Centro, Imigrante - RS, CEP 95885-000 | E55: =G55&" de "&B55 -> Prefeitura Municipal de Imigrante | G55: Prefeitura Municipal | H55: 41160002 | I55: Custeio - MAC | J55: Saúde | K55: Custeio | L55: 50000 | N55: Emenda Individual
A56: 2019 | B56: Santo Antônio das Missões | C56: =IFERROR(VLOOKUP(B56,'Regiões'!A:B,2,0),"") -> Missões | D56: E.T.E. Achilino de Santis, Santo Antônio das Missões, RS | E56: Escola Agrotécnica | G56: E.T.E. Achilino de Santis | H56: 71220005 | I56: Educação (escola estadual agrotécnica) | J56: Educação | K56: Investimento | L56: 54000 | N56: Emenda de Bancada | O56: Recurso pago | P56: Recurso para a aquisição de implementos agrícolas
A57: 2019 | B57: Lagoa Vermelha | C57: =IFERROR(VLOOKUP(B57,'Regiões'!A:B,2,0),"") -> Nordeste Riograndense | D57: E.E.T.A Desidério Finamor, Lagoa Vermelha, RS | E57: Escola Agrotécnica | G57: E.E.T.A Desidério Finamor | H57: 71220005 | I57: Educação (escola estadual agrotécnica) | J57: Educação | K57: Investimento | L57: 54000 | N57: Emenda de Bancada (processo seletivo) | O57: Recurso pago | P57: Recurso para a aquisição de implementos agrícolas | Q57: Implementos agrícolas entregues a partir de abril de 2021.
A58: 2019 | B58: São Lourenço do Sul | C58: =IFERROR(VLOOKUP(B58,'Regiões'!A:B,2,0),"") -> Zona Sul | D58: Escola Técnica Estadual Santa Isabel, São Lourenço do Sul, RS | E58: Escola Agrotécnica | G58: Escola Técnica Estadual Santa Isabel | H58: 71220005 | I58: Educação (escola estadual agrotécnica) | J58: Educação | K58: Investimento | L58: 55000 | N58: Emenda de Bancada (processo seletivo) | O58: Recurso pago | P58: Recurso para a aquisição de implementos agrícolas
A59: 2023 | B59: Formigueiro | C59: =IFERROR(VLOOKUP(B59,'Regiões'!A:B,2,0),"") -> Centro do Estado | D59: R. São João, 988, Formigueiro - RS, 97210-000 | E59: Prefeitura | G59: Prefeitura de Formigueiro | I59: Segurança Pública (Investimento) | J59: =LEFT(I59,FIND(" (",I59) - 1) -> Segurança Pública | K59: Investimento | L59: 56000 | N59: Emenda Individual | O59: Recurso Pago | P59: Aquisição de armas e equipamentos (Transferência Especial) Transferegov: OB enviada pagto em 30/08/2023.
A60: 2023 | B60: Formigueiro | C60: =IFERROR(VLOOKUP(B60,'Regiões'!A:B,2,0),"") -> Centro do Estado | D60: R. São João, 988, Formigueiro - RS, 97210-000 | E60: APAE | G60: APAE de Formigueiro | I60: Saúde (Custeio) | J60: Saúde | K60: Custeio | L60: 58000 | N60: Emenda de Bancada | O60: Recurso Pago
A61: 2019 | B61: Carazinho | C61: =IFERROR(VLOOKUP(B61,'Regiões'!A:B,2,0),"") -> Alto Jacuí | D61: E.E.E.P. de Carazinho, Carazinho, RS | E61: Escola Agrotécnica | G61: E.E.E.P. de Carazinho | H61: 71220005 | I61: Educação (escola estadual agrotécnica) | J61: Educação | K61: Investimento | L61: 59000 | N61: Emenda de Bancada (processo seletivo) | O61: Recurso pago | P61: Recurso para a aquisição de implementos agrícolas | Q61: Implementos agrícolas entregues a partir de abril de 2021.
A62: 2020 | B62: Estância Velha | C62: =IFERROR(VLOOKUP(B62,'Regiões'!A:B,2,0),"") -> Vale dos Sinos | D62: Hospital Municipal Getúlio Vargas, Estância Velha, RS | E62: Hospital | G62: Hospital Municipal Getúlio Vargas | H62: 7122 0006 | I62: Saúde (Custeio - MAC) | J62: Saúde | K62: Custeio | L62: 60000 | N62: Emenda de Bancada | O62: Recurso pago | P62: Recursos para custeio do combate à COVID-19 (Média e Alta Complexidade)
A63: 2023 | B63: Tupandi | C63: =IFERROR(VLOOKUP(B63,'Regiões'!A:B,2,0),"") -> Vale do Rio Caí | D63: Av. Salvador, 1919, Tupandi - RS, 95775-000 | E63: Prefeitura | G63: Prefeitura de Tupandi | I63: Segurança Pública (Investimento) | J63: =LEFT(I63,FIND(" (",I63) - 1) -> Segurança Pública | K63: Investimento | L63: 60000 | N63: Emenda Individual | O63: Empenhado | P63: Videomonitoramento
A64: 2024 | B64: Bom Princípio | C64: =IFERROR(VLOOKUP(B64,'Regiões'!A:B,2,0),"") -> Vale do Rio Caí | D64: Avenida Guilherme Winter, 65 - Centro, Bom Princípio - RS, 95765-000 | E64: =G64&" de "&B64 -> Prefeitura Municipal de Bom Princípio | G64: Prefeitura Municipal | H64: 41160002 | I64: Custeio - MAC | J64: Saúde | K64: Custeio | L64: 60000 | N64: Emenda Individual
A65: 2019 | B65: Bom Progresso | C65: =IFERROR(VLOOKUP(B65,'Regiões'!A:B,2,0),"") -> Celeiro do Rio Grande | D65: E.T.E. Celeiro, Bom Progresso, RS | E65: Escola Agrotécnica | G65: E.T.E. Celeiro | H65: 71220005 | I65: Educação (escola estadual agrotécnica) | J65: Educação | K65: Investimento | L65: 63000 | N65: Emenda de Bancada (processo seletivo) | O65: Recurso pago | P65: Recurso para a aquisição de implementos agrícolas | Q65: Implementos agrícolas entregues a partir de abril de 2021.
A66: 2019 | B66: Erechim | C66: =IFERROR(VLOOKUP(B66,'Regiões'!A:B,2,0),"") -> Alto Uruguai | D66: C.A.E. Ângelo Emílio Grando, Erechim, RS | E66: Escola Agrotécnica | G66: C.A.E. Ângelo Emílio Grando | H66: 71220005 | I66: Educação (escola estadual agrotécnica) | J66: Educação | K66: Investimento | L66: 63000 | N66: Emenda de Bancada (processo seletivo) | O66: Recurso pago | P66: Recurso para a aquisição de implementos agrícolas | Q66: Implementos agrícolas entregues a partir de abril de 2021.
A67: 2019 | B67: Dom Pedrito | C67: =IFERROR(VLOOKUP(B67,'Regiões'!A:B,2,0),"") -> Sudoeste do Estado | D67: E.E.E.P. Dom Pedrito, Dom Pedrito, RS | E67: Escola Agrotécnica | G67: E.E.E.P. Dom Pedrito | H67: 71220005 | I67: Educação (escola estadual agrotécnica) | J67: Educação | K67: Investimento | L67: 64000 | N67: Emenda de Bancada (processo seletivo) | O67: Recurso pago | P67: Recurso para a aquisição de implementos agrícolas | Q67: Implementos agrícolas entregues a partir de abril de 2021.
A68: 2019 | B68: Palmeira das Missões | C68: =IFERROR(VLOOKUP(B68,'Regiões'!A:B,2,0),"") -> Zona da Produção | D68: E.E.T. Celeste Gobbato, Palmeira das Missões, RS | E68: Escola Agrotécnica | G68: E.E.T. Celeste Gobbato | H68: 71220005 | I68: Educação (escola estadual agrotécnica) | J68: Educação | K68: Investimento | L68: 66000 | N68: Emenda de Bancada (processo seletivo) | O68: Recurso pago | P68: Recurso para a aquisição de implementos agrícolas | Q68: Implementos agrícolas entregues a partir de abril de 2021.
A69: 2023 | B69: São Sepé | C69: =IFERROR(VLOOKUP(B69,'Regiões'!A:B,2,0),"") -> Centro do Estado | D69: RUA PERCIVAL BRENNER, 1992. Centro - São Sepé - RS | E69: APAE | G69: APAE de São Sepé | I69: Saúde (Custeio) | J69: =LEFT(I69,FIND(" (",I69) - 1) -> Saúde | K69: Custeio | L69: 66576.11 | N69: Emenda de Bancada | O69: Recurso Pago | P69: Painéis solares
A70: 2020 | B70: Boqueirão do Leão | C70: =IFERROR(VLOOKUP(B70,'Regiões'!A:B,2,0),"") -> Vale do Taquari | D70: Prefeitura Municipal, Boqueirão do Leão, RS | E70: Município | G70: Prefeitura Municipal | H70: 41160001 | I70: Saúde (Custeio - PAB) | J70: Saúde | K70: Custeio | L70: 67500 | N70: Emenda Individual (processo seletivo) | O70: Recurso pago | P70: Recurso para custeio dos serviços de saúde (Piso de Atenção Básica)
A71: 2020 | B71: Canela | C71: =IFERROR(VLOOKUP(B71,'Regiões'!A:B,2,0),"") -> Turismo da Serra | D71: Prefeitura Municipal, Canela, RS | E71: Município | G71: Prefeitura Municipal | H71: 41160001 | I71: Saúde (Custeio - PAB) | J71: Saúde | K71: Custeio | L71: 67500 | N71: Emenda Individual (processo seletivo) | O71: Recurso pago | P71: Recurso para custeio dos serviços de saúde (Piso de Atenção Básica)
A72: 2020 | B72: Serafina Corrêa | C72: =IFERROR(VLOOKUP(B72,'Regiões'!A:B,2,0),"") -> Encosta Superior do Nordeste | D72: Prefeitura Municipal, Serafina Corrêa, RS | E72: Município | G72: Prefeitura Municipal | H72: 41160001 | I72: Saúde (Custeio - PAB) | J72: Saúde | K72: Custeio | L72: 67500 | N72: Emenda Individual (processo seletivo) | O72: Recurso pago | P72: Recurso para custeio dos serviços de saúde (Piso de Atenção Básica) | Q72: Sim, recurso foi investido na manutenção da frota municipal, manutenção das unidades básicas de saúde e aquisição de insumos para o combate a pandemia do covid-19.
A73: 2020 | B73: Nova Hartz | C73: =IFERROR(VLOOKUP(B73,'Regiões'!A:B,2,0),"") -> Vale dos Sinos | D73: Prefeitura Municipal, Nova Hartz, RS | E73: Município | G73: Prefeitura Municipal | H73: 41160001 | I73: Saúde (Custeio - PAB) | J73: Saúde | K73: Custeio | L73: 67727 | N73: Emenda Individual | O73: Recurso pago | P73: Recurso para custeio dos serviços de saúde (Piso de Atenção Básica) | Q73: Utilizamos para pagamento da empresa prestadora de serviços médicos - proativa saude coop. Prof area saude ltda cnpj 07.656.276/0001-71
A74: 2024 | B74: Putinga | C74: =IFERROR(VLOOKUP(B74,'Regiões'!A:B,2,0),"") -> Vale do Taquari | D74: Rua Duque de Caxias, 333 - Centro, Putinga - RS, CEP 95975-000 | E74: =G74&" de "&B74 -> Prefeitura Municipal de Putinga | G74: Prefeitura Municipal | H74: 41160001 | I74: Custeio - PAB | J74: Saúde | K74: Custeio | L74: 68364 | N74: Emenda Individual
A75: 2020 | B75: Imigrante | C75: =IFERROR(VLOOKUP(B75,'Regiões'!A:B,2,0),"") -> Vale do Taquari | D75: Prefeitura Municipal, Imigrante, RS | E75: Município | G75: Prefeitura Municipal | H75: 41160009 | I75: Saúde (Custeio - MAC) | J75: Saúde | K75: Custeio | L75: 68418 | N75: Emenda Individual (processo seletivo) | O75: Recurso pago | P75: Recurso para custeio dos serviços de saúde (Piso de Atenção Básica) | Q75: Pagamento de outros serviços de terceiros, pessoa jurídica, Convênio com Hospital Estrela para atendimento de urgência/emergência, exames de diagnóstico, cirurgias, partos, avaliações com especialistas, internações em leito de UTI.
A76: 2024 | B76: Porto Alegre | C76: =IFERROR(VLOOKUP(B76,'Regiões'!A:B,2,0),"") -> Metropolitana de Porto Alegre | D76: Prefeitura Municipal de Porto Alegre (Paço Municipal), Praça Montevidéu, 10 - Porto Alegre - RS, CEP 90010-170, Brasil | E76: =G76&" de "&B76 -> Prefeitura Municipal de Porto Alegre | G76: Prefeitura Municipal | H76: 41160004 | I76: Investimento MAC | J76: Saúde | K76: Investimento | L76: 69646 | N76: Emenda Individual
A77: 2023 | B77: Tapejara | C77: =IFERROR(VLOOKUP(B77,'Regiões'!A:B,2,0),"") -> Nordeste Riograndense | D77: R. Luís Costa, 293 - São Cristóvão, Tapejara - RS, 99950-000 | E77: APAE | G77: APAE de Tapejara | I77: Saúde (Custeio) | J77: =LEFT(I77,FIND(" (",I77) - 1) -> Saúde | K77: Custeio | L77: 70000 | N77: Emenda de Bancada | O77: Recurso pago | P77: Painéis fotovoltaicos
A78: 2025 | B78: Morro Reuter | C78: =IFERROR(VLOOKUP(B78,'Regiões'!A:B,2,0),"") -> Vale dos Sinos | D78: Rua Anita Garibaldi, 219 - Centro, Morro Reuter - RS, CEP 93990-000 | E78: Morro Reuter | F78: 11787446000124 | H78: 41160001 | I78: Custeio dos Serviços de Atenção Primária à Saúde | J78: Saúde | K78: Custeio | L78: 70000 | N78: Emenda individual | P78: Recurso de custeio para apoio aos serviços de atenção básica da saúde do Município
A79: 2023 | B79: Santo Antônio da Patrulha | C79: =IFERROR(VLOOKUP(B79,'Regiões'!A:B,2,0),"") -> Metropolitana de Porto Alegre | D79: R. Marcolino de Carli - Centro, Santo Antônio da Patrulha - RS, 95500-000 | E79: APAE | G79: APAE de Santo Antônio da Patrulha | I79: Saúde (Custeio) | J79: =LEFT(I79,FIND(" (",I79) - 1) -> Saúde | K79: Custeio | L79: 71500 | N79: Emenda de Bancada | O79: Recurso pago
A80: 2019 | B80: Guarani das Missões | C80: =IFERROR(VLOOKUP(B80,'Regiões'!A:B,2,0),"") -> Missões | D80: E.E.T. Guaramano, Guarani das Missões, RS | E80: Escola Agrotécnica | G80: E.E.T. Guaramano | H80: 71220005 | I80: Educação (escola estadual agrotécnica) | J80: Educação | K80: Investimento | L80: 78705.88 | N80: Emenda de Bancada (processo seletivo) | O80: Recurso pago | P80: Recurso para a aquisição de implementos agrícolas | Q80: Implementos agrícolas entregues a partir de abril de 2021.
A81: 2020 | B81: Passo Fundo | C81: =IFERROR(VLOOKUP(B81,'Regiões'!A:B,2,0),"") -> Planalto | D81: Hospital São Vicente de Paulo, Passo Fundo, RS | E81: Hospital | G81: Hospital São Vicente de Paulo | H81: 7122 0006 | I81: Saúde (Custeio - MAC) | J81: Saúde | K81: Custeio | L81: 80000 | N81: Emenda de Bancada | O81: Recurso pago | P81: Recursos para custeio do combate à COVID-19 (Média e Alta Complexidade)
A82: 2021 | B82: Picada Café | C82: =IFERROR(VLOOKUP(B82,'Regiões'!A:B,2,0),"") -> Turismo da Serra | D82: Prefeitura Municipal, Picada Café, RS | E82: Prefeitura | G82: Prefeitura Municipal | H82: 41160003 | I82: Saúde (Custeio - MAC) | J82: Saúde | K82: Custeio | L82: 80000 | N82: Emenda individual (processo seletivo) | O82: Recurso pago | P82: Autoclave (75 a 150 litros), ar-condicionado, analisador de ions/eletrolitos, deionizador, micropipeta monocanal e termohigrometro para aumentar a resolutividade dos exames realizados na UBS do município. Emenda de investimento foi transformada em custeio para recebimento por parte do município.
A83: 2020 | B83: Camaquã | C83: =IFERROR(VLOOKUP(B83,'Regiões'!A:B,2,0),"") -> Costa Doce | D83: Brigada Militar de Camaquã, Camaquã, RS | E83: Brigada Militar | G83: Brigada Militar de Camaquã | I83: Segurança pública | J83: Segurança Pública | K83: Investimento | L83: 81280 | N83: Emenda de Bancada | O83: Em licitação | P83: Coletes balísticos e pistolas para o contingente da Brigada Militar | Q83: Material em processo licitatório pela Secretaria de Segurança Pública do Rio Grande do Sul
A84: 2024 | B84: Alvorada | C84: =IFERROR(VLOOKUP(B84,'Regiões'!A:B,2,0),"") -> Metropolitana de Porto Alegre | D84: Avenida Presidente Getúlio Vargas, 2266, Bairro Sumaré (ou Bela Vista), Alvorada - RS, CEP 94810-001. | E84: =G84&" de "&B84 -> Prefeitura Municipal de Alvorada | G84: Prefeitura Municipal | H84: 41160004 | I84: Investimento MAC | J84: Saúde | K84: Investimento | L84: 83953 | N84: Emenda Individual
A85: 2020 | B85: Não-Me-Toque | C85: =IFERROR(VLOOKUP(B85,'Regiões'!A:B,2,0),"") -> Alto Jacuí | D85: Hospital Beneficência Alto Jacuí, Não-Me-Toque, RS | E85: Hospital | G85: Hospital Beneficência Alto Jacuí | H85: 41160005 | I85: Saúde (Custeio - MAC) | J85: Saúde | K85: Custeio | L85: 86000 | N85: Emenda Individual (suplente - processo seletivo) | O85: Recurso pago | P85: Recurso para custeio dos serviços de saúde (Média e Alta Complexidade) | Q85: Medicamentos, Material Médico Hospitalar e Alimentação
A86: 2020 | B86: Porto Alegre | C86: =IFERROR(VLOOKUP(B86,'Regiões'!A:B,2,0),"") -> Metropolitana de Porto Alegre | D86: Instituto Geral de Perícias , Porto Alegre, RS | E86: Instituto Geral de Perícias | G86: Instituto Geral de Perícias | H86: 41160010 | I86: Segurança pública | J86: Segurança Pública | K86: Investimento | L86: 88086 | N86: Emenda individual | O86: Pregão eletrônio concluído. | P86: Atualização de equipamento de extração de dados de dispositivos móveis para o IGP.
A87: 2024 | B87: São José do Herval | C87: =IFERROR(VLOOKUP(B87,'Regiões'!A:B,2,0),"") -> Alta da Serra do Botucarai | D87: Avenida Getúlio Vargas, 731 - Centro, São José do Herval - RS, CEP 99380-000 | E87: =G87&" de "&B87 -> Prefeitura Municipal de São José do Herval | G87: Prefeitura Municipal | H87: 41160001 | I87: Custeio - PAB | J87: Saúde | K87: Custeio | L87: 90000 | N87: Emenda Individual
A88: 2024 | B88: São Vendelino | C88: =IFERROR(VLOOKUP(B88,'Regiões'!A:B,2,0),"") -> Vale do Rio Caí | D88: Rua Padre Emílio Schneider, 70, Centro, São Vendelino - RS, CEP 95795-000 | E88: =G88&" de "&B88 -> Prefeitura Municipal de São Vendelino | G88: Prefeitura Municipal | H88: 41160001 | I88: Custeio - PAB | J88: Saúde | K88: Custeio | L88: 90000 | N88: Emenda Individual
A89: 2023 | B89: Três de Maio | C89: =IFERROR(VLOOKUP(B89,'Regiões'!A:B,2,0),"") -> Fronteira Noroeste | D89: R. Minas Gerais - Três de Maio, RS, 98910-000 | E89: Prefeitura | G89: Prefeitura de Três de Maio | I89: Segurança Pública (Investimento) | J89: =LEFT(I89,FIND(" (",I89) - 1) -> Segurança Pública | K89: Investimento | L89: 95000 | N89: Emenda Individual | O89: Empenhado | P89: Videomonitoramento
A90: 2026 | B90: Caseiros | C90: =IFERROR(VLOOKUP(B90,'Regiões'!A:B,2,0),"") -> Nordeste Riograndense | E90: Fundo Municipal de Saúde de Caseiros - RS | F90: 12390666000182 | H90: 41160005 | I90: Saúde | J90: Saúde | K90: PAP Custeio | L90: 98000 | N90: Emenda individual
A91: 2020 | B91: Campo Bom | C91: =IFERROR(VLOOKUP(B91,'Regiões'!A:B,2,0),"") -> Vale dos Sinos | D91: Hospital de Campo Bom Dr. Lauro Reus, Campo Bom, RS | E91: Hospital | G91: Hospital de Campo Bom Dr. Lauro Reus | H91: 7122 0006 | I91: Saúde (Custeio - MAC) | J91: Saúde | K91: Custeio | L91: 100000 | N91: Emenda de Bancada | O91: Recurso pago | P91: Recursos para custeio do combate à COVID-19 (Média e Alta Complexidade)
A92: 2020 | B92: Parobé | C92: =IFERROR(VLOOKUP(B92,'Regiões'!A:B,2,0),"") -> Vale do Paranhana | D92: Hospital São Francisco de Assis, Parobé, RS | E92: Hospital | G92: Hospital São Francisco de Assis | H92: 7122 0006 | I92: Saúde (Custeio - MAC) | J92: Saúde | K92: Custeio | L92: 100000 | N92: Emenda de Bancada | O92: Recurso pago | P92: Recursos para custeio do combate à COVID-19 (Média e Alta Complexidade)
A93: 2020 | B93: Arroio do Meio | C93: =IFERROR(VLOOKUP(B93,'Regiões'!A:B,2,0),"") -> Vale do Taquari | D93: Prefeitura Municipal, Arroio do Meio, RS | E93: Município | G93: Prefeitura Municipal | H93: 41160001 | I93: Saúde (Custeio - PAB) | J93: Saúde | K93: Custeio | L93: 100000 | N93: Emenda Individual (processo seletivo) | O93: Recurso pago | P93: Recurso para custeio dos serviços de saúde (Piso de Atenção Básica)
A94: 2020 | B94: Bagé | C94: =IFERROR(VLOOKUP(B94,'Regiões'!A:B,2,0),"") -> Sudoeste do Estado | D94: Santa Casa de Caridade de Bagé, Bagé, RS | E94: Hospital | G94: Santa Casa de Caridade de Bagé | H94: 41160005 | I94: Saúde (Custeio - MAC) | J94: Saúde | K94: Custeio | L94: 100000 | N94: Emenda Individual (processo seletivo) | O94: Recurso pago | P94: Recurso para custeio dos serviços de saúde (Média e Alta Complexidade)
A95: 2020 | B95: Barão | C95: =IFERROR(VLOOKUP(B95,'Regiões'!A:B,2,0),"") -> Vale do Rio Caí | D95: Prefeitura Municipal, Barão, RS | E95: Município | G95: Prefeitura Municipal | H95: 41160001 | I95: Saúde (Custeio - PAB) | J95: Saúde | K95: Custeio | L95: 100000 | N95: Emenda Individual (processo seletivo) | O95: Recurso pago | P95: Recurso para custeio dos serviços de saúde (Piso de Atenção Básica) | Q95: .
A96: 2020 | B96: Bento Gonçalves | C96: =IFERROR(VLOOKUP(B96,'Regiões'!A:B,2,0),"") -> Encosta Superior do Nordeste | D96: Hospital Tacchini, Bento Gonçalves, RS | E96: Hospital | G96: Hospital Tacchini | H96: 41160005 | I96: Saúde (Custeio - MAC) | J96: Saúde | K96: Custeio | L96: 100000 | N96: Emenda Individual (processo seletivo) | O96: Recurso pago | P96: Recurso para custeio dos serviços de saúde (Média e Alta Complexidade) | Q96: Em atenção ao Of. n. 135/2020, de 26/11/2020, e com base no Projeto apresentado através do e-mail datado de 27/07/2020 (leitura realizada em 28/07/2020), com o valor de 100.000,00 recebido através de Emenda Parlamentar - Portaria GM/MS nº 679/2020, de autoria do Deputado Federal Marcel Van Hattem, foi possível reduzir o indicador percentual de tempo de espera cirúrgica acima de 60 dias, de 54,00% para 30,33% , ao mesmo tempo em que, foi possível ampliar o atendimento e beneficiar na realização de tratamento cirúrgico em oncologia de 26 novos pacientes oncológicos, que ingressaram na UNACON do Hospital Tacchini (Bento Gonçalves - RS), período de agosto, setembro e outubro de 2020, conforme as seguintes AIH's: Agosto/2020 - 4320104280140; 4320105042715; 4320105069049; 4320105808865; 4320103526959; 4320103526937; 4320103527400 / Setembro/2020 - 4320104281537; 4320104281548; 4320104281890; 4320104283891; 4320104281603; 4320104277907; 4320104281559 / Outubro/2020 - 4320104284353; 4320106584453; 4320106586796; 4320107313566; 4320107346115; 4320105048699; 4320105048534; 4320105809900; 4320105048370; 4320105822087; 4320104286069; 4320105050635.
A97: 2020 | B97: Bom Princípio | C97: =IFERROR(VLOOKUP(B97,'Regiões'!A:B,2,0),"") -> Vale do Rio Caí | D97: Prefeitura Municipal, Bom Princípio, RS | E97: Município | G97: Prefeitura Municipal | H97: 41160001 | I97: Saúde (Custeio - PAB) | J97: Saúde | K97: Custeio | L97: 100000 | N97: Emenda Individual (processo seletivo) | O97: Recurso pago | P97: Recurso para custeio dos serviços de saúde (Piso de Atenção Básica)
A98: 2020 | B98: Brochier | C98: =IFERROR(VLOOKUP(B98,'Regiões'!A:B,2,0),"") -> Vale do Rio Caí | D98: Prefeitura Municipal, Brochier, RS | E98: Município | G98: Prefeitura Municipal | H98: 41160001 | I98: Saúde (Custeio - PAB) | J98: Saúde | K98: Custeio | L98: 100000 | N98: Emenda Individual (processo seletivo) | O98: Recurso pago | P98: Recurso para custeio dos serviços de saúde (Piso de Atenção Básica) | Q98: 1) Pagamento de parte das despesas com Serviços Médicos e profissionais de saúde, através do Consórcio dos Municípios do Vale do Caí - CIS/CAI conforme empenhos a seguir relacionados: - 3818/2020 - no valor de 20.993,50; - 3494/2020 - no valor de 20.553,00; - 3218/2020 - no valor de 9.344,00; - 3216/2020 - no valor de 6.230,00; - 2928/2020 - no valor de 13.333,00; - 2926/2020 - no valor de 9.065,00; - 2587/2020 - no valor de 6.722,00; - 2580/2020 - no valor de 6.610,00; - 2579/2020 - no valor de 41.552,00; - 2237/2020 - no valor de 42.754,00; Trata esta prestação de contas de informação complementar à prestação de contas enviada na data de ontem, no intuito de esclarecer que os recursos aplicados serviram para ampliar o horário de atendimento no posto de saúde da sede do Município, que ocorre então das 7h da manhã até às 21h ininterruptamente. Com pode ser observado os recursos servem para custear parte da contratação de pessoal necessário para possibilitar o atendimento estendido no posto de saúde.
A99: 2020 | B99: Carlos Barbosa | C99: =IFERROR(VLOOKUP(B99,'Regiões'!A:B,2,0),"") -> Encosta Superior do Nordeste | D99: Prefeitura Municipal, Carlos Barbosa, RS | E99: Município | G99: Prefeitura Municipal | H99: 41160001 | I99: Saúde (Custeio - PAB) | J99: Saúde | K99: Custeio | L99: 100000 | N99: Emenda Individual (processo seletivo) | O99: Recurso pago | P99: Recurso para custeio dos serviços de saúde (Piso de Atenção Básica)
A100: 2020 | B100: Dois Irmãos | C100: =IFERROR(VLOOKUP(B100,'Regiões'!A:B,2,0),"") -> Vale dos Sinos | D100: Prefeitura Municipal, Dois Irmãos, RS | E100: Município | G100: Prefeitura Municipal | H100: 41160001 | I100: Saúde (Custeio - PAB) | J100: Saúde | K100: Custeio | L100: 100000 | N100: Emenda Individual | O100: Recurso pago | P100: Recurso para custeio dos serviços de saúde (Piso de Atenção Básica)
...

Sheet Página17
A1: Área
A2: Investimento em Atenção Especializada em Saúde | B2: Saúde | C2: 1
A3: Investimento em Atenção Especializada em Saúde | B3: Saúde | C3: 2
A4: Investimento em Atenção Primária à Saúde | B4: Saúde | C4: 3
A5: Investimento em Atenção Primária à Saúde | B5: Saúde | C5: 4
A6: Investimento em Atenção Primária à Saúde | B6: Saúde | C6: 5
A7: Investimento em Atenção Primária à Saúde | B7: Saúde | C7: 6
A8: Investimento em Atenção Primária à Saúde | B8: Saúde | C8: 7
A9: Investimento em Atenção Primária à Saúde | B9: Saúde | C9: 8
A10: Investimento em Atenção Primária à Saúde | B10: Saúde | C10: 9
A11: Investimento em Atenção Primária à Saúde | B11: Saúde | C11: 10
A12: Investimento em Atenção Primária à Saúde | B12: Saúde | C12: 11
A13: Apoio a Projetos de Infraestrutura Turística | B13: Infraestrutura Turística | C13: 12
... A144: Custeio dos Serviços de Média e Alta Complexidade | B144: Saúde | C144: 143

Sheet Página16
A1: Cidade 1 | B1: Cidade
A2: Cerro Branco | B2: =VLOOKUP(A2,E:E,1,0) -> Cerro Branco | C2: 1 | E2: Aceguá | I2: Alvorada | J2: 17
A3: Nova Palma | B3: =VLOOKUP(A3,E:E,1,0) -> Nova Palma | C3: 2 | E3: Água Santa | I3: Alvorada | J3: 84
A4: Sao Sebastiao Do Cai | B4: São Sebastião do Caí | C4: 3 | E4: Agudo | I4: Arambare | J4: 85
A5: Cotipora | B5: Cotiporã | C5: 4 | E5: Ajuricaba | I5: Arroio Do Meio | J5: 95
A6: Gramado | B6: =VLOOKUP(A6,E:E,1,0) -> Gramado | C6: 5 | E6: Alecrim | I6: Arroio Do Meio | J6: 99
A7: Vera Cruz | B7: =VLOOKUP(A7,E:E,1,0) -> Vera Cruz | C7: 6 | E7: Alegrete | I7: Arroio Do Tigre | J7: 62
A8: Bento Goncalves | B8: Bento Gonçalves | C8: 7 | E8: Alegria | I8: Bento Goncalves | J8: 7
A9: Bom Principio | B9: Bom Princípio | C9: 8 | E9: Almirante Tamandaré do Sul | I9: Bento Goncalves | J9: 42
A10: Cachoeira Do Sul | B10: =VLOOKUP(A10,E:E,1,0) -> Cachoeira do Sul | C10: 9 | E10: Alpestre | I10: Bento Goncalves | J10: 76
A11: Dois Irmaos | B11: Dois Irmãos | C11: 10 | E11: Alto Alegre | I11: Bom Principio | J11: 8
A12: Faxinal Do Soturno | B12: =VLOOKUP(A12,E:E,1,0) -> Faxinal do Soturno | C12: 11 | E12: Alto Feliz | I12: Bom Principio | J12: 43
A13: Feliz | B13: =VLOOKUP(A13,E:E,1,0) -> Feliz | C13: 12 | E13: Alvorada | I13: Cachoeira Do Sul | J13: 9
A14: Lajeado | B14: =VLOOKUP(A14,E:E,1,0) -> Lajeado | C14: 13 | E14: Amaral Ferrador | I14: Cachoeira Do Sul | J14: 44
A15: Pelotas | B15: =VLOOKUP(A15,E:E,1,0) -> Pelotas | C15: 14 | E15: Ametista do Sul | I15: Cachoeirinha | J15: 74
A16: Porto Alegre | B16: =VLOOKUP(A16,E:E,1,0) -> Porto Alegre | C16: 15 | E16: André da Rocha | I16: Campo Bom | J16: 49
A17: Santa Cruz Do Sul | B17: =VLOOKUP(A17,E:E,1,0) -> Santa Cruz do Sul | C17: 16 | E17: Anta Gorda | I17: Campo Bom | J17: 86
A18: Alvorada | B18: =VLOOKUP(A18,E:E,1,0) -> Alvorada | C18: 17 | E18: Antônio Prado | I18: Candelaria | J18: 18
A19: Candelaria | B19: Candelária | C19: 18 | E19: Arambaré | I19: Candelaria | J19: 50
A20: Esteio | B20: =VLOOKUP(A20,E:E,1,0) -> Esteio | C20: 19 | E20: Araricá | I20: Canoas | J20: 87
A21: Farroupilha | B21: =VLOOKUP(A21,E:E,1,0) -> Farroupilha | C21: 20 | E21: Aratiba | I21: Caxias Do Sul | J21: 88
A22: Igrejinha | B22: =VLOOKUP(A22,E:E,1,0) -> Igrejinha | C22: 21 | E22: Arroio do Meio | I22: Caxias Do Sul | J22: 110
A23: Ivoti | B23: =VLOOKUP(A23,E:E,1,0) -> Ivoti | C23: 22 | E23: Arroio do Sal | I23: Caxias Do Sul | J23: 121
A24: Jaguari | B24: =VLOOKUP(A24,E:E,1,0) -> Jaguari | C24: 23 | E24: Arroio do Padre | I24: Cerro Branco | J24: 1
A25: Lindolfo Collor | B25: =VLOOKUP(A25,E:E,1,0) -> Lindolfo Collor | C25: 24 | E25: Arroio dos Ratos | I25: Charqueadas | J25: 83
A26: Nova Petropolis | B26: Nova Petrópolis | C26: 25 | E26: Arroio do Tigre | I26: Cotipora | J26: 4
A27: Passo Do Sobrado | B27: =VLOOKUP(A27,E:E,1,0) -> Passo do Sobrado | C27: 26 | E27: Arroio Grande | I27: Dois Irmaos | J27: 10
A28: Picada Cafe | B28: Picada Café | C28: 27 | E28: Arvorezinha | I28: Dois Lajeados | J28: 101
A29: Presidente Lucena | B29: =VLOOKUP(A29,E:E,1,0) -> Presidente Lucena | C29: 28 | E29: Augusto Pestana | I29: Dois Lajeados | J29: 111
A30: Sao Jose Do Herval | B30: São José do Herval | C30: 29 | E30: Áurea | I30: Eldorado Do Sul | J30: 65
A31: Segredo | B31: =VLOOKUP(A31,E:E,1,0) -> Segredo | C31: 30 | E31: Bagé | I31: Eldorado Do Sul | J31: 96
A32: Tres Coroas | B32: Três Coroas | C32: 31 | E32: Balneário Pinhal | I32: Encantado | J32: 55
A33: Estancia Velha | B33: Estância Velha | C33: 32 | E33: Barão | I33: Encantado | J33: 70
A34: Putinga | B34: =VLOOKUP(A34,E:E,1,0) -> Putinga | C34: 33 | E34: Barão de Cotegipe | I34: Estancia Velha | J34: 32
A35: Sapiranga | B35: =VLOOKUP(A35,E:E,1,0) -> Sapiranga | C35: 34 | E35: Barão do Triunfo | I35: Esteio | J35: 19
A36: Montenegro | B36: =VLOOKUP(A36,E:E,1,0) -> Montenegro | C36: 35 | E36: Barracão | I36: Esteio | J36: 51
A37: Sao Vendelino | B37: São Vendelino | C37: 36 | E37: Barra do Guarita | I37: Farroupilha | J37: 20
A38: Santa Maria | B38: =VLOOKUP(A38,E:E,1,0) -> Santa Maria | C38: 37 | E38: Barra do Quaraí | I38: Farroupilha | J38: 52
A39: Sao Luiz Gonzaga | B39: São Luiz Gonzaga | C39: 38 | E39: Barra do Ribeiro | I39: Faxinal Do Soturno | J39: 11
A40: Sao Sebastiao Do Cai | B40: São Sebastião do Caí | C40: 39 | E40: Barra do Rio Azul | I40: Feliz | J40: 12
A41: Gramado | B41: =VLOOKUP(A41,E:E,1,0) -> Gramado | C41: 40 | E41: Barra Funda | I41: Flores Da Cunha | J41: 102
A42: Forquetinha | B42: =VLOOKUP(A42,E:E,1,0) -> Forquetinha | C42: 41 | E42: Barros Cassal | I42: Flores Da Cunha | J42: 112
A43: Bento Goncalves | B43: Bento Gonçalves | C43: 42 | E43: Benjamin Constant do Sul | I43: Forquetinha | J43: 41
A44: Bom Principio | B44: Bom Princípio | C44: 43 | E44: Bento Gonçalves | I44: General Camara | J44: 71
A45: Cachoeira Do Sul | B45: =VLOOKUP(A45,E:E,1,0) -> Cachoeira do Sul | C45: 44 | E45: Boa Vista das Missões | I45: Gramado | J45: 5
A46: Novo Hamburgo | B46: =VLOOKUP(A46,E:E,1,0) -> Novo Hamburgo | C46: 45 | E46: Boa Vista do Buricá | I46: Gramado | J46: 40
A47: Santa Cruz Do Sul | B47: =VLOOKUP(A47,E:E,1,0) -> Santa Cruz do Sul | C47: 46 | E47: Boa Vista do Cadeado | I47: Gramado | J47: 97
A48: Sapucaia Do Sul | B48: =VLOOKUP(A48,E:E,1,0) -> Sapucaia do Sul | C48: 47 | E48: Boa Vista do Incra | I48: Gramado | J48: 100
A49: Venancio Aires | B49: Venâncio Aires | C49: 48 | E49: Boa Vista do Sul | I49: Guaiba | J49: 53
A50: Campo Bom | B50: =VLOOKUP(A50,E:E,1,0) -> Campo Bom | C50: 49 | E50: Bom Jesus | I50: Guaiba | J50: 89
A51: Candelaria | B51: Candelária | C51: 50 | E51: Bom Princípio | I51: Guapore | J51: 72
A52: Esteio | B52: =VLOOKUP(A52,E:E,1,0) -> Esteio | C52: 51 | E52: Bom Progresso | I52: Ibarama | J52: 66
A53: Farroupilha | B53: =VLOOKUP(A53,E:E,1,0) -> Farroupilha | C53: 52 | E53: Bom Retiro do Sul | I53: Igrejinha | J53: 21
A54: Guaiba | B54: Guaíba | C54: 53 | E54: Boqueirão do Leão | I54: Igrejinha | J54: 67
A55: Restinga Seca | B55: Restinga Sêca | C55: 54 | E55: Bossoroca | I55: Igrejinha | J55: 98
A56: Encantado | B56: =VLOOKUP(A56,E:E,1,0) -> Encantado | C56: 55 | E56: Bozano | I56: Imigrante | J56: 59
A57: Marques De Souza | B57: =VLOOKUP(A57,E:E,1,0) -> Marques de Souza | C57: 56 | E57: Braga | I57: Imigrante | J57: 103
A58: Parobe | B58: Parobé | C58: 57 | E58: Brochier | I58: Imigrante | J58: 113
A59: Santa Maria | B59: =VLOOKUP(A59,E:E,1,0) -> Santa Maria | C59: 58 | E59: Butiá | I59: Ivoti | J59: 22
A60: Imigrante | B60: =VLOOKUP(A60,E:E,1,0) -> Imigrante | C60: 59 | E60: Caçapava do Sul | I60: Jaguari | J60: 23
A61: Sao Sebastiao Do Cai | B61: São Sebastião do Caí | C61: 60 | E61: Cacequi | I61: Lagoa Vermelha | J61: 104
A62: Sao Martinho Da Serra | B62: São Martinho da Serra | C62: 61 | E62: Cachoeira do Sul | I62: Lagoa Vermelha | J62: 114
A63: Arroio Do Tigre | B63: =VLOOKUP(A63,E:E,1,0) -> Arroio do Tigre | C63: 62 | E63: Cachoeirinha | I63: Lajeado | J63: 13
A64: Novo Hamburgo | B64: =VLOOKUP(A64,E:E,1,0) -> Novo Hamburgo | C64: 63 | E64: Cacique Doble | I64: Lindolfo Collor | J64: 24
A65: Sao Valentim Do Sul | B65: São Valentim do Sul | C65: 64 | E65: Caibaté | I65: Maquine | J65: 105
A66: Eldorado Do Sul | B66: =VLOOKUP(A66,E:E,1,0) -> Eldorado do Sul | C66: 65 | E66: Caiçara | I66: Maquine | J66: 115
A67: Ibarama | B67: =VLOOKUP(A67,E:E,1,0) -> Ibarama | C67: 66 | E67: Camaquã | I67: Marques De Souza | J67: 56
A68: Igrejinha | B68: =VLOOKUP(A68,E:E,1,0) -> Igrejinha | C68: 67 | E68: Camargo | I68: Montenegro | J68: 35
A69: Pareci Novo | B69: =VLOOKUP(A69,E:E,1,0) -> Pareci Novo | C69: 68 | E69: Cambará do Sul | I69: Morro Reuter | J69: 106
A70: Silveira Martins | B70: =VLOOKUP(A70,E:E,1,0) -> Silveira Martins | C70: 69 | E70: Campestre da Serra | I70: Morro Reuter | J70: 116
A71: Encantado | B71: =VLOOKUP(A71,E:E,1,0) -> Encantado | C71: 70 | E71: Campina das Missões | I71: Mucum | J71: 117
A72: General Camara | B72: General Câmara | C72: 71 | E72: Campinas do Sul | I72: Mucum | J72: 122
A73: Guapore | B73: Guaporé | C73: 72 | E73: Campo Bom | I73: Nova Palma | J73: 2
A74: Santa Maria | B74: =VLOOKUP(A74,E:E,1,0) -> Santa Maria | C74: 73 | E74: Campo Novo | I74: Nova Petropolis | J74: 25
A75: Cachoeirinha | B75: =VLOOKUP(A75,E:E,1,0) -> Cachoeirinha | C75: 74 | E75: Campos Borges | I75: Nova Santa Rita | J75: 93
A76: Triunfo | B76: =VLOOKUP(A76,E:E,1,0) -> Triunfo | C76: 75 | E76: Candelária | I76: Novo Hamburgo | J76: 45
A77: Bento Goncalves | B77: Bento Gonçalves | C77: 76 | E77: Cândido Godói | I77: Novo Hamburgo | J77: 63
A78: Novo Hamburgo | B78: =VLOOKUP(A78,E:E,1,0) -> Novo Hamburgo | C78: 77 | E78: Candiota | I78: Novo Hamburgo | J78: 77
A79: Porto Alegre | B79: =VLOOKUP(A79,E:E,1,0) -> Porto Alegre | C79: 78 | E79: Canela | I79: Pareci Novo | J79: 68
A80: Santa Cruz Do Sul | B80: =VLOOKUP(A80,E:E,1,0) -> Santa Cruz do Sul | C80: 79 | E80: Canguçu | I80: Parobe | J80: 57
A81: Sao Jose Do Norte | B81: São José do Norte | C81: 80 | E81: Canoas | I81: Passo Do Sobrado | J81: 26
A82: Sao Leopoldo | B82: São Leopoldo | C82: 81 | E82: Canudos do Vale | I82: Pelotas | J82: 14
A83: Taquara | B83: =VLOOKUP(A83,E:E,1,0) -> Taquara | C83: 82 | E83: Capão Bonito do Sul | I83: Picada Cafe | J83: 27
A84: Charqueadas | B84: =VLOOKUP(A84,E:E,1,0) -> Charqueadas | C84: 83 | E84: Capão da Canoa | I84: Porto Alegre | J84: 15
A85: Alvorada | B85: =VLOOKUP(A85,E:E,1,0) -> Alvorada | C85: 84 | E85: Capão do Cipó | I85: Porto Alegre | J85: 78
A86: Arambare | B86: Arambaré | C86: 85 | E86: Capão do Leão | I86: Presidente Lucena | J86: 28
A87: Campo Bom | B87: =VLOOKUP(A87,E:E,1,0) -> Campo Bom | C87: 86 | E87: Capivari do Sul | I87: Putinga | J87: 33
A88: Canoas | B88: =VLOOKUP(A88,E:E,1,0) -> Canoas | C88: 87 | E88: Capela de Santana | I88: Relvado | J88: 107
A89: Caxias Do Sul | B89: =VLOOKUP(A89,E:E,1,0) -> Caxias do Sul | C89: 88 | E89: Capitão | I89: Relvado | J89: 118
A90: Guaiba | B90: Guaíba | C90: 89 | E90: Carazinho | I90: Restinga Seca | J90: 54
A91: Rio Grande | B91: =VLOOKUP(A91,E:E,1,0) -> Rio Grande | C91: 90 | E91: Caraá | I91: Rio Grande | J91: 90
A92: Rio Pardo | B92: =VLOOKUP(A92,E:E,1,0) -> Rio Pardo | C92: 91 | E92: Carlos Barbosa | I92: Rio Pardo | J92: 91
A93: Roca Sales | B93: =VLOOKUP(A93,E:E,1,0) -> Roca Sales | C93: 92 | E93: Carlos Gomes | I93: Roca Sales | J93: 92
A94: Nova Santa Rita | B94: =VLOOKUP(A94,E:E,1,0) -> Nova Santa Rita | C94: 93 | E94: Casca | I94: Santa Cruz Do Sul | J94: 16
A95: Veranopolis | B95: Veranópolis | C95: 94 | E95: Caseiros | I95: Santa Cruz Do Sul | J95: 46
A96: Arroio Do Meio | B96: =VLOOKUP(A96,E:E,1,0) -> Arroio do Meio | C96: 95 | E96: Catuípe | I96: Santa Cruz Do Sul | J96: 79
A97: Eldorado Do Sul | B97: =VLOOKUP(A97,E:E,1,0) -> Eldorado do Sul | C97: 96 | E97: Caxias do Sul | I97: Santa Maria | J97: 37
A98: Gramado | B98: =VLOOKUP(A98,E:E,1,0) -> Gramado | C98: 97 | E98: Centenário | I98: Santa Maria | J98: 58
A99: Igrejinha | B99: =VLOOKUP(A99,E:E,1,0) -> Igrejinha | C99: 98 | E99: Cerrito | I99: Santa Maria | J99: 73
A100: Arroio Do Meio | B100: =VLOOKUP(A100,E:E,1,0) -> Arroio do Meio | C100: 99 | E100: Cerro Branco | I100: Sao Jose Do Herval | J100: 29
...

Sheet Página15
A1: Contemplado | B1: Inscrição | C1: Município | D1: Valor solicitado | E1: Valor destinado | F1: Resumo do Projeto | G1: Objeto do Projeto | H1: Endereço de e-mail | I1: População do município | J1: Nome do responsável | K1: Telefone | L1: E-mail | M1: E-mail da Prefeitura | N1: CPF | O1: CNPJ do Fundo Municipal da Saúde | P1: O município possui teto MAC para receber os recursos da emenda parlamentar? | Q1: Total da receita prevista em 2022 (em R$) | R1: Total da receita arrecadada em 2022 (em R$) | S1: Total da despesa liquidada em 2022 (em R$) | T1: Receita corrente líquida em 2022 (em R$) | U1: Despesa com pessoal do Poder Executivo municipal em 2022 (em R$) | V1: A Prefeitura dispõe de profissionais/recursos humanos necessários para operar o equipamento solicitado? | W1: A Prefeitura dispõe de estrutura física necessária para por em funcionamento o equipamento solicitado? | X1: Justificativa do Projeto | Y1: Qual é o objetivo geral do Projeto? | Z1: Detalhe o público-alvo do Projeto | AA1: Descreva os resultados esperados após a execução do Projeto | AB1: Resumo
A2: TRUE | B2: 472 | C2: Campo Bom | D2: R$ 220.400,00 | E2: 220400 | F2: Através da aquisição de 1 (uma) mesa cirúrgica elétrica, 5 (cinco) monitores multiparamétricos, 1 (um)desfibrilador automático de mesa, 1 (um) eletrocautério e 2 (dois) carros-maca hidráulicos, o Município de Ivoti visa a qualificar e ampliar os serviços de média complexidade já ofertados pelo poder público municipal. Com esse projeto, pretende-se atender o usuário de serviços de média complexidade com maior agilidade, qualidade e resolutividade, bem como reduzir as filas de espera para as especialidades pactuadas, impactando positivamente a região. O projeto visa a captar R$ 200.000,00 e atender os usuários do serviços público de saúde. | G2: Aquisição de um Aparelho de Anestesia com Monitor Multiparâmetros | H2: CLEIDIANE@CAMPOBOM.RS.GOV.BR | I2: 66712 | J2: CLEIDIANE SANMARTIM | K2: 51 3598-8689 | L2: CLEIDIANE@CAMPOBOM.RS.GOV.BR | M2: gabinetepmcb@campobom.rs.gov.br | N2: 1845116070 | O2: 11310266000155 | P2: Sim | Q2: R$317.800.000,00 | R2: R$336.969.496,53 | S2: R$314.830.623,62 | T2: R$333.821.771,97 | U2: R$161.712.068,13 - 48,45% | V2: Sim | W2: Sim | X2: O Hospital de Campo Bom Dr. Lauro Réus é referência para a população do município. Conta com 91 leitos de internação e serviço de urgência e emergência 24h referência para uma população regional de 840 mil hab. Atende a linha de cuidado de maternidade risco habitual, cirurgia geral e traumatologia, referência para 140 mil hab. Possui ambulatório de especialidades, procedimentos ambulatoriais, exames de diagnóstico diversos e laboratório de análises clínicas. Os atendimentos são quase 100% a usuários do Sistema Único de Saúde – SUS. O centro cirúrgico do hospital, conta com três salas de cirurgias e apenas duas em operação, devido a falta de equipamentos necessários para funcionamento da terceira. Para abreviar a lista de espera da população por cirurgias eletivas (demanda reprimida), trazendo resolutividade e cuidado a população é necessária a aquisição do carro de anestesia para ativar esta sala e ampliar o número de cirurgias, visando atender a população em fila de espera. | Y2: Ativar a terceira sala de cirurgia eletiva do Hospital que não opera por falta de equipamentos, através da aquisição de um carro de anestesia para abreviar a fila de espera da população. | Z2: Pacientes com necessidade de intervenção cirúrgica, oriundos do Sistema Único de Saúde - SUS da região do Vale do Sinos. | AA2: Espera-se abreviar a fila de espera, através da resolutividade dademanda existente de forma local, gerando cuidado; bem-estar e sobrevida a população. | AB2: Equipamentos para reduzir fila de cirurgias eletivas.
A3: TRUE | B3: 70 | C3: Caxias Do Sul | D3: R$ 300.000,00 | E3: 300000 | F3: O município de Quaraí tem uma população de aproximadamente 24 mil habitantes, pertence a 10ªCoordenadoria Regional de Saúde. Está localizado na região da fronteira oeste do Estado do Rio Grande do Sul, a aproximadamente a 600km da capital gaúcha, 350 km de Santa Maria, 127 km de Uruguaiana ,106 Km de Santana do Livramento, 115Km de Alegrete e a 428km de Ijuí, sendo esses os principais destinos dos atendimentos tratamentos de fora do domícilio via GERCON. E de extrema relevância um meio de transporte adequado e seguro nos atendimentos dos usuários que necessitam realizar procedimentos de caráter eletivos e regulados em situações previsíveis de atenção programada nos municípios de referências disponibilizados. Destaca-se também o atendimento das gestantes de alto risco os quais são realizados no AGAR de Alegrete, sendo um público prioritário e que requer acompanhantes em todos atendimentos. | G3: O objeto do projeto é a aquisição de equipamento de ultrassonografia para a Central de Exames Complementares da Secretaria Municipal de Saúde. | H3: afandrade@caxias.rs.gov.br | I3: 517451 | J3: Andréia Félix Andrade | K3: 54 3290-4487 | L3: afandrade@caxias.rs.gov.br | M3: gabinetesaude@caxias.rs.gov.br | N3: 95472550025 | O3: 10546325000128 | P3: Sim | Q3: R$2.646.757.248,65 | R3: R$2.845.053.101,00 | S3: R$2.718.657.631,66 | T3: R$2.273.901.606,69 | U3: R$1.110.788.132,79 | V3: Sim | W3: Sim | X3: A aquisição do equipamento se justifica pela necessidade de suprir o atendimento à demanda crescente de usuários SUS que registra, atualmente, uma demanda reprimida de exames ecográficos em torno de 6000 unidades. | Y3: O objetivo geral do projeto visa melhorar a qualidade do serviço, permitindo o diagnóstico adequado e o manejo rápido dos pacientes, com consequente preservação da vida. | Z3: Atendimento da população em geral do município de Caxias do Sul e os demais 49 municípios da 5ª CRS. | AA3: Manter e melhorar a qualidade do serviço, atendendo a demanda reprimida de exames ecográficos. | AB3: Equipamento para diagnóstico por imagem ultrassônica.
A4: TRUE | B4: 245 | C4: Encantado | D4: R$ 192.000,00 | E4: 192000 | F4: Aquisição de equipamentos médicos para a CASA DA MULHER, oportunizando melhoria de qualidade de vida a todas mulheres, com diagnóstico rápido, preciso, sendo adquirido os seguintes equipamentos: ultrassom diagnóstico sem aplicação transesofágica; mesa para exames ginecológicos elétrica, colposcópio com camara, monitor; e tela de projeção. | G4: Aquisição de equipamentos | H4: arquitetura@encantado-rs.com.br | I4: 23000 | J4: ANA DELSA TRONCO CIVARDI | K4: 51999954279 | L4: arquitetura@encantado-rs.com.br | M4: arquitetura@encantado-rs.com.br | N4: 24358037020 | O4: 12149722000191 | P4: Sim | Q4: 109000000 | R4: 129912954 | S4: 115229707 | T4: 108672298 | U4: 42487136 | V4: Sim | W4: Sim | X4: Encantado possui somente um Hospital que presta serviços especializados e de emergência para toda a população local e regional. Estamos montando a CASA DA MULHER, onde ofereceremos atendimentos médicos especializados, tendo um atendimento diferenciado. Para tal precisamos que de equipamentos específicos para este atendimento. Com isto, teremos um atendimento de qualidade e preciso, com tecnologia e agilidade. | Y4: Aquisição de equipamentos para disponibilizar nos atendimentos especializados de média complexidade, na CASA DE MULHER. | Z4: Toda as mulheres do Município. | AA4: Melhoria da qualidade de vida das mulheres, com realização de exames específicos, oportunizando rápido encaminhamento para procedimentos e tratamentos médicos necessários | AB4: Equipamentos médicos para a CASA DA MULHER
A5: TRUE | B5: 434 | C5: Flores Da Cunha | D5: R$ 130.000,00 | E5: 130000 | F5: A aquisição das cadeiras odontológicas é muito importante, pois podem ser consideradas um dos principais equipamentos de trabalho dos serviços odontológicos, na qual facilitam o trabalho dos profissionais durante o tratamento bucal, mantendo o paciente confortável para que os procedimentos sejam realizados de forma rápida e precisa. Já, a aquisição do veículo possibilitará melhor atendimento médico e também a ampliação do atendimento domiciliar das equipes de saúde, uma vez que viabilizará a visita aos pacientes que não conseguem se deslocar até a unidade. Além das visitas regulares, a aquisição também possibilita a entrega de medicações, atendimentos em residência e coleta. | G5: Aquisição de um veículo de passeio com câmbio automático e aquisição de duas cadeiras odontológicas para a utilização na UBS - Centro de Saúde Irmã Benedita Zorzi. | H5: dppu@floresdacunha.rs.gov.br | I5: 31352 | J5: Rosiane Machado Pradella | K5: (54)3279-3600 | L5: dppu@floresdacunha.rs.gov.br | M5: planejamento@floresdacunha.rs.gov.br | N5: 1472271009 | O5: 10443938000130 | P5: Sim | Q5: R$125.498.321,00 | R5: R$162.115.259,41 | S5: R$127.730.682,21 | T5: R$138.539.650,06 | U5: R$127.730.682,21 | V5: Sim | W5: Sim | X5: O Projeto que visa a aquisição de 01 veículo de passeio com câmbio automático a ser utilizado na Unidade Básica de Saúde - Centro de Saúde Irmã Benedita Zorzi é muito importante, tendo em vista a necessidade de deslocamentos recorrentes por parte dos servidores a fim de resolver questões da saúde em todo o município. O Centro de Saúde Irmã Benedita Zorzi está em fase de ampliação e estão previstas salas para atendimento odontológico, justificando assim, a aquisição de 2 cadeiras odontológicas para melhor atender a população municipal | Y5: O Objetivo geral do Projeto é proporcionar um melhor atendimento à população municipal, melhorando a qualidade de saúde e de vidas das pessoas. | Z5: Servidores públicos da Prefeitura Municipal que exercem suas funções junto à Unidade Básica de Saúde - Centro de Saúde Irmã Benedita Zorzi, bem como, a população urbana e rural do município que necessita e busca atendimento junto à UBS. | AA5: Cadeiras odontológicas - facilidade para os profissionais durante o tratamento bucal, mantendo o paciente confortável para que os procedimentos sejam realizados de forma rápida e precisa. Veículo - melhor atendimento médico e também, a ampliação do atendimento domiciliar das equipes de saúde, uma vez que permitirá visitas aos pacientes que não podem se deslocar até a unidade. | AB5: Cadeiras odontológicas
A6: TRUE | B6: 197 | C6: Gravataí | D6: R$ 569.226,00 | E6: 569226 | F6: A Política Nacional de Atenção às Urgências é uma política baseada em serviços descentralizados, em regime de gestão pactuada entre as três esferas de governo, tendo os municípios autonomia relativa (Granja et al., 2013; Uchimura et al., 2015). Nossa solicitação de emenda parlamentar visa adquirir uma nova Unidade Móvel de Saúde – SAMU e três equipamentos cardioversores, mediante recursos da União, no valor de R$ 569.226,00. Como resultado, focamos em tecnologia, eficiência, segurança e qualidade nos atendimentos de emergência aos residentes de Gravataí e Cachoeirinha, além de maior segurança à equipe multiprofissional, no exercício de suas funções, contando com aumento de 10% no número de atendimentos realizados pelo SAMU. Por fim, tal emenda tanto qualificará os atendimentos, quanto proporcionará ampliação e racionalização do uso dos recursos públicos, em equipe e manutenção de equipamentos, possibilitando um salto de eficiência na assistência prestada. | G6: Captação de recursos para aquisição de uma Unidade Móvel de Saúde – SAMU e três equipamentos cardioversores, no valor de R$ 569.226,00 (Quinhentos e sessenta e nove mil duzentos e vinte e seis reais). | H6: sms.habilitacoes@gravatai.rs.gov.br | I6: 285564 | J6: Simone Stochero Kummer | K6: (51) 9.9967-5945 | L6: sms.habilitacoes@gravatai.rs.gov.br | M6: sms@gravatai.rs.gov.br | N6: 69371644087 | O6: 12195662000143 | P6: Sim | Q6: R$928.717.000,00 | R6: R$992.424.370,87 | S6: R$959.061.817,33 | T6: R$938.197.669,82 | U6: R$ 384.996.01,02 | V6: Sim | W6: Sim | X6: Nossos equipamentos tem apresentado repetidas necessidades de manutenção, reduzindo tempo de oferta do serviço aos usuários do SUS e/ou oferecendo risco à vida dos pacientes, considerando a imprevisibilidade dos problemas. Um atendimento qualificado e eficaz na Unidade Móvel de Saúde – SAMU-192, articulado com uma boa estrutura para o acolhimento e atendimento sequencial nas Unidades de Pronto Atendimento Municipal – UPAs, é essencial para atender efetivamente às necessidades pontuais de cada paciente. Com a Unidade, reduziremos o tempo de inatividade das equipes técnicas e alcançaremos um progresso de 10% nos atendimentos. Em 2022 tivemos 8.865 atendimentos e 876 transportes medicalizados; temos elevada quilometragem rodada em grande extensão área de cobertura para suporte avançado (512.066 Km²); Unidades Móveis datam de 2013 e 2019. Geograficamente, Gravataí é recortada por 03 precárias rodovias estaduais e 01 rodovia federal, que geram15% dos nossos atendimentos de traumas graves. | Y6: Ampliar eficiência e qualidade na Urgência e Emergência de Gravataí, com tecnologia adequadas, desde o primeiro contato até o momento da estabilização de saúde, nas Unidades de Pronto Atendimento. | Z6: População de 414.860 habitantes, residentes de Gravataí e Cachoeirinha, em suas demandas espontâneas e a partir dos atendimentos gerados em toda a rede básica, especializada e de urgência e emergência, de ambos os territórios municipais. | AA6: Segurança aos pacientes em urgências, com tecnologia qualificada e eficaz. Estima-se aumento de 10% nos atendimentos SAMU-192 e disponibilidade de uma Unidade Móvel como reserva técnica. Redução do desperdício da carga horária multiprofissional, por falta de disponibilidade da Unidade Móvel, bem como redução de custos exorbitantes com serviços de manutenção, provenientes dos cofres municipais. | AB6: Unidade Móvel de Saúde – SAMU e três equipamentos cardioversores
A7: TRUE | B7: 52 | C7: Igrejinha | D7: R$ 300.000,00 | E7: 300000 | F7: O Município de Igrejinha pretende modernizar a sua infraestrutura de TI, adquirindo 40 computadores para interligar as 14 estruturas de saúde do Município, e através da utilização de Sistemas de Informação em Saúde, agilizar o protocolo de atendimento dos pacientes, diminuindo o tempo de espera entre a marcação das consultas, atendimento, regulação e dispensação de medicamentos, além de munir os profissionais de saúde de informações para facilitar o diagnóstico e o tratamento desses pacientes. | G7: Aquisição de Computadores | H7: saude@igrejinha.rs.gov.br | I7: 37770 | J7: Vinicio Jair Wallauer | K7: 51980193111 | L7: viniciowallauer@gmail.com | M7: saude@igrejinha.rs.gov.br | N7: 61672629004 | O7: 12121651000119 | P7: Sim | Q7: R$144.300.000,00 | R7: R$168.083.845,22 | S7: R$170.580.499,53 | T7: R$163.321.270,46 | U7: R$70.761.206,06 | V7: Sim | W7: Sim | X7: A qualificação no atendimento da população na área de saúde requer que todas as estruturas funcionem em rede, de forma síncrona e para isso são necessários além de recursos humanos, equipamentos de processamento e de comunicação de dados. O Município possui 14 unidades de saúde (ESF, UBS, Farmácia, CAPS) e 1 Hospital, que precisam estar interligados para atender a comunidade e isso é feito através de Sistemas de Informação em Saúde. Os Sistemas de Informação em saúde utilizados no município de Igrejinha possibilitam esse atendimento em rede, porém o aperfeiçoamento tecnológico e a expansão da quantidade de dados a serem processados exigem uma infraestrutura de TI mais robusta e atualizada. Sabemos que na área de saúde o tempo é fundamental e para otimizar esse tempo, é necessário que todos os atores do sistema possam ter as informações necessárias em tempo real. | Y7: Adquirir computadores mais modernos e com maior poder de processamento e substituir os equipamentos obsoletos e ultrapassados para possibilitar mais agilidade e modernidade no atendimento à população. | Z7: O Público alvo do projeto são os usuários do SUS em Igrejinha cobertos pela Atenção Primária em Saúde, que representam mais de 90% da população de Igrejinha, perfazendo uma estimativa de mais de 33 mil pessoas. | AA7: Os principais resultados esperados são a agilização dos processos de encaminhamento de consultas e exames, a possibilidade de implantar sistemas mais robustos e aumentar a capacidade de armazenamento de informações, e possibilitar a regulação eletrônica, facilitando a vida dos pacientes do SUS | AB7: 40 computadores para interligar as 14 estruturas de saúde do Município
A8: TRUE | B8: 340 | C8: Ivoti | D8: R$ 200.000,00 | E8: 200000 | F8: A aquisição deste equipamento beneficiará toda a população do Município de Riozinho, na realização dos exames de imagem, evitando deslocamentos, ou se submeter a serviços na inciativa privada; o SUS - Sistema Único de Saúde estará disponível ao acesso da população em geral, mas acima de tudo das gestantes, em seu período de Pré Natal. Outro fator a ser sublinhado é o grande fluxo sazonal de turistas na visitação das atrações naturais, como cascatas e parques, tendo estes, a garantia de atendimento, quando necessário. | G8: Aquisição de 1 (uma) mesa cirúrgica elétrica, 5 (cinco) monitores multiparamétricos, 1 (um)desfibrilador automático de mesa, 1 (um) eletrocautério e 2 (dois) carros-maca hidráulicos. | H8: gabineteivoti@gmail.com | I8: 25068 | J8: Martin Cesar Kalkamnn | K8: 51 3568800 | L8: gabineteivoti@gmail.com | M8: gabinete@ivoti.rs.gov.br | N8: 513320008 | O8: 12104575000133 | P8: Sim | Q8: R$122.230.000,00 | R8: R$141.398.605,32 | S8: R$120.572.331,92 | T8: R$116.754.372,30 | U8: R$49.467.887,18 | V8: Sim | W8: Sim | X8: A Prefeitura de Ivoti, através da Secretaria de Saúde, apesar de ter o compromisso legal de atender a atenção básica, já vem oferecendo serviços de média complexidade, como pequenas cirurgias e atendimentos de especialidades. Com o intuito de qualificar e ampliar esse serviço, está em fase de construção um Centro de Especialidades, o qual exigirá equipamentos que supram as necessidades. | Y8: Qualificar e ampliar os serviços de média complexidade já ofertados pelo poder público municipal. | Z8: Usuários do serviço público de saúde - SUS. | AA8: Atendimento do usuário de serviços de média complexidade com maior agilidade, qualidade e resolutividade. Redução das filas de espera para as especialidades pactuadas, impactando positivamente a região. | AB8: - 1 mesa cirúrgica elétrica - 5 monitores multiparamétricos - 1 desfibrilador automático de mesa - 1 eletrocautério - 2 carros-maca hidráulicos.
A9: TRUE | B9: 183 | C9: Nova Roma Do Sul | D9: R$ 100.000,00 | E9: 100000 | F9: A central de exames, obra que está em finalização e com data para ser inaugurada em março do presente ano, foi idealizada para proporcionar à população de Nova Roma do Sul diversos serviços médicos que até então eram realizados em municípios vizinhos. Fato este que gerava enorme desconforto pois que demandava agendamento de viagens e grande deslocamento de pessoas. Neste sentido, busca-se implementar a central de exames no qual possibilitará o diagnóstico e tratamento mais rápido e com mais comodidade a população nova-romenses. | G9: O recurso solicitado será utilizado para compra dos equipamentos necessários à implementação do serviço de laboratório de análises clínicas, da Central de Exames de Nova Roma do Sul. | H9: tcervo2022@gmail.com | I9: 3430 | J9: TIAGO CERVO | K9: (54) 9.9967-0653 | L9: tcervo2022@gmail.com | M9: planejamento@novaromadosul.rs.gov.br | N9: 2598238052 | O9: 13895113000144 | P9: Sim | Q9: 26300000 | R9: 32123634 | S9: 31098403 | T9: 29850561 | U9: 13129734 | V9: Sim | W9: Sim | X9: Considerando que atualmente são realizados no Município de Nova Roma do Sul, apenas exames de sangue e ecografia, a Central de Exames, viria a sanar uma grande lacuna do serviço de saúde do município, pois contribuiria na agilidade dos diagnósticos, reduzindo viagens e tempo de espera para a realização destes. | Y9: Atendendo à universalidade e à igualdade, o projeto possibilitará maior agilidade no diagnóstico e retorno das consultas. | Z9: Todos os munícipes novaromenses, que dos serviços necessitarem. | AA9: Espera-se zerar a fila de espera por atendimentos, bem como proporcionar uma maior agilidade nos diagnósticos e maior eficácia no tratamento. Também se espera uma diminuição com os custos das viagens que implicam em mão de obra, diárias, combustíveis, manutenção de veículos, entre outros. | AB9: Central de exames para serviços médicos locais eficientes.
A10: TRUE | B10: 391 | C10: Presidente Lucena | D10: R$ 400.000,00 | E10: 400000 | F10: Busca o Projeto reivindicar emenda para aquisição de ambulância uma vez que o único veículo do tipo que o Município possui é velho e não atende mais as necessidades da população. Assim busca-se dotar o Município com ambulância nova que ofereça atendimento humanizado aos pacientes e propicie condições dignas de trabalho à equipe de profissionais. Diante da situação precária da ambulância do Município, pacientes que estão em condição delicada de saúde já não tem mais a garantia de que chegarão em tempo e segurança a seu destino. Tal situação causa aflição tanto a equipe de profissionais envolvidos no transporte, como aos pacientes e familiares dos mesmos. O veículo a ser adquirido irá atender a toda população do Município e eventualmente a outras pessoas que estiverem de passagem por Presidente Lucena e venham a precisar desse serviço. Para adquirir o veículo pleiteado a estimativa de mercado é que o mesmo terá custo de R$400.000,00 | G10: Aquisição de Ambulância | H10: saude@presidentelucena.rs.gov.br | I10: 3300 | J10: Joice Silvinha Froehlich | K10: (51)980413544 | L10: saude@presidentelucena.rs.gov.br | M10: fazenda@presidentelucena.rs.gov.br | N10: 889456003 | O10: 12077214000145 | P10: Sim | Q10: R$26.973.000,00 | R10: R$32.096.580,40 | S10: R$26.490.031,54 | T10: R$27.447.015,48 | U10: R$10.181.973,09 | V10: Sim | W10: Sim | X10: O Município possui um veículo com as características da ambulância a ser adquirida, porém a mesma já é um veículo com mais de 11 anos de uso e alta quilometragem, não oferecendo mais perfeitas condições de uso, não atendendo mais a real necessidade do Município. A ambulância nova a ser adquirida irá tornar mais ágeis os atendimentos, além de oferecer mais segurança e garantia de que o veículo não irá estragar no deslocamento. O Município, como entidade, através da Unidade de Saúde busca atender as demandas da população na própria Unidade Básica, porém casos complexos e de risco a saúde exigem o deslocamento dos pacientes para Hospitais em cidades próximas, região metropolitana e até à Capital. E para estes deslocamentos é necessário que os pacientes sejam conduzidos por meio de ambulância que dê o devido suporte a vida dos mesmos. Atualmente isso já não acontece mais, pois a única ambulância do Município está constantemente estragada em virtude do tempo de uso e o desgaste das peças. | Y10: Dotar o Município de ambulância nova para atender as necessidades do transporte de pacientes. | Z10: Toda população do Município, bem como pessoas de outros cidades que circularem por Presidente Lucena e vierem a precisar do serviço de ambulância. | AA10: Espera-se com a aquisição de ambulância nova, dotar a única Unidade de Saúde do Munícipio de veículo capaz de atender as necessidades dos pacientes. Dotar a saúde pública do Município de condições de oferecer atendimento humanizado aos pacientes e propiciar condições dignas de trabalho à equipe de profissionais encarregada de atender situações de emergência. | AB10: Ambulância
A11: TRUE | B11: 112 | C11: Riozinho | D11: R$ 152.600,00 | E11: 152600 | F11: Equipar toda a UBS com o mínimo de equipamento e material permanente para colocar em funcionamento. | G11: Ultrassom Diagnóstico sem aplicação transesofágica | H11: vanderleivilipetry@gmail.com | I11: 4676 | J11: Ramão Roberto Corso | K11: (51) 9.96116096 | L11: secretaria.saude@pmriozinho.com.br | M11: prefeitura@pmriozinho.com.br | N11: 80517838087 | O11: 11868258000120 | P11: Sim | Q11: R$26.770.226,50 | R11: R$33.140.807,90 | S11: R$29.645.276,10 | T11: R$25.648.260,65 | U11: R$11.598.762,24 | V11: Sim | W11: Sim | X11: Buscar qualificar um serviço na rede de atenção à saúde do usuário na média e alta complexidade, caracterizado pelo bem equipar dos ambulatórios de especialidades médicas, evitando desta forma o deslocamento para outras localidades. Embora o Município tem cotas pactuadas através de CIR e CIB, destes exames, os mesmos são realizados em número reduzido, quando seria possível instalar este equipamento junto ao atendimento da rede de atenção local, sem terceirizações e com atendimento da integralidade da demanda. Necessário grifar também que todo o acompanhamento de Pré-natal, no que tange a realização das ecografias, sem necessidade de qualquer espera ou mesmo para ofertar um número razoável destes exames em um cuidado humanizado, torna a assistência integral às gestantes. | Y11: O objetivo geral do projeto visa beneficiar os usuários, incluindo a manutenção do bem estar e do conforto durante a realização de procedimentos, menos invasivos, o que é fundamental. | Z11: Gestantes em seu Pré-Natal, visando uma gestação saudável e redução da mortalidade neonatal e infantil, como evitar o avanço de outras patologias; Prevenção de câncer de mama, sendo a ultrassonografia o exame capaz de diagnosticar casos assintomáticos, não identificados na mamografia em mulheres jovens, com alta densidade mamária e com histórico familiar. Usuários demandados da Atenção Primária. | AA11: Espera-se a humanização na prestação dos serviços, acesso facilitado para o usuário, zerar qualquer fila de espera pelos exames e economia de gastos em manutenção de frota veicular ao deixarem de buscar atendimento em outras cidades de referência. | AB11: Equipamentos para realização de exames de imagem e cirurgias eletivas.
A12: TRUE | B12: 506 | C12: São Marcos | D12: R$ 249.321,00 | E12: 249321 | F12: Em suma, o projeto visa reduzir a fila de espera significativa para cirurgias eletivas (cirurgia geral, traumatologia, oncologia, etc), decorrente do aumento no número de casos, da demanda reprimida oriunda da pandemia, bem como, pela dificuldade de encaminhamento dos casos aos centros de referência com a ativação da terceira sala de cirurgia do Hospital, que está inoperante por falta de equipamentos necessários a sua operação. Com a aquisição do carro de anestesia, a sala poderá ser ativada, ampliando assim o número de cirurgias, a fim de atender a população em fila de espera. | G12: Ambulância tipo A | H12: secretaria.saude@saomarcos.rs.gov.br | I12: 21756 | J12: MARISTELA LUNEDO | K12: 54999987889 | L12: secretaria.saude@saomarcos.rs.gov.br | M12: gabinete@saomarcos.rs.gov.br | N12: 69574332004 | O12: 12117217000165 | P12: Sim | Q12: R$103.000.000,00 | R12: R$119.629.846,13 | S12: R$104.220.015,24 | T12: R$97.152.366,91 | U12: R$37.748.316,38 | V12: Sim | W12: Sim | X12: As ambulâncias do município estão em constantes manutenções corretivas devido ao uso, atualmente conta com carro alugado e a demanda de transporte aumentou consideravelmente, visto que, temos referencias em outros municípios ( EX: gestantes e traumatologia) sendo assim, necessitamos auxilio para aquisição de uma nova viatura. | Y12: Aquisição de uma ambulância para transporte de pacientes | Z12: Todo paciente que necessite de transporte na horizontal. | AA12: Segurança e conforto para os pacientes e equipe de transporte. | AB12: Ambulância tipo A
A13: TRUE | B13: 256 | C13: Sapiranga | D13: R$ 843.316,00 | E13: 843316 | F13: O município de Sapiranga/RS, por meio deste, solicita Emenda Parlamentar no valor de R$ 843.316,00, para aquisição de 1 equipamento de Raio-X com CR, 1 impressora dry, 6 computadores básicos, 1 computador Desktop Avançado, 2 aparelhos de ar condicionado, 1 escada 2 degraus, 2 cadeiras, 1 banqueta e 1 cadeira de rodízios. Os equipamentos serão utilizados na UPA I 24 horas do município, para realização de exames de Raio-X nos atendimentos de urgência e emergência, aos usuários deste serviço, com digitalização e envio das imagens para o sistema informatizado, compartilhados e acessíveis em computadores, possibilitando maior agilidade no atendimento, e, ainda, impressão das imagens, maior conforto térmico e melhor acomodação dos pacientes. Sendo assim, solicitamos Emenda Parlamentar para o atendimento qualificado, ágil e eficiente aos usuários do SUS, pois a UPA I 24 horas é um serviço pré-hospitalar de atendimento de urgência e emergência em sistema “portas abertas”. | G13: A proposta tem por objetivo a aquisição de equipamento de Raio-X com CR, computadores básicos, computador (Desktop-Avançado) e impressora dry, aparelhos de ar condicionado 17.000 a 30.000 btus, escada 2 degraus, cadeiras, banqueta e cadeira de rodízios, para a UPA I 24 horas de Sapiranga/RS . | H13: sapsaude@sapiranga.rs.gov.br | I13: 80514 | J13: Marta Regina Klein Reichert | K13: (51) 9.9658-0736 | L13: martareichert@sapiranga.rs.gov.br | M13: gabinete@sapiranga.rs.gov.br | N13: 93934769004 | O13: 11295120000180 | P13: Sim | Q13: R$280.449.196,00 | R13: R$316.046.593,70 | S13: R$253.780.811,63 | T13: R$283.112.373,16 | U13: R$121.551.231,54 | V13: Sim | W13: Sim | X13: A UPA I 24 horas é um serviço público de saúde da rede de urgência e emergência, componente pré-hospitalar fixo, estando habilitada e qualificada junto ao Ministério da Saúde, e dispõe de atendimento médico e exames complementares pertinentes. A aquisição do aparelho de Raio-X com CR proporcionará maior praticidade no atendimento aos pacientes, com realização do exame e diagnóstico no local. Assim, o exame realizado na unidade será disponibilizado em rede, praticamente no mesmo instante, para acesso do médico no consultório e, com a impressora dry, será possível imprimir as imagens do exame, disponibilizando-as ao paciente. A climatização é importante para a conservação e bom funcionamento dos equipamentos, pois necessitam de controle de temperatura, e o cuidado com o bem-estar do paciente depende destas condições, sendo importante a instalação do ar condicionado. Por fim, os itens escada 2 degraus, cadeiras, banqueta e cadeira de rodízios contribuem para adequação da ambiência. | Y13: Aquisição de aparelho de Raio-X com CR, 7 computadores sendo e 1 Desktop avançado, 1 impressora dry, 2 aparelhos de ar condicionado, 1 escada 2 degraus, 2 cadeiras, 1 banqueta e 1 cadeira de rodízios. | Z13: A presente Proposta tem como público-alvo a população sapiranguense e, eventualmente, demais pacientes que acessem ao serviço de urgência e emergência disponibilizado pela UPA I – 24 horas, considerando o sistema de atendimento “portas abertas” da unidade. | AA13: Com a aquisição dos equipamentos objetos dessa proposta vislumbramos atender com agilidade, qualidade e eficiência aos usuários do serviço de urgência e emergência junto à UPA I 24 horas, permitindo a tomada de conduta médica antecipada e minimizando os riscos e o tempo de espera e atendimento, tempo este que pode ser crucial à saúde e à vida do paciente. | AB13: - 1 equipamento de Raio-X com CR - 1 impressora dry - 6 computadores básicos - 1 computador Desktop Avançado - 2 aparelhos de ar condicionado - 1 escada 2 degraus - 2 cadeiras - 1 banqueta - 1 cadeira de rodízios
A14: TRUE | B14: 87 | C14: Taquara | D14: R$ 320.000,00 | E14: 320000 | F14: A aquisição de um veículo de Transporte Sanitário, com acessibilidade, irá ajudar a garantir o transporte seguro dos pacientes, inclusive cadeirantes, para o comparecimento à consultas e exames. Com a aquisição do veículo, a Secretaria diminuirá os custos com transporte, tendo em vista que fará um número menor de viagens, já que o veículo possuí mais lugares que os veículos que atualmente realizam esses transportes. | G14: Aquisição de um Veículo de Transporte Sanitário (com Acessibilidade - 1 Cadeirante). | H14: planej04@taquara.rs.gov.br | I14: 57740 | J14: Valentine Vaccari Dall'Acqua | K14: (51) 9.9992-6965 | L14: valentinedallacqua@gmail.com | M14: planej04@taquara.rs.gov.br | N14: 2515145019 | O14: 11940346000196 | P14: Sim | Q14: R$197.907.923,22 | R14: R$229.273.987,85 | S14: R$213.170.171,63 | T14: R$181.747.422,26 | U14: R$104.002.024,13 | V14: Sim | W14: Sim | X14: O município de Taquara está localizado na Região 6 - Paranhana - de Saúde, que é composta por 8 municípios. Todos municípios possuem hospitais e foi construído um processo de regionalização onde cada hospital assumiu um tipo de vocacionamento. Os paciente do município são atendidos nos municípios da Região e para as especialidades que não estão contempladas regionalmente são encaminhados para outros locais, principalmente Porto Alegre (80 km) e Canoas (72 km). Para comparecer às consultas agendadas os pacientes, em sua grande maioria, recorrem ao transporte sanitário disponibilizado pela Secretaria Municipal de Saúde, seja através de ônibus contratado ou veículos próprios do município. Sem a oferta deste tipo de transporte muitos pacientes não teriam condições de comparecer aos atendimentos médicos necessários para o tratamento, sendo responsabilidade da Secretaria de Saúde oferecer condições para que os pacientes possam comparecer aos atendimentos de forma eficiente e segura. | Y14: Realizar o transporte de pacientes para comparecimento em consultas agendadas, em especialidades médicas ou realização de exames diagnósticos, ofertadas em outros municípios. | Z14: O público-alvo do projeto são os pacientes residentes no município de Taquara que acessam serviços de saúde, seja atendimento médico especializado, sejam exames diagnósticos, em outros municípios. Atualmente são realizadas mensalmente aproximadamente 800 viagens de carro para transporte de pacientes (cerca de 4.000 pessoas). | AA14: O resultado esperado é que seja possível garantir que os pacientes compareçam aos seus atendimentos agendados, evitando faltas no comparecimento à consultas e exames por insuficiência de transporte. | AB14: Veículo de Transporte Sanitário com acessibilidade

Sheet Regiões
A1: Município | B1: Região
A2: Aceguá | B2: Sudoeste do Estado
A3: Água Santa | B3: Nordeste Riograndense
A4: Agudo | B4: Centro do Estado
A5: Ajuricaba | B5: Planalto Médio
A6: Alecrim | B6: Fronteira Noroeste
A7: Alegrete | B7: Fronteira Oeste
A8: Alegria | B8: Fronteira Noroeste
A9: Almirante Tamandaré do Sul | B9: Alto Jacuí
A10: Alpestre | B10: Zona da Produção
A11: Alto Alegre | B11: Alta da Serra do Botucarai
A12: Alto Feliz | B12: Vale do Rio Caí
... A498: Xangri-lá | B498: Litoral Norte

Sheet SEC. SEGURANÇA E DEFESA
A1: OGU | B1: MUNICÍPIO | C1: BENEFICIÁRIO | D1: INSTITUIÇÃO | E1: Nº DA EMENDA | F1: Área de alocação | G1: Modalidade | H1: TIPO DE EMENDA | I1: VALOR | J1: Tipo da emenda | K1: SITUAÇÃO | L1: INFORMAÇÕES | M1: Endereço | N1: Como foi executado | O1: ARQUIVOS | P1: Código
A2: 2021 | B2: A definir | C2: Polícia Civil | D2: Polícia Civil | E2: 71220009 | H2: Emenda de Bancada | I2: 700000 | L2: 2 viaturas pick up ostensiva com cela | O2: Aquisição de 2 viaturas pick up ostensiva com cela. O valor total da emenda é de 1.650.930,54 que inclui 05 viaturas discretas tipo Sedan. Com contrapartida de 33.692,46. Proposta 028239: https://drive.google.com/file/d/13UJPbFK0izb7oc7oPflF1d60qA_i3jsW/view?usp=sharing
A3: 2021 | B3: A definir | C3: Brigada Militar | D3: Brigada Militar | E3: 71220009 | H3: Emenda de Bancada | I3: 358785 | L3: 09 motocicletas caracterizadas | O3: Viatura caracterizada tipo motocicleta. Valor total (17 motocicletas) 665.691,61. Proposta - 028449: https://drive.google.com/file/d/1WlGh1kHSwuugd7ZkBZBGgSXTxeI_v28C/view?usp=sharing
A4: 2021 | B4: A definir | C4: Brigada Militar | D4: Brigada Militar | E4: 71220009 | H4: Emenda de Bancada | I4: 296745.33 | L4: 04 Viatura ostensiva tipo pick up | O4: Aquisição 04 viatura caracterizada tipo PickUp. Valor total 1.280.468,00. Proposta 028449 : https://drive.google.com/file/d/1WlGh1kHSwuugd7ZkBZBGgSXTxeI_v28C/view?usp=sharing
A5: 2022 | B5: A definir | C5: Secretaria de Segurança Pública | D5: Brigada Militar | E5: 41160001 | F5: Segurança Pública | H5: Emenda individual | I5: 1238648.8 | J5: Emenda Individual | K5: Indicado | L5: Compra de duas SUV 118 CV (preço: 234.954,25/un) e duas PICK UP 4x4 ( 384.370,17/un) | P5: 125
A6: 2022 | B6: A definir | C6: Secretaria de Segurança Pública | D6: Polícia Civil | E6: 41160001 | F6: Segurança Pública | H6: Emenda individual | I6: 1238648.8 | J6: Emenda Individual | K6: Indicado | L6: Compra de duas SUV 118 CV (preço: 234.954,25/un) e duas PICK UP 4x4 ( 384.370,17/un) | P6: 120
A7: 2022 | B7: A definir | C7: Secretaria de Segurança Pública | D7: Corpo de Bombeiros | E7: 41160001 | F7: Segurança Pública | H7: Emenda individual | I7: 1089232.9 | J7: Emenda Individual | K7: Indicado | L7: Compra de três SUV 118 CV (preço: 234.954,25/un) e uma PICK UP 4x4 ( 384.370,17/un) | P7: 124
A8: 2022 | B8: A definir | C8: Polícia Rodoviária Federal | D8: Polícia Rodoviária Federal | H8: Emenda de bancada | I8: 500000 | J8: Emenda de bancada | K8: Indicado | P8: 121
A9: 2020 | B9: Bagé | C9: Polícia Civil | D9: 9ª Delegacia de Polícia Regional – Bagé | E9: 41160010 | H9: Emenda individual | I9: 12142.85 | K9: Recurso empenhado. Inexigibilidade de licitação aceita pelo Ministério. Recurso pago em 25/04/2022 | L9: Aquisição de Ferramenta Forense para extração, processamento e apoio na análise de dados e informações a partir de plataformas eletrônicas portáteis para estruturar a 9ª Delegacia de Polícia Regional do Interior - Bagé. | O9: Na aquisição de 01 ferramenta de extração de dados o deputado Marcel contibuiu com 12.142,85. Outro parlamentar (emenda 20980007) com 150.000,00. Proposta 2045/2020 - https://drive.google.com/file/d/1dA-xI-LIxcR9fUfK2Teoul4ATJp55IX9/view?usp=sharing | P9: 123
A10: 2020 | B10: Camaquã | C10: Brigada Militar | D10: Brigada Militar de Camaquã | H10: Emenda de Bancada | I10: 81280 | K10: Em licitação | L10: Coletes balísticos e pistolas para o contingente da Brigada Militar
A11: 2021 | B11: Caxias do sul | C11: Polícia Rodoviária Federal | D11: Polícia Rodoviária Federal | E11: 411660007 | H11: Emenda individual | I11: 250000 | K11: Licitação concluída. | L11: 1 cobertura de pista para unidade da PRF | O11: Em licitação. Com contrapartida da PRF. | P11: 121
A12: 2021 | B12: Caxias do Sul | C12: Polícia Civil | D12: 8ª Delegacia de Polícia Regional - Caxias do Sul | E12: 411600010 | H12: Emenda individual | I12: 186808.33 | L12: Viatura caracterizada tipo SUV. | O12: Proposta 21266/2021 - https://drive.google.com/file/d/100R98VIt1lNeUjjwm3cteeyTBJBt15O-/view?usp=sharing
A13: 2020 | B13: Dois Irmãos | C13: Corpo de Bombeiros | D13: Corpo de Bombeiros de Dois Irmãos | E13: 41160012 | H13: Emenda individual | I13: 162125 | K13: Recurso empenhado. Em licitação. | L13: Desencarcerador hidráulico | O13: O valor indicado pelo deputado nessa emenda (41160012) é de 500 mil. Pela proposta da Sec. de Segurança do RS serão comprados 3 desencarceradores e 23 roupas de incêndio, com contrapartida do governo do RS. Proposta 2167/2020 - https://drive.google.com/file/d/1HFuozWEpW-69Bac0gN8IIG7uNPATNnEg/view?usp=sharing
A14: 2020 | B14: Dois Irmãos | C14: Brigada Militar | D14: Brigada Militar de Dois Irmãos | H14: Emenda de Bancada | I14: 209500 | K14: Em licitação | L14: Viatura camionete pick-up 150 CV flex 4x2 para a Brigada Militar
A15: 2023 | B15: Dois Irmãos | C15: Prefeitura | D15: Prefeitura de Dois Irmãos | E15: 41160001 | H15: Emenda Individual | I15: R$ 540.000,00 | K15: Pago | L15: Implantação de video monitoramento | O15: https://drive.google.com/open?id=1aL4TlCcRuZ6KjDxbeWjlJc6erT2tVJQe
A16: 2023 | B16: Entre Rios do Sul | C16: Prefeitura | D16: Prefeitura de Entre Rios do Sul | E16: 41160001 | H16: Emenda Individual | I16: R$ 250.000,00 | K16: Indicado | L16: Aquisição de viaturas
A17: 2020 | B17: Erechim | C17: Polícia Civil | D17: 11ª Delegacia de Polícia Regional – Erechim | E17: 41160010 | H17: Emenda individual | I17: 162142.85 | K17: Recurso empenhado. Inexigibilidade de licitação aceita pelo Ministério. Recurso pago em 25/04/2022. | L17: Aquisição de Ferramenta Forense para extração, processamento e apoio na análise de dados e informações a partir de plataformas eletrônicas portáteis para a estruturação da 11ª Delegacia de Polícia Regional – Erechim | O17: Na aquisição de Ferramenta Forense para extração, processamento e apoio na análise de dados e informações a partir de plataformas eletrônicas portáteis o deputado contibuiu sozinho com 3 ferramentas totalizando 486.428,55. Proposta 2045/2020 - https://drive.google.com/file/d/1dA-xI-LIxcR9fUfK2Teoul4ATJp55IX9/view?usp=sharing
A18: 2020 | B18: Estância Velha | C18: Corpo de Bombeiros | D18: Corpo de Bombeiros de Estância Velha | E18: 41160012 | H18: Emenda individual | I18: 162125 | K18: Recurso empenhado. Em licitação. | L18: Desencarcerador hidráulico | O18: O valor indicado pelo deputado nessa emenda (41160012) é de 500 mil. Pela proposta da Sec. de Segurança do RS serão comprados 3 desencarceradores e 23 roupas de incêndio, com contrapartida do governo do RS. Proposta 2167/2020 - https://drive.google.com/file/d/1HFuozWEpW-69Bac0gN8IIG7uNPATNnEg/view?usp=sharing
A19: 2023 | B19: Feliz | C19: Prefeitura | D19: Prefeitura de Feliz | E19: 41160001 | H19: Emenda Individual | I19: R$ 150.000,00 | K19: Pago | L19: Aquisição de equipamentos para execução da 2a etapa do projeto de cercamento eletrônico do município de Feliz. | O19: https://drive.google.com/open?id=1ztfp5Xwl3eTFFIOQpG2kNGu6li8USVam
A20: 2021 | B20: Flores da Cunha | C20: Corpo de Bombeiros | D20: Corpo de Bombeiros de Flores da Cunha | E20: 41160001 | H20: Emenda individual | I20: 333333 | K20: Recurso empenhado. | L20: Ambulância/Resgate tipo C Furgão teto alto | O20: Proposta 20877/2021 - https://drive.google.com/file/d/1zay9tOPtsNNVzpC6ZdFBF2vYKCbjoI0d/view?usp=sharing
A21: 2023 | B21: Formigueiro | C21: Prefeitura | D21: Prefeitura de Formigueiro | E21: 41160001 | H21: Emenda Individual | I21: R$ 56.000,00 | K21: Pago | L21: Aquisição de armamento e equipamento de cercamento eletrônico | O21: https://drive.google.com/open?id=10mYrEJyAyHP-Lmi3w4MTScPOJxfw0cdg
A22: 2021 | B22: Giruá | C22: Corpo de Bombeiros | D22: Corpo de Bombeiros de Giruá | E22: 41160001 | H22: Emenda individual | I22: 333333 | K22: Recurso empenhado. | L22: Ambulância/Resgate tipo C Furgão teto alto | O22: Proposta 20877/2021 - https://drive.google.com/file/d/1zay9tOPtsNNVzpC6ZdFBF2vYKCbjoI0d/view?usp=sharing
A23: 2021 | B23: Ivoti | C23: Corpo de Bombeiros | D23: Corpo de Bombeiros de Ivoti | E23: 41160001 | H23: Emenda individual | I23: 333333 | K23: Recurso empenhado. | L23: Ambulância/Resgate tipo C Furgão teto alto | O23: Proposta 20877/2021 - https://drive.google.com/file/d/1zay9tOPtsNNVzpC6ZdFBF2vYKCbjoI0d/view?usp=sharing
A24: 2023 | B24: Lajeado | C24: Prefeitura | D24: Prefeitura de Lajeado | E24: 41160001 | H24: Emenda Individual | I24: R$ 165.000,00 | K24: Pago | L24: Aquisição de equipamentose ferramentas de resgate veicular para o 3º Pelotão do Copro de Bambeiros Militar do Rio Grande do Sul, no município de Lajeado. | O24: https://drive.google.com/open?id=1j0K9osA10cCunagvL0GTED-6w8Mokzo8
A25: 2023 | B25: Maximiliano de Almeida | C25: Prefeitura | D25: Prefeitura de Maximiliano de Almeida | E25: 41160001 | H25: Emenda Individual | I25: R$ 200.000,00 | K25: Indicado | L25: objetivo principal visa à participaço do municipio no Sistema de Segurança Integrada, bem como a Integração de sistemas com o escopo de compartilhamento de informaçoes para a operacionalização de monitoramento e cercamento eletrônico (vídeo monitoramento). | O25: https://drive.google.com/open?id=1Agv-3pTULJG50K9Xz5aaUtJFgxXi1FZ3
A26: 2023 | B26: Montenegro | C26: Prefeitura | D26: Prefeitura de Montenegro | E26: 41160001 | H26: Emenda Individual | I26: R$ 140.000,00 | K26: Pago | L26: O objeto do presente projeto visa a instalação de sistema de câmeras de segu- rança em 14 escolas, no município de Montenegro. (video monitoramento) | O26: https://drive.google.com/open?id=1cZ_hV_fbZXTmQP_PLDCyVHyWQC1SMGW2 | P26: 122
A27: 2023 | B27: Morro Reuter | C27: Prefeitura | D27: Prefeitura de Morro Reuter | E27: 41160001 | H27: Emenda Individual | I27: R$ 450.000,00 | K27: Indicado | L27: Instalação de equipamentos de monitoramento em 20 (vinte) pontos estratégicos e de cercamento eletrônico em 4 (quatro). (video monitoramento) | O27: https://drive.google.com/open?id=1u65kxRbekiiWARxCMGi29waOcbCJFsQ2
A28: 2020 | B28: Nova Pádua | C28: Brigada Militar | D28: Brigada Militar de Nova Pádua | E28: 71220004 | H28: Emenda de Bancada | I28: 137569 | K28: Em licitação | L28: Viatura camionete/SUV 118 CV flex 4x2 para o grupamento da Brigada Militar | O28: Proposta 006251/2020
A29: 2023 | B29: Nova Petrópolis | C29: Prefeitura | D29: Prefeitura de Nova Petrópolis | E29: 41160001 | H29: Emenda Individual | I29: R$ 450.000,00 | K29: Indicado | L29: Implantação de complemento a uma solução de monitoramento e cercamento eletrônico . | O29: https://drive.google.com/open?id=14B9ZElFlCZSWjAyQy-lwkz6P_x27HA27
A30: 2021 | B30: Novo Hamburgo | C30: Polícia Civil | D30: 2ª Delegacia de Polícia de Novo Hamburgo | E30: 41160001 | H30: Emenda individual | I30: 26383.34 | K30: Recurso empenhado. | L30: Viatura caracterizada tipo SUV. | O30: Na aquisição de 02 viaturas caracterizadas tipo SUV, o deputado Marcel contribuiu com 26.383,34. Outros parlamentares contribuíram com 300.000,00 (emenda nº 40330009), 13.191,67 (emenda nº 41210006), 3.184,67 (emenda nº 40330005) e 30.856,98 (contrapartida do estado). Proposta 21266/2021 - https://drive.google.com/file/d/100R98VIt1lNeUjjwm3cteeyTBJBt15O-/view?usp=sharing
A31: 2021 | B31: Osório | C31: Polícia Rodoviária Federal | D31: Polícia Rodoviária Federal | E31: 411660007 | H31: Emenda individual | I31: 114993 | K31: Licitação concluída. | L31: 1 cobertura de pista para unidade da PRF | O31: Em licitação. Com contrapartida da PRF.
A32: 2023 | B32: Osório | C32: Prefeitura | D32: Prefeitura de Osório | E32: 41160001 | H32: Emenda Individual | I32: R$ 300.000,00 | K32: Pago | L32: fornecimento, instalação e configuração de sistema de segurança eletrônica por meio de Videomonitoramento e Cercamento Eletrônico. | O32: https://drive.google.com/open?id=1yVxCcmVcD4APakUWqdG3jbrQ_uHVkt8h
A33: 2020 | B33: Passo Fundo | C33: Polícia Civil | D33: 6ª Delegacia de Polícia Regional – Passo Fundo | E33: 41160010 | H33: Emenda individual | I33: 162142.85 | K33: Recurso empenhado. Inexigibilidade de licitação aceita pelo Ministério. Recurso pago em 25/04/2022. | L33: Aquisição de Ferramenta Forense para extração, processamento e apoio na análise de dados e informações a partir de plataformas eletrônicas portáteis para a estruturação da 6ª Delegacia de Polícia Regional – Passo Fundo. | O33: Na aquisição de Ferramenta Forense para extração, processamento e apoio na análise de dados e informações a partir de plataformas eletrônicas portáteis o deputado contibuiu sozinho com 3 ferramentas totalizando 486.428,55. Proposta 2045/2020 - https://drive.google.com/file/d/1dA-xI-LIxcR9fUfK2Teoul4ATJp55IX9/view?usp=sharing | P33: 129
A34: 2021 | B34: Pelotas | C34: Secretaria de Administração Penitenciária | D34: 5ª Delegacia Penitenciária Regional - Pelotas | E34: 41160005 | H34: Emenda individual | I34: 180837.86 | K34: Proposta em análise no Ministério da Segurança. | L34: Aparelhamento do Grupo de Intervenção Regional (GIR): 1 Viatura Tática de Transporte Rápido, 1 Escudo Balístico, 10 Espingarda PUMP Calibre 12. | O34: O valor total indicado para o município nessa emenda (41160005) é de 201.895,56. Sendo 180.837,86 do deputado, com contrapartida de 10,43% = 21.057,70. Detalhamento: 159.074,89 - Viatura Tática de Transporte Rápido; 8.200,00 - Escudo Balístico; 34.620,67 - Espingarda PUMP Calibre 12. . Proposta 024831/2021 - https://drive.google.com/file/d/1mCz2mZU6VW77kVuqa9wnRbEiD-TvMQMu/view?usp=sharing | P34: 132
A35: 2023 | B35: Picada Café | C35: Prefeitura | D35: Prefeitura de Picada Café | E35: 41160001 | H35: Emenda Individual | I35: R$ 250.000,00 | K35: Indicado | L35: Cercamento eletronico e video monitoramento | O35: https://drive.google.com/open?id=1xnrNDYdknilwXMtJ6TcTSG84bgp2nxK1 | P35: 131
A36: 2020 | B36: Porto Alegre | C36: Polícia Civil | D36: Divisão Estadual de Combate à Corrupção e à Lavagem de Dinheiro da Polícia Civil | E36: 41160006 | H36: Emenda individual | I36: 261914 | K36: Recurso empenhado. Aguardando aceite da inexigibilidade de licitação por parte do Ministério da Justiça. Pagamento realizado em 01/04/2022. | L36: Aquisição e renovação de solução de extração de dados e análise criminal para a Divisão Estadual de Combate à Corrupção e à Lavagem de Dinheiro da Polícia Civil do Rio Grande do Sul. } RENOVAÇÃO DE LICENÇA DE SOLUÇÃO DE EXTRAÇÃO DE DADOS: | O36: Contrapartida da Secretaria Estadual de Segurança de 33.028,00. Proposta 4591/2020 - https://drive.google.com/file/d/1d12Pvlf17mGPa5Mbtjy0ixgV_QkIzcMa/view?usp=sharing
A37: 2020 | B37: Porto Alegre | C37: Polícia Civil | D37: Divisão Estadual de Combate à Corrupção e à Lavagem de Dinheiro | E37: 41160010 | H37: Emenda individual | I37: 31428.6 | K37: Recurso empenhado. Inexigibilidade de licitação aceita pelo Ministério. | L37: Aquisição de Ferramenta Forense de extração e processamento de dados provenientes da navegação na Internet para a estruturação da Divisão Estadual de Combate à Corrupção e à Lavagem de Dinheiro. | O37: Na aquisição de 01 ferramenta de extração de dados o deputado Marcel contribuiu com 31.428,60. Outro parlamentar (emenda 37930012) com 74.964,30 e a contrapartida do governo do RS foi de 4.431,86 Proposta 2045/2020 - https://drive.google.com/file/d/1dA-xI-LIxcR9fUfK2Teoul4ATJp55IX9/view?usp=sharing
A38: 2020 | B38: Porto Alegre | C38: Polícia Civil | D38: Gabinete de Inteligência e Assuntos Estratégicos da Polícia Civil | E38: 41160010 | H38: Emenda individual | I38: 111914 | K38: Recurso empenhado. Inexigibilidade de licitação aceita pelo Ministério. | L38: Aquisição de renovação de licença para solução de extração de dados (01 renovação de licença) para o Gabinete de Inteligência e Assuntos Estratégicos da Polícia Civil. | O38: Contrapartida da Secretaria Estadual de Segurança de 23.785.45. Proposta 2045/2020 - https://drive.google.com/file/d/1dA-xI-LIxcR9fUfK2Teoul4ATJp55IX9/view?usp=sharing
A39: 2020 | B39: Porto Alegre | C39: Polícia Rodoviária Federal | D39: Polícia Rodoviária Federal | E39: 41160007 | H39: Emenda individual | I39: 290000 | K39: Recurso pago | L39: Corolla blindado para a Delegacia de Santa Maria | O39: https://www.facebook.com/watch/?extid=SEO----&v=274761207761657
A40: 2021 | B40: Porto Alegre | C40: Polícia Civil | D40: Departamento Estadual de Investigações do Narcotráfico (DENARC) | E40: 41160001 | H40: Emenda individual | I40: 186808.33 | K40: Recurso empenhado. | L40: Viatura caracterizada tipo SUV. | O40: Proposta 21266/2021 - https://drive.google.com/file/d/100R98VIt1lNeUjjwm3cteeyTBJBt15O-/view?usp=sharing
A41: 2022 | B41: Porto Alegre | C41: Exército Brasileiro | D41: Comando do Exército | E41: 41160009 | H41: Emenda individual | I41: 300000 | J41: Emenda Individual | K41: Indicado | L41: Reforma do Museu MIlitar - Comando Militar do Sul
A42: 2020 | B42: Porto Alegre [IGP] | C42: Instituto Geral de Perícias | D42: Instituto Geral de Perícias | E42: 41160008 | H42: Emenda individual | I42: 31616.04 | K42: Pregão eletrônio concluído. | L42: Equipamentos e insumos para o IGP: 2 colunas LC/MS. | O42: Proposta 2174/2020 - https://drive.google.com/file/d/1d12Pvlf17mGPa5Mbtjy0ixgV_QkIzcMa/view?usp=sharing | P42: 133
A43: 2020 | B43: Porto Alegre [IGP] | C43: Instituto Geral de Perícias | D43: Instituto Geral de Perícias | E43: 41160008 | H43: Emenda individual | I43: 355.975,13 (na licitação ficou em 330 mil) | K43: Pregão eletrônio concluído. Pagamento no valor de 330.000,00 realizado em 25/04/2022. O valor unitário do espectrômetro da proposta vencedora ficou em 330.000,00 economizando recursos públicos, já que o valor empenhado era de 355.975,13 pelo aparelho. | L43: Equipamentos e insumos para o IGP: espectrômetro na região do infravermelho. Pagamento realizado em 25/04/2022. | O43: Proposta 2174/2020 - https://drive.google.com/file/d/1d12Pvlf17mGPa5Mbtjy0ixgV_QkIzcMa/view?usp=sharing | P43: 136
A44: 2020 | B44: Porto Alegre [IGP] | C44: Instituto Geral de Perícias | D44: Instituto Geral de Perícias | E44: 41160008 | H44: Emenda individual | I44: 41.388,5 (na licitação ficou em 27.999,00) | K44: Pregão eletrônio concluído. Pagamento no valor de 27.999,00 realizado em 25/10/2021. O valor unitário das mesas ginecológicas da proposta vencedora ficou em 1.866,00, economizando recursos públicos, já que o valor empenhado era de 2,759,23 por mesa (total de 41.388,50 conforme o Plano de Trabalho) | L44: Equipamentos e insumos para o IGP: 15 mesas ginecológicas. | O44: Proposta 2174/2020 - https://drive.google.com/file/d/1d12Pvlf17mGPa5Mbtjy0ixgV_QkIzcMa/view?usp=sharing
A45: 2020 | B45: Porto Alegre [IGP] | C45: Instituto Geral de Perícias | D45: Instituto Geral de Perícias | E45: 41160008 | H45: Emenda individual | I45: 41565.73 | K45: Pregão eletrônio concluído. | L45: Equipamentos e insumos para o IGP: Vials 1,5 -2 ml com tampa e septo (287 caixas com 100 unidades). | O45: Proposta 2174/2020 - https://drive.google.com/file/d/1d12Pvlf17mGPa5Mbtjy0ixgV_QkIzcMa/view?usp=sharing | P45: 130
A46: 2020 | B46: Porto Alegre [IGP] | C46: Instituto Geral de Perícias | D46: Instituto Geral de Perícias | E46: 41160008 | H46: Emenda individual | I46: 26706.33 | K46: Pregão eletrônio concluído. | L46: Equipamentos e insumos para o IGP: Vials 20 ml com tampa, lacre e septo (50 caixas com 100 unidades). | O46: Proposta 2174/2020 - https://drive.google.com/file/d/1d12Pvlf17mGPa5Mbtjy0ixgV_QkIzcMa/view?usp=sharing
A47: 2020 | B47: Porto Alegre [IGP] | C47: Instituto Geral de Perícias | D47: Instituto Geral de Perícias | E47: 41160010 | H47: Emenda individual | I47: 88086 | K47: Pregão eletrônio concluído. | L47: Atualização de equipamento de extração de dados de dispositivos móveis para o IGP. | O47: Proposta 2174/2020 - https://drive.google.com/file/d/1d12Pvlf17mGPa5Mbtjy0ixgV_QkIzcMa/view?usp=sharing
A48: 2020 | B48: Porto Alegre [IGP] | C48: Instituto Geral de Perícias | D48: Instituto Geral de Perícias | E48: 41160010 | H48: Emenda individual | I48: 200841.17 | K48: Pregão eletrônio concluído. | L48: Kit Forense de Extração Celular para PC para o IGP. | O48: Proposta 2174/2020 - https://drive.google.com/file/d/1d12Pvlf17mGPa5Mbtjy0ixgV_QkIzcMa/view?usp=sharing
A49: 2020 | B49: Porto Alegre [IGP] | C49: Instituto Geral de Perícias | D49: Instituto Geral de Perícias | E49: 41160010 | H49: Emenda individual | I49: 122560.34 | K49: Pregão eletrônio concluído. | L49: Kit Forense de Extração Celular unidade portátil para o IGP. | O49: Proposta 2174/2020 - https://drive.google.com/file/d/1d12Pvlf17mGPa5Mbtjy0ixgV_QkIzcMa/view?usp=sharing
A50: 2021 | B50: Porto Alegre [IGP] | C50: Instituto Geral de Perícias | D50: Instituto Geral de Perícias | E50: 41160001 | H50: Emenda individual | I50: 400000 | K50: Recurso empenhado. | L50: 44 câmeras fotográficas, 08 lentes para câmeras fotográficas, 05 licença perpétua do magnet ief, 01 manequim adulto para reprodução simulada dos fatos, 01 manequim infantil para reprodução simulada dos fatos, 89 pincéis para aplicação de pó revelador de impressões papilares. | O50: O deputado Marcel contribuiu com 400.000,00, com contrapartida de 57.030,19. Proposta 021355/2021 - https://drive.google.com/file/d/1snCNLonqwErA_N4mdpMmTLDYHoa30OB3/view?usp=sharing
A51: 2022 | B51: Rio Grande | C51: Marinha do Brasil | D51: Comando da Marinha Rio Grande | E51: 41160010 | H51: Emenda individual | I51: 350000 | J51: Emenda Individual | K51: Indicado | L51: Embarcação de patrulhamento
A52: 2021 | B52: Rio Pardo | C52: Corpo de Bombeiros | D52: Corpo de Bombeiros | E52: 71220009 | H52: Emenda de Bancada | I52: 330000 | L52: 01 ambulância/resgate tipo C furgão teto alto. | O52: Aquisição de 01 viatura de resgate e salvamento. Com contrapartida 33.966,66. Valor total 353.966,66. Proposta - 028534: https://drive.google.com/file/d/1z0Sm5HAnkqAcRLsVO6CusjDhOGmRDcIF/view?usp=sharing
A53: 2021 | B53: Santa Cruz do Sul | C53: Secretaria de Administração Penitenciária | D53: 8ª Delegacia Penitenciária Regional - Santa Cruz do Sul | E53: 41160005 | H53: Emenda individual | I53: 180837.86 | K53: Proposta em análise no Ministério da Segurança. | L53: Aparelhamento do Grupo de Intervenção Regional (GIR): 1 Viatura Tática de Transporte Rápido,10 Espingarda PUMP Calibre 12, 1 Escudo Balístico. | O53: O valor total indicado pelo para o município nessa emenda (41160005) é de 201.895,56. Sendo 18.0837,86 do deputado, com contrapartida de 10,43% = 21.057,70. Detalhamento: 34.620,67 - Espingarda PUMP Calibre 12; 8.200,00 - Escudo Balístico; 159.074,89 - Viatura Tática de Transporte Rápido. Proposta 024831/2021 - https://drive.google.com/file/d/1mCz2mZU6VW77kVuqa9wnRbEiD-TvMQMu/view?usp=sharing
A54: 2020 | B54: Santa Maria | C54: Polícia Civil | D54: 3ª Delegacia de Polícia Regional – Santa Maria | E54: 41160010 | H54: Emenda individual | I54: 162142.85 | K54: Recurso empenhado. Inexigibilidade de licitação aceita pelo Ministério. Recurso pago em 25/04/2022. | L54: Aquisição de Ferramenta Forense para extração, processamento e apoio na análise de dados e informações a partir de plataformas eletrônicas portáteis para a estruturação da 3ª Delegacia de Polícia Regional – Santa Maria. | O54: Na aquisição de Ferramenta Forense para extração, processamento e apoio na análise de dados e informações a partir de plataformas eletrônicas portáteis o deputado contibuiu sozinho com 3 ferramentas totalizando 486.428,55. Proposta 2045/2020 - https://drive.google.com/file/d/1dA-xI-LIxcR9fUfK2Teoul4ATJp55IX9/view?usp=sharing
A55: 2020 | B55: Santa Maria | C55: Polícia Rodoviária Federal | D55: Polícia Rodoviária Federal | E55: 41160007 | H55: Emenda Individual | I55: 290000 | K55: Recurso pago | L55: Trailblazer caminhonete 4x4 para o Centro de Operações Especiais da PRF, com sede em Porto Alegre | O55: https://www.facebook.com/watch/?extid=SEO----&v=274761207761657
A56: 2021 | B56: Santa Maria | C56: Secretaria de Administração Penitenciária | D56: 2ª Delegacia Penitenciária Regional - Santa Maria | E56: 41160005 | H56: Emenda individual | I56: 38354.48 | K56: Proposta em análise no Ministério da Segurança. | L56: Aparelhamento do Grupo de Intervenção Regional (GIR):1 Escudo Balístico, 10 Espingarda PUMP Calibre 12. | O56: O valor indicado para o município nesta emenda (41160005) é de 42.820,67. Sendo 38.354,48 do deputado, com contrapartida de 10,43% = 4466,19. Detalhamento: 8.200,00 - Escudo balístico; 34.620,67 - 10 espingardas . Proposta 024831/2021 - https://drive.google.com/file/d/1mCz2mZU6VW77kVuqa9wnRbEiD-TvMQMu/view?usp=sharing
A57: 2022 | B57: Santa Maria | C57: Aeronáutica do Brasil | D57: Comando da Aeronáutica Brasília | E57: 41160008 | H57: Emenda individual | I57: 300000 | J57: Emenda Individual | K57: Indicado | L57: Reforma das Instalações da Base Aérea de Santa Maria
A58: 2019 | B58: Santa Maria do Herval | C58: Brigada Militar | D58: Brigada Militar de Santa Maria do Herval | F58: Segurança pública | G58: Investimento | H58: Emenda de Bancada | I58: 140000 | J58: Emenda de Bancada (processo seletivo) | K58: Recurso pago | L58: Viatura Duster semi-blindada para a Brigada Militar | M58: R. 12 de Maio, Santa Maria do Herval - RS, 93995-000
A59: 2023 | B59: Santa Maria do Herval | C59: Prefeitura | D59: Prefeitura de Santa Maria do Herval | E59: 41160001 | H59: Emenda Individual | I59: R$ 235.000,00 | K59: Indicado | L59: Implantação de video monitoramento | O59: https://drive.google.com/open?id=1xM1yRvfJ0To3f4eNBd5t3jKR7XnxUZ0V
A60: 2023 | B60: Santo Antônio da Patrulha | C60: Prefeitura | D60: Prefeitura de Santo Antônio da Patrulha | E60: 41160001 | H60: Emenda Individual | I60: R$ 350.000,00 | K60: Indicado | L60: Aquisição de veículo que será destinado à Brigada Militar de Santo Antônio da Patrulha, para reforço do aparelhamento da corporação, voltado para o policiamento ostensivo. | O60: https://drive.google.com/open?id=188ZgP7AVxaIKAfpYmcOFHpGdohpAovsN
A61: 2019 | B61: São José do Hortêncio | C61: Polícia Civil | D61: Polícia Civil de São José do Hortêncio | F61: Segurança pública | G61: Investimento | H61: Emenda de Bancada | I61: 140000 | J61: Emenda de Bancada (processo seletivo) | K61: Recurso pago | L61: Viatura Duster semi-blindada para a Polícia Civil | M61: Delegacia de Polícia Civil de São José do Hortêncio, São José do Hortêncio - RS, 95755-000 | N61: https://www.primeirahora.rs/web/noticias/19911/polcia-civil-de-so-jos-do-hortncio-recebe-nova-viatura-semiblindada
A62: 2023 | B62: Sapucaia do Sul | C62: Prefeitura | D62: Prefeitura de Sapucaia do Sul | E62: 41160001 | H62: Emenda Individual | I62: R$ 481.000,00 | K62: Pago | L62: Aquisição de viaturas | O62: https://drive.google.com/open?id=1P3jAEGWvd_y5wGA_glK6yFHkwz-nb2hU
A63: 2023 | B63: Sarandi | C63: Prefeitura | D63: Prefeitura de Sarandi | E63: 41160001 | H63: Emenda Individual | I63: R$ 428.000,00 | K63: Pago | L63: veículo (viatura) utilizado para a atividade de combate a incêndio florestal, vegetações e plantações no âmbito de atendimento da cidade de Sarandi – RS, pelo Corpo de Bombeiros Militar do Estado do Rio Grande do Sul. | O63: https://drive.google.com/open?id=1XMidcmecSY7y0kVeVo6PC9FF7OXlp7QX
A64: 2023 | B64: Tapejara | C64: Prefeitura | D64: Prefeitura de Tapejara | E64: 41160001 | H64: Emenda Individual | I64: R$ 400.000,00 | K64: Pago | L64: Implantação de video monitoramento | O64: https://drive.google.com/open?id=1-1YSc6-qHIu_sYvuS9cky8UmtR32yt5w
A65: 2023 | B65: Três de Maio | C65: Prefeitura | D65: Prefeitura de Três de Maio | E65: 41160001 | H65: Emenda Individual | I65: R$ 95.000,00 | K65: Indicado | L65: Aquisição de equipamentos para videomonitoramento | O65: https://drive.google.com/open?id=1ojrLpQDGPv53im1NtuF60HvQpMRvIZeg
A66: 2019 | B66: Tupanci do Sul | C66: Brigada Militar | D66: Brigada Militar de Tupanci do Sul | F66: Segurança pública | G66: Investimento | H66: Emenda de Bancada | I66: 140000 | J66: Emenda de Bancada (processo seletivo) | K66: Recurso pago | L66: Viatura Duster semi-blindada para a Brigada Militar | M66: R. Antônio Zoti, 404, Tupanci do Sul - RS, 99878-000
A67: 2023 | B67: Tupandi | C67: Prefeitura | D67: Prefeitura de Tupandi | E67: 41160001 | H67: Emenda Individual | I67: R$ 60.000,00 | K67: Indicado | L67: Aquisição de equipamentos para videomonitoramento | O67: https://drive.google.com/open?id=1IoznEZofF-0pOtgcDUKiI35hkaFXohUz
A68: 2020 | B68: Vários municípios | C68: Brigada Militar | D68: Unidades da Brigada Militar em Porto Alegre, Canoas, Cruz Alta, Santa Maria, Guaíba, Santa Rosa, Osório, Santo Ângelo, Passo Fundo, Caxias do Sul, Pelotas, Montenegro, Santa Cruz do Sul, Novo Hamburgo e Lajeado. | E68: 41160002 | H68: Emenda individual | I68: 317925 | K68: Convênio 905241/2020 (23/12/2020). | L68: 471 capacetes de motociclista. | O68: Proposta 1500/2020 - https://drive.google.com/file/d/1aVbHDu-DKviaNACegsEerGDS8Nd_-893/view?usp=sharing
A69: 2020 | B69: Vários municípios | C69: Brigada Militar | D69: Unidades da Brigada Militar em Porto Alegre, Canoas, Cruz Alta, Santa Maria, Guaíba, Santa Rosa, Osório, Santo Ângelo, Passo Fundo, Caxias do Sul, Pelotas, Montenegro, Santa Cruz do Sul, Novo Hamburgo e Lajeado. | E69: 41160002 | H69: Emenda individual | I69: 201110,34 (valor final da licitação 91,292,31) | K69: Pagamento da emenda realizado em 25/06/2021. 102 Coletes Balísticos IIIA Masculino M, totalizando 91.292,31. Valor unitário mais baixo do que aquele previsto no Plano de Trabalho. Os 102 coletes foram direcionados para o Comando de Policiamento da Capital. | L69: 102 coletes balísticos IIIA Masculino M | O69: Proposta 1500/2020 - https://drive.google.com/file/d/1aVbHDu-DKviaNACegsEerGDS8Nd_-893/view?usp=sharing
A70: 2020 | B70: Vários municípios | C70: Brigada Militar | D70: Unidades da Brigada Militar em Porto Alegre e Região Metropolitana. | E70: 41160011 | H70: Emenda individual | I70: 224.845,32 (valor final da licitação 200.000,00) | K70: Pagamento realizado em 25/08/2021. Dos 42 dispositivos elétricos incapacitantes, 23 foram para o Comando de Policiamento Metropolitano e 19 para o Comando de Policiamento da Capital. O valor final da licitação foi de 200.000,00, abaixo dos 224.845,32 reservado pela emenda para a compra dos equipamentos | L70: 42 dispositivo elétricos incapacitantes. | O70: Proposta 1500/2020 - https://drive.google.com/file/d/1aVbHDu-DKviaNACegsEerGDS8Nd_-893/view?usp=sharing
A71: 2020 | B71: Vários municípios | C71: Brigada Militar | D71: Unidades da Brigada Militar em Porto Alegre e Região Metropolitana. | E71: 41160011 | H71: Emenda individual | I71: 156000 | L71: 75 mil unidades de munição calibre 9mm Luger para treinamento. | O71: Proposta 1500/2020 - https://drive.google.com/file/d/1aVbHDu-DKviaNACegsEerGDS8Nd_-893/view?usp=sharing
A72: 2020 | B72: Vários municípios | C72: Brigada Militar | D72: Unidades da Brigada Militar em Porto Alegre e Região Metropolitana. | E72: 41160011 | H72: Emenda individual | I72: 149872 | L72: 30400 unidades de munição calibre 9mm Luger para emprego dos brigadianos. | O72: Proposta 1500/2020 - https://drive.google.com/file/d/1aVbHDu-DKviaNACegsEerGDS8Nd_-893/view?usp=sharing
A73: 2020 | B73: Vários municípios | C73: Corpo de Bombeiros | D73: 2º Batalhão de Bombeiros Militar nas seguintes cidades: Campo Bom, Dois Irmãos, Estância Velha, Ivoti, Montenegro, Novo Hamburgo, Parobé, Portão , Sapiranga, Sapucaia do Sul, Taquara e Taquari | E73: 41160012 | H73: Emenda individual | I73: 134550 (na licitação ficou 99.387,60) | K73: Recurso empenhado. Pagamento no valor de 73.864,86 realizado em 23/03/2022. As roupas de proteção irão para o 2o Batalhão de Bombeiro Militar, com sede em São Leopoldo, e assim assim distribuídas: Campo Bom (2 unidades), Estância Velha (2), Dois Irmãos (2), Ivoti (2), Montenegro (2), Parobé (2), Portão (2), Sapiranga (2), Sapucaia do Sul (2), Taquara (2), Taquari (2), Novo Hamburgo (1). O valor unitário das roupas de combate a incêndio ficou em 4.321,20, totalizando 99.387.60. Houve economia de recursos públicos porque o valor unitário empenhado para as roubas era de 5.850,00 (totalizando 134.550,00, já com a contrapartida do governo do RS). No total o valor das roupas ficou em 99.387,060, sendo 73.864,86 da emenda do deputado e 25.522,74 do governo do RS como contrapartida. | L73: 23 roupas de combate a incêndio RIP STOP | O73: O valor indicado pelo deputado nessa emenda (41160012) é de 500 mil. Pela proposta da Sec. de Segurança do RS serão comprados 3 desencarceradores e 23 roupas de incêndio, com contrapartida do governo do RS. Proposta 2167/2020 - https://drive.google.com/file/d/1HFuozWEpW-69Bac0gN8IIG7uNPATNnEg/view?usp=sharing
A74: 2021 | B74: Vários municípios | C74: Brigada Militar | D74: Unidade da Brigada Militar a ser definida | E74: 41160001 | H74: Emenda individual | I74: 1000000 | K74: Recurso empenhado. | L74: 05 viaturas sedan | O74: Na aquisição das viaturas caracterizadas o deputado Marcel contribuiu com 1.000.000,00 com contrapartida 64.586,67. Proposta 021307/2021: https://drive.google.com/file/d/1yonAHlCerIqzVP-hw2Ps4plFF2TWlLr3/view?usp=sharing
B120: 14,4 MILHÕES PARA A SEGURANÇA PÚBLICA DO RIO GRANDE DO SUL – Orçamentos 2019, 2020, 2021 e 2022 (individuais e bancada gaúcha)
B121: Brigada Militar, Po­lícia Civil, Corpo de Bombeiros, Instituto Geral de Perícias, Secretaria de Adminis­tração Penitenciária, Polícia Rodoviária Federal e Marinha.
B122: 13 milhões – Segurança RS
B123: 1,1 milhão - PRF
B124: 300 mil – Marinha do Brasil

Sheet FLYER REGIÃO MARCEL
B1: Município | C1: Beneficiário | D1: Instituição | E1: Nº da Emenda | F1: Área de alocação | G1: Modalidade | H1: Valores destinados | I1: Tipo da emenda | J1: Situação | K1: Informações adicionais | L1: Como foi executado
A2: 2021 | B2: Porto Alegre | C2: Hospital | D2: Hospital Banco de Olhos de Porto Alegre (Associação de Literatura e Beneficência) | E2: 41160002 | F2: Saúde (Investimento - MAC) | G2: Investimento | H2: 987650 | I2: Emenda individual (processo seletivo) | J2: Recurso empenhado. | K2: Equipamentos de diagnóstico oftalmológico e gerenciamento de imagens para o Centro de Diagnósticos do hospital. Os equipamentos (microscópio especular, ecógrafo ocular, biômetro ultrassônico, tomógrafo de coerência óptica, biômetro óptico, servidor e armazenamento para sistema PACS) irão permitir maior agilidade no atendimento dos pacientes, redução no tempo de avaliação diagnóstica e diminuição da fila de espera da instituição.
A3: 2022 | B3: Porto Alegre | C3: Universidade Federal do Rio Grande Do Sul | D3: Universidade Federal do Rio Grande Do Sul | E3: 41160006 | F3: Educação | G3: Investimento | H3: 350000 | I3: Emenda Individual | J3: Indicado
A4: 2022 | B4: A definir | C4: Secretaria de Segurança Pública | D4: Brigada Militar | E4: 41160001 | F4: Segurança Pública | G4: Investimento | H4: 1238648.8 | I4: Emenda Individual | J4: Indicado | K4: Compra de duas SUV 118 CV (preço: 234.954,25/un) e duas PICK UP 4x4 ( 384.370,17/un)
A5: 2022 | B5: A definir | C5: Secretaria de Segurança Pública | D5: Polícia Civil | E5: 41160001 | F5: Segurança Pública | G5: Investimento | H5: 1238648.8 | I5: Emenda Individual | J5: Indicado | K5: Compra de duas SUV 118 CV (preço: 234.954,25/un) e duas PICK UP 4x4 ( 384.370,17/un)
A6: 2022 | B6: A definir | C6: Secretaria de Segurança Pública | D6: Corpo de Bombeiros | E6: 41160001 | F6: Segurança Pública | G6: Investimento | H6: 1089232.9 | I6: Emenda Individual | J6: Indicado | K6: Compra de três SUV 118 CV (preço: 234.954,25/un) e uma PICK UP 4x4 ( 384.370,17/un)
A7: 2021 | B7: A definir | C7: Polícia Civil | D7: Polícia Civil | E7: 71220009 | F7: Segurança Pública | G7: Investimento | H7: 700000 | I7: Emenda de Bancada | J7: Indicado | K7: 2 viaturas pick up ostensiva com cela
A8: 2021 | B8: A definir | C8: Brigada Militar | D8: Brigada Militar | E8: 71220009 | F8: Segurança Pública | G8: Investimento | H8: 358785 | I8: Emenda de Bancada | J8: Indicado | K8: 09 motocicletas caracterizadas
A9: 2021 | B9: A definir | C9: Brigada Militar | D9: Brigada Militar | E9: 71220009 | F9: Segurança Pública | G9: Investimento | H9: 296745.33 | I9: Emenda de Bancada | J9: Indicado | K9: 04 Viatura ostensiva tipo pick up
A10: 2022 | B10: Agudo | C10: Município | D10: Prefeitura Municipal | E10: 41160005 | F10: Infraestrutura Turística | G10: Investimento | H10: 250000 | I10: Emenda Individual (processo seletivo) | J10: Indicado | K10: Volkslager como centro de comercialização de produtos gastronômicos turísticos
A11: 2021 | B11: Agudo | C11: Hospital | D11: Hospital Agudo | E11: 41160003 | F11: Saúde (Custeio - MAC) | G11: Custeio | H11: 102000 | I11: Emenda individual (processo seletivo) | J11: Recurso indicado via Fundo Estadual de Saúde. Emenda paga, falttando o Fundo transferir os recursos para os hospitais. | K11: Aquisição de um novo gerador de energia elétrica para o hospital.
A12: 2021 | B12: Ajuricaba | C12: Hospital | D12: Associação Hospitalar Beneficente Ajuricaba | E12: 41160002 | F12: Saúde (Investimento - MAC) | G12: Investimento | H12: 100000 | I12: Emenda individual (processo seletivo) | J12: Recurso empenhado. | K12: Grupo-gerador movido a diesel, com potência mínima de 100 KVA, para manter em funcionamento ininterrupto os equipamentos essenciais ao suporte de pacientes do Hospital. Assegura-se, assim, o abastecimento de energia em momentos de desabastecimento, mantendo a qualidade e segurança dos atendimentos.
A13: 2022 | B13: Alegrete | C13: Hospital | D13: Santa Casa de Caridade de Alegrete | E13: 7120004 | F13: Saúde (Custeio - MAC) | G13: Custeio | H13: 300000 | I13: Emenda de bancada (processo seletivo) | J13: Recurso indicado via Fundo Estadual de Saúde. | K13: Custeio para o hospital.
B14: Alvorada | C14: Brigada Militar | F14: Segurança Pública | G14: Investimento | H14: 234954.25 | K14: SUV 118CV
A15: 2021 | B15: Arambaré | C15: Município | D15: Prefeitura Municipal | E15: 7122 0006 | F15: Infraestrutura Turística | G15: Investimento | H15: 250000 | I15: Emenda Individual (processo seletivo) | J15: Empenhado | K15: Iluminação da orla da praia da Costa Doce | L15: Proposta Aceita. Plano de Trabalho em Análise.
A16: 2020 | B16: Araricá | C16: Município/hospital mais próximo | D16: Prefeitura/Hospital Sapiranga | F16: Saúde (Custeio - MAC) | G16: Custeio | H16: 50000 | I16: Emenda de bancada | J16: Recurso pago | K16: Recursos para custeio do combate à COVID-19 (Média e Alta Complexidade). Como o município não possuía hospital para atender pacientes de COVID-19, e como o recurso era destinado a hospitais, a emenda foi alocada no hospital de referência do município. Prefeitos e hospitais foram comunicados.
A17: 2020 | B17: Arroio do Meio | C17: Município | D17: Prefeitura Municipal | E17: 41160001 | F17: Saúde (Custeio - PAB) | G17: Custeio | H17: 100000 | I17: Emenda Individual (processo seletivo) | J17: Recurso pago | K17: Recurso para custeio dos serviços de saúde (Piso de Atenção Básica)
A18: 2022 | B18: Arroio do Tigre | C18: Hospital | D18: Associação Beneficente Santa Rosa De Lima | E18: 41160003 | F18: Saúde (Investimento - MAC) | G18: Investimento | H18: 120000 | I18: Emenda Individual | J18: Indicado
A19: 2020 | B19: Bagé | C19: Hospital | D19: Santa Casa de Caridade de Bagé | E19: 41160005 | F19: Saúde (Custeio - MAC) | G19: Custeio | H19: 100000 | I19: Emenda Individual (processo seletivo) | J19: Recurso pago | K19: Recurso para custeio dos serviços de saúde (Média e Alta Complexidade)
A20: 2020 | B20: Bagé | C20: Polícia Civil | D20: 9ª Delegacia de Polícia Regional – Bagé | E20: 41160010 | F20: Segurança pública | G20: Investimento | H20: 12142.85 | I20: Emenda individual | J20: Recurso empenhado. Inexigibilidade de licitação aceita pelo Ministério. Recurso pago em 25/04/2022 | K20: Aquisição de Ferramenta Forense para extração, processamento e apoio na análise de dados e informações a partir de plataformas eletrônicas portáteis para estruturar a 9ª Delegacia de Polícia Regional do Interior - Bagé.
A21: 2022 | B21: Bagé | C21: Fundação Universidade Federal do Pampa | D21: Fundação Universidade Federal do Pampa | E21: 41160004 | F21: Educação | G21: Investimento | H21: 350000 | I21: Emenda Individual | J21: Indicado
A22: 2020 | B22: Barão | C22: Município | D22: Prefeitura Municipal | E22: 41160001 | F22: Saúde (Custeio - PAB) | G22: Custeio | H22: 100000 | I22: Emenda Individual (processo seletivo) | J22: Recurso pago | K22: Recurso para custeio dos serviços de saúde (Piso de Atenção Básica) | L22: .
A23: 2022 | B23: Barão de Cotegipe | C23: Município | D23: Prefeitura Municipal | E23: 41160002 | F23: Saúde (Custeio - PAB) | G23: Custeio | H23: 20000 | I23: Emenda Individual | J23: Indicado
A24: 2022 | B24: Barão de Cotegipe | C24: Prefeitura | D24: Prefeitura Municipal | E24: 41160002 | F24: Saúde (Custeio - PAB) | G24: Custeio | H24: 20000 | I24: Emenda individual (processo seletivo 2021) | J24: Prefeitura submeteu proposta ao Ministério da Saúde | K24: Câmara para conservação de vacinas, medicamentos e termolábeis de 420L para a UBS do município.
A25: 2021 | B25: Barros Cassal | C25: Município | D25: Prefeitura Municipal | E25: 41160002 | F25: Saúde (Investimento - MAC) | G25: Investimento | H25: 245000 | I25: Emenda individual (processo seletivo) | J25: Proposta aprovada para pagamento. | K25: Van para implantar o transporte sanitário eletivo, beneficiando a população de baixa renda que necessita deslocar-se a hospitais da região para atendimentos com médicos especializados e realização de procedimentos de maior complexidade. Recurso enviado via Fundo Municipal de Saúde de Barros Cassal.
A26: 2020 | B26: Bento Gonçalves | C26: Hospital | D26: Hospital Tacchini | E26: 41160005 | F26: Saúde (Custeio - MAC) | G26: Custeio | H26: 100000 | I26: Emenda Individual (processo seletivo) | J26: Recurso pago | K26: Recurso para custeio dos serviços de saúde (Média e Alta Complexidade) | L26: Em atenção ao Of. n. 135/2020, de 26/11/2020, e com base no Projeto apresentado através do e-mail datado de 27/07/2020 (leitura realizada em 28/07/2020), com o valor de 100.000,00 recebido através de Emenda Parlamentar - Portaria GM/MS nº 679/2020, de autoria do Deputado Federal Marcel Van Hattem, foi possível reduzir o indicador percentual de tempo de espera cirúrgica acima de 60 dias, de 54,00% para 30,33% , ao mesmo tempo em que, foi possível ampliar o atendimento e beneficiar na realização de tratamento cirúrgico em oncologia de 26 novos pacientes oncológicos, que ingressaram na UNACON do Hospital Tacchini (Bento Gonçalves - RS), período de agosto, setembro e outubro de 2020, conforme as seguintes AIH's: Agosto/2020 - 4320104280140; 4320105042715; 4320105069049; 4320105808865; 4320103526959; 4320103526937; 4320103527400 / Setembro/2020 - 4320104281537; 4320104281548; 4320104281890; 4320104283891; 4320104281603; 4320104277907; 4320104281559 / Outubro/2020 - 4320104284353; 4320106584453; 4320106586796; 4320107313566; 4320107346115; 4320105048699; 4320105048534; 4320105809900; 4320105048370; 4320105822087; 4320104286069; 4320105050635.
A27: 2021 | B27: Bento Gonçalves | C27: Hospital | D27: Associação Dr. Bartholomeu Tacchini - Hospital Tacchini | E27: 41160002 | F27: Saúde (Investimento - MAC) | G27: Investimento | H27: 140000 | I27: Emenda individual (processo seletivo) | J27: Recurso empenhado. | K27: Aquisição e instalação de duas novas máquinas de hemodiálise para o tratamento de pacientes nefrológicos crônicos e agudos através do SUS. O hospital atende pacientes de oito municípios da Serra Gaúcha.
A28: 2021 | B28: Bento Gonçalves | C28: Hospital Municipal | D28: Complexo Hospitalar de Bento Gonçalves | E28: 41160003 | F28: Saúde (Custeio - MAC) | G28: Custeio | H28: 1000000 | I28: Emenda individual (processo seletivo) | J28: Recurso pago. | K28: Instalação de energia fotovoltaica no Complexo de Saúde do Trabalhador, que compreende laboratório, centro de imagens, UPA 24 horas, farmácia e 40 leitos. O Complexo gastou, em 2020, 400.000,00 com energia elétrica. A usina de energia solar fotovoltaica, com a instalação de 811 placas de 330W, pretende reduzir em 70% o valor do gasto com energia, uma economia de 26.000,00 mensais. O valor economizado será revertido para a ampliação do atendimento da população que procura o complexo público de saúde. Recurso enviado via Fundo Municipal de Saúde de Bento Gonçalves.
A29: 2020 | B29: Bom Princípio | C29: Município | D29: Prefeitura Municipal | E29: 41160001 | F29: Saúde (Custeio - PAB) | G29: Custeio | H29: 100000 | I29: Emenda Individual (processo seletivo) | J29: Recurso pago | K29: Recurso para custeio dos serviços de saúde (Piso de Atenção Básica)
A30: 2019 | B30: Bom Progresso | C30: Escola Agrotécnica | D30: E.T.E. Celeiro | E30: 71220005 | F30: Educação (escola estadual agrotécnica) | G30: Investimento | H30: 63000 | I30: Emenda de Bancada (processo seletivo) | J30: Recurso pago | K30: Recurso para a aquisição de implementos agrícolas | L30: Implementos agrícolas entregues a partir de abril de 2021.
A31: 2021 | B31: Bom Retiro do Sul | C31: Hospital | D31: Hospital de Caridade Santana | E31: 41160003 | F31: Saúde (Custeio - MAC) | G31: Custeio | H31: 114409 | I31: Emenda individual (processo seletivo) | J31: Recurso indicado via Fundo Estadual de Saúde. Emenda paga, falttando o Fundo transferir os recursos para os hospitais. | K31: Usina de energia solar fotovoltaica.
A32: 2020 | B32: Boqueirão do Leão | C32: Município | D32: Prefeitura Municipal | E32: 41160001 | F32: Saúde (Custeio - PAB) | G32: Custeio | H32: 67500 | I32: Emenda Individual (processo seletivo) | J32: Recurso pago | K32: Recurso para custeio dos serviços de saúde (Piso de Atenção Básica)
A33: 2020 | B33: Brochier | C33: Município | D33: Prefeitura Municipal | E33: 41160001 | F33: Saúde (Custeio - PAB) | G33: Custeio | H33: 100000 | I33: Emenda Individual (processo seletivo) | J33: Recurso pago | K33: Recurso para custeio dos serviços de saúde (Piso de Atenção Básica) | L33: 1) Pagamento de parte das despesas com Serviços Médicos e profissionais de saúde, através do Consórcio dos Municípios do Vale do Caí - CIS/CAI conforme empenhos a seguir relacionados: - 3818/2020 - no valor de 20.993,50; - 3494/2020 - no valor de 20.553,00; - 3218/2020 - no valor de 9.344,00; - 3216/2020 - no valor de 6.230,00; - 2928/2020 - no valor de 13.333,00; - 2926/2020 - no valor de 9.065,00; - 2587/2020 - no valor de 6.722,00; - 2580/2020 - no valor de 6.610,00; - 2579/2020 - no valor de 41.552,00; - 2237/2020 - no valor de 42.754,00; Trata esta prestação de contas de informação complementar à prestação de contas enviada na data de ontem, no intuito de esclarecer que os recursos aplicados serviram para ampliar o horário de atendimento no posto de saúde da sede do Município, que ocorre então das 7h da manhã até às 21h ininterruptamente. Com pode ser observado os recursos servem para custear parte da contratação de pessoal necessário para possibilitar o atendimento estendido no posto de saúde.
A34: 2022 | B34: Cachoeira do Sul | C34: Hospital | D34: Hospital de Caridade e Beneficência de Cachoeira do Sul | E34: 7120004 | F34: Saúde (Custeio - MAC) | G34: Custeio | H34: 200000 | I34: Emenda de bancada (processo seletivo) | J34: Recurso indicado via Fundo Municipal de Saúde de Cachoeira do Sul. | K34: Energia fotovoltaica
B35: Cachoeirinha | C35: Brigada Militar | H35: 384370.17 | K35: PICK UP 4X4
A36: 2020 | B36: Camaquã | C36: Brigada Militar | D36: Brigada Militar de Camaquã | F36: Segurança pública | G36: Investimento | H36: 81280 | I36: Emenda de Bancada | J36: Em licitação | K36: Coletes balísticos e pistolas para o contingente da Brigada Militar | L36: Material em processo licitatório pela Secretaria de Segurança Pública do Rio Grande do Sul
A37: 2020 | B37: Cambará do Sul | C37: Hospital | D37: Fundação Hospitalar São José de Cambará do Sul | E37: 7122 0006 | F37: Saúde (Custeio - MAC) | G37: Custeio | H37: 174741 | I37: Emenda de Bancada | J37: Recurso pago | K37: Recursos para custeio do combate à COVID-19 (Média e Alta Complexidade)
A38: 2022 | B38: Campo Bom | C38: Município | D38: Fundo Municipal de Saúde | E38: 41160003 | F38: Saúde (Investimento - MAC) | G38: Investimento | H38: 250000 | I38: Emenda Individual | J38: Indicado
A39: 2020 | B39: Campo Bom | C39: Hospital | D39: Hospital de Campo Bom Dr. Lauro Reus | E39: 7122 0006 | F39: Saúde (Custeio - MAC) | G39: Custeio | H39: 100000 | I39: Emenda de Bancada | J39: Recurso pago | K39: Recursos para custeio do combate à COVID-19 (Média e Alta Complexidade)
A40: 2022 | B40: Campos Borges | C40: Município | D40: Prefeitura Municipal | E40: 41160002 | F40: Saúde (Custeio - PAB) | G40: Custeio | H40: 35000 | I40: Emenda Individual | J40: Indicado
A41: 2022 | B41: Campos Borges | C41: Prefeitura | D41: Prefeitura Municipal | E41: 41160002 | F41: Saúde (Custeio - PAB) | G41: Custeio | H41: 35000 | I41: Emenda individual (processo seletivo 2021) | J41: Prefeitura submeteu proposta ao Ministério da Saúde | K41: Equipamentos de fisioterapia (barra, eletroestimulador, bicicleta ergométrica, maca hidráulica) para ampliar a rede de atendimento e a oferta de serviços fisioterápicos na UBS do município.
A42: 2022 | B42: Candelária | C42: Município | D42: Prefeitura Municipal | E42: 41160005 | F42: Infraestrutura Turística | G42: Investimento | H42: 250000 | I42: Emenda Individual (processo seletivo) | J42: Indicado | K42: Colocação de escada no Morro Botucaraí e construção de dois sanitários aos pés do Morro.
A43: 2020 | B43: Canela | C43: Hospital | D43: Hospital de Caridade de Canela | E43: 7122 0006 | F43: Saúde (Custeio - MAC) | G43: Custeio | H43: 50000 | I43: Emenda de Bancada | J43: Recurso pago | K43: Recursos para custeio do combate à COVID-19 (Média e Alta Complexidade)
A44: 2020 | B44: Canela | C44: Município | D44: Prefeitura Municipal | E44: 41160001 | F44: Saúde (Custeio - PAB) | G44: Custeio | H44: 67500 | I44: Emenda Individual (processo seletivo) | J44: Recurso pago | K44: Recurso para custeio dos serviços de saúde (Piso de Atenção Básica)
A45: 2022 | B45: Canoas | C45: Município | D45: Fundo Municipal de Saúde | E45: 41160003 | F45: Saúde (Investimento - MAC) | G45: Investimento | H45: 610000 | I45: Emenda Individual | J45: Indicado
A46: 2020 | B46: Canoas | C46: Hospital | D46: Hospital Universitário de Canoas | E46: 41160005 | F46: Saúde (Custeio - MAC) | G46: Custeio | H46: 150.000,00 / 200.000,00 | I46: Emenda Individual | J46: Recurso pago | K46: Recurso para Implemento Mac | L46: Por se tratar de recursos para INCREMENTO MAC, os mesmos foram repassados para os CNES que foram cadastrados no sistema do FNS(Hospital Universitário e Hospital Nossa Senhora da Graças).
A47: 2020 | B47: Canoas | C47: Hospital | D47: Hospital Nossa Senhora das Graças | E47: 41160005 | F47: Saúde (Custeio - MAC) | G47: Custeio | H47: 50000 | I47: Emenda Individual | J47: Recurso pago | K47: Recurso para Implemento Mac | L47: Após cumprimentá-lo, vimos através desta, em resposta ao ofício de n. 137/2020, prestar informações atualizadas sobre o recurso financeiro destinado ao HNSG, em razão de emenda parlamentar impositiva individual de nº 41160005, na área da saúde (custeio) no Orçamento Geral da União 2020, no valor de 50.000,00 (cinqüenta mil reais). Primeiramente, insta apontar que o recurso em questão restou aplicado no Fundo Municipal de Saúde do Município de Canoas/RS, porém, com o não atingimento das metas do Plano Operativo do ano corrente, tais verbas não foram repassadas ao Hospital. A instituição destinatária da emenda parlamentar esteve, durante todo o ano de 2020, em estado crítico financeiro e assistencial, de forma tão grave que desencadeou a declaração de Requisição Administrativa pela Prefeitura Municipal de Canoas, através do Decreto nº 263, de 23 de outubro de 2020, como forma de tentativa de reversão deste quadro. Por isso, apesar de não ter observado o Plano Operativo de 2020 em sua integralidade, tem chances reais e concretas de fazê-lo em 2021, em razão do advento da nova diretoria nomeada pelo Poder Público Municipal, bem como por conta da ampliação de previsão de procedimentos e serviços à população Canoense no novo Plano Operativo. Com isso, haverá, então, o repasse dos recursos financeiros do Fundo Municipal da Saúde ao nosocômio, e a efetiva aplicação destes, possibilitando a prestação de contas requerida.
B48: Canoas | C48: Corpo de Bombeiros | D48: 8º Batalhão de Bombeiro Militar) | H48: 234954.25 | K48: SUV 118CV
A49: 2020 | B49: Capão Bonito do Sul | C49: Município/hospital mais próximo | D49: Prefeitura/Hospital São Paulo de Lagoa Vermelha | E49: 7122 0006 | F49: Saúde (Custeio - MAC) | G49: Custeio | H49: 50000 | I49: Emenda de bancada OGU 2020 | J49: Recurso pago | K49: Recursos para custeio do combate à COVID-19 (Média e Alta Complexidade). Como o município não possuía hospital para atender pacientes de COVID-19, e como o recurso era destinado a hospitais, a emenda foi alocada no hospital de referência do município. Prefeitos e hospitais foram comunicados.
A50: 2019 | B50: Carazinho | C50: Escola Agrotécnica | D50: E.E.E.P. de Carazinho | E50: 71220005 | F50: Educação (escola estadual agrotécnica) | G50: Investimento | H50: 59000 | I50: Emenda de Bancada (processo seletivo) | J50: Recurso pago | K50: Recurso para a aquisição de implementos agrícolas | L50: Implementos agrícolas entregues a partir de abril de 2021.
A51: 2020 | B51: Carazinho | C51: Hospital | D51: Hospital Comunitário de Carazinho | E51: 7122 0006 | F51: Saúde (Custeio - MAC) | G51: Custeio | H51: 50000 | I51: Emenda de Bancada | J51: Recurso pago | K51: Recursos para custeio do combate à COVID-19 (Média e Alta Complexidade)
A52: 2020 | B52: Carlos Barbosa | C52: Município | D52: Prefeitura Municipal | E52: 41160001 | F52: Saúde (Custeio - PAB) | G52: Custeio | H52: 100000 | I52: Emenda Individual (processo seletivo) | J52: Recurso pago | K52: Recurso para custeio dos serviços de saúde (Piso de Atenção Básica)
A53: 2021 | B53: Carlos Barbosa | C53: Hospital | D53: Hospital São Roque | E53: 41160003 | F53: Saúde (Custeio - MAC) | G53: Custeio | H53: 400000 | I53: Emenda individual (processo seletivo) | J53: Recurso pago. | K53: Instalação de um gerador fotovoltaico com capacidade de 10.800 kW/mês. O hospital gastou, em 2020, 260.000,00 com energia elétrica. O projeto irá reduzir em 40% a energia consumida, produzindo uma economia, no longo prazo (em 20 anos e considerando uma inflação de 5% na energia ao ano) de 4.405.336,21. A redução desse custo permitirá investimentos em equipamentos, ampliação do hospital e capacitação dos funcionários. Recurso enviado via Fundo Municipal de Saúde de Carlos Barbosa.
A54: 2021 | B54: Casca | C54: Hospital | D54: Hospital Beneficente Santa Lucia | E54: 41160002 | F54: Saúde (Investimento - MAC) | G54: Investimento | H54: 250000 | I54: Emenda individual (processo seletivo) | K54: Aparelho de endoscopia e colonoscopia para qualificar o atendimento SUS e possibilitar que o hospital torne-se referência regional de média complexidade na especialidade de proctologia, beneficiando 32 municípios da região e atendendo demanda reprimida.
A55: 2020 | B55: Caxias do sul | C55: Hospital | D55: Hospital Virvi Ramos | E55: 41160005 | F55: Saúde (Custeio - MAC) | G55: Custeio | H55: 300000 | I55: Emenda Individual (processo seletivo) | J55: Recurso pago | K55: Recurso para custeio dos serviços de saúde (Média e Alta Complexidade) | L55: Foi elaborado um Termo de Fomento com a Prefeitura Municipal de Caxias do Sul juntamente com outras Emendas Parlamentares. O valor será utilizado para aquisição de medicamentos , pagamento aos fornecedores de gases medicinais, Energia Elétrica, Água e prestadores de serviços de manutenção de equipamentos e descarte de resíduos. Termo de Fomento nº 2020/716.
A56: 2020 | B56: Caxias do sul | C56: Hospital | D56: Hospital Geral de Caxias do Sul | E56: 41160005 | F56: Saúde (Custeio - MAC) | G56: Custeio | H56: 200000 | I56: Emenda Individual (processo seletivo) | J56: Recurso pago | K56: Recurso para custeio dos serviços de saúde (Média e Alta Complexidade) | L56: O recurso foi utilizado para a aquisição de insumos de uso mensal, como: Papel A4, Luvas de procedimentos, Micropore, Máscara descartável, Campo operatório, Escova descartável com clorexidina, Compressa cirúrgica, Algodão, Gaze e Compressa de gaze.
A57: 2021 | B57: Caxias do sul | C57: Polícia Rodoviária Federal | D57: Polícia Rodoviária Federal | E57: 411660007 | F57: Segurança pública | G57: Investimento | H57: 250000 | I57: Emenda individual | J57: Empresa contratada e em fase de execução. | K57: 1 cobertura de pista para unidade da PRF
A58: 2021 | B58: Caxias do sul | C58: Polícia Civil | D58: 8ª Delegacia de Polícia Regional - Caxias do Sul | E58: 411600010 | F58: Segurança pública | G58: Investimento | H58: 186808.33 | I58: Emenda individual | J58: Indicado | K58: Viatura caracterizada tipo SUV.
A59: 2021 | B59: Caxias do sul | C59: Hospital | D59: Hospital Pompeia | E59: 41160003 | F59: Saúde (Custeio - MAC) | G59: Custeio | H59: 170000 | I59: Emenda individual (processo seletivo) | J59: Recurso indicado via Fundo Municipal de Saúde de Caxias do Sul. | K59: Custeio para o hospital.
A60: 2022 | B60: Caxias do sul | C60: Hospital | D60: Hospital Geral de Caxias do Sul | E60: 7120004 | F60: Saúde (Custeio - MAC) | G60: Custeio | H60: 350000 | I60: Emenda de bancada (processo seletivo) | J60: Recurso indicado via Fundo Municipal de Saúde de Caxias do Sul. | K60: Custeio para o hospital.
A61: 2021 | B61: Cruz Alta | C61: Hospital | D61: Hospital São Vicente de Paulo (Associação das Damas de Caridade) | E61: 41160002 | F61: Saúde (Investimento - MAC) | G61: Investimento | H61: 141478.98 | I61: Emenda individual (processo seletivo) | J61: Empenhado | K61: Modernização do serviço de diálise com a aquisição de duas novas máquinas para tratamento. Aumento do número de atendimentos na Unidade de Terapia Renal e UTI.
A62: 2022 | B62: Derrubadas | C62: Município | D62: Prefeitura Municipal | E62: 41160005 | F62: Infraestrutura Turística | G62: Investimento | H62: 250000 | I62: Emenda Individual (processo seletivo) | J62: Indicado | K62: Instalação de pontos de apoio e centro regional de atendimento ao turista (rotas de cicloturismo e caminhada).
A63: 2019 | B63: Dilermando de Aguiar | C63: Brigada Militar | D63: Brigada Militar de Dilermando de Aguiar | F63: Segurança pública | G63: Investimento | H63: 140000 | I63: Emenda de Bancada (processo seletivo) | J63: Recurso pago | K63: Viatura Duster semi-blindada para a Brigada Militar | L63: Viatura entregue em maio de 2021.
A64: 2020 | B64: Dois Irmãos | C64: Município | D64: DNIT-DEPARTAMENTO NACIONAL DE INFRAEST DE TRANSPORTES Porto Alegre | E64: 41160003 | F64: DNIT-DEPARTAMENTO NACIONAL DE INFRAEST DE TRANSPORTES Porto Alegre | G64: Investimento | H64: 3780227 | I64: Emenda Individual | J64: Recurso pago
A65: 2021 | B65: Dois Irmãos | C65: Município | D65: Min. Desenvolvimento Regional | E65: 41160006 | F65: Ministério do Desenvolvimento Regional | G65: Investimento | H65: 2814993 | I65: Emenda Individual | J65: Recurso pago
A66: 2020 | B66: Dois Irmãos | C66: Corpo de Bombeiros | D66: Corpo de Bombeiros de Dois Irmãos | E66: 41160012 | F66: Segurança pública | G66: Investimento | H66: 162125 | I66: Emenda individual | J66: Aguarda liberação de recurso | K66: Desencarcerador hidráulico
A67: 2020 | B67: Dois Irmãos | C67: Corpo de Bombeiros | D67: Corpo de Bombeiros de Dois Irmãos | E67: 41160012 | F67: Segurança pública | G67: Investimento | I67: Emenda individual | J67: Aguarda entrega | K67: Roupa de combate a incêndio RIP STOP
A68: 2020 | B68: Dois Irmãos | C68: Hospital | D68: Hospital São José de Dois Irmãos | E68: 7122 0006 | F68: Saúde (Custeio - MAC) | G68: Investimento | H68: 1874000 | I68: Emenda de Bancada | J68: Recurso pago | K68: Obra de ampliação de ala do Hospital São José de Dois Irmãos com 20 novos leitos e bloco cirúrgico. Recursos COVID-19. | L68: Obra concluída e inaugurada em abril de 2021.
A69: 2020 | B69: Dois Irmãos | C69: Município | D69: Prefeitura Municipal | E69: 41160001 | F69: Saúde (Custeio - PAB) | G69: Custeio | H69: 100000 | I69: Emenda Individual | J69: Recurso pago | K69: Recurso para custeio dos serviços de saúde (Piso de Atenção Básica)
A70: 2020 | B70: Dois Irmãos | C70: Brigada Militar | D70: Brigada Militar de Dois Irmãos | F70: Segurança pública | G70: Investimento | H70: 209500 | I70: Emenda de Bancada | J70: Em licitação | K70: Viatura camionete pick-up 150 CV flex 4x2 para a Brigada Militar | L70: Viatura em processo licitatório pela Secretaria de Segurança Pública do Rio Grande do Sul
A71: 2022 | B71: Dois Irmãos | C71: Hospital | D71: Hospital São José de Dois Irmãos | E71: 7120004 | F71: Saúde (Custeio - MAC) | G71: Custeio | H71: 106674.25 | I71: Emenda de bancada | J71: Recurso indicado via Fundo Estadual de Saúde. | K71: Custeio para o hospital.
A72: 2020 | B72: Dois Irmãos | C72: Polícia Civil | F72: Segurança pública | G72: Investimento | H72: 384370.17 | I72: Emenda de Bancada | J72: Aguarda aprovação de licitação e liberação de recurso | K72: PICK UP 4X4
A73: 2019 | B73: Dom Pedrito | C73: Escola Agrotécnica | D73: E.E.E.P. Dom Pedrito | E73: 71220005 | F73: Educação (escola estadual agrotécnica) | G73: Investimento | H73: 64000 | I73: Emenda de Bancada (processo seletivo) | J73: Recurso pago | K73: Recurso para a aquisição de implementos agrícolas | L73: Implementos agrícolas entregues a partir de abril de 2021.
A74: 2020 | B74: Encantado | C74: Município | D74: Prefeitura Municipal | E74: 41160009 | F74: Saúde (Custeio - MAC) | G74: Custeio | H74: 150000 | I74: Emenda Individual (processo seletivo) | J74: Recurso pago | K74: Recurso para custeio dos serviços de saúde (Média e Alta Complexidade) | L74: Foram pagos procedimentos especializados para o hospital beneficencia camiliada do sul - hospital santa terezinha de encantado, no mes de maio/2020
A75: 2022 | B75: Erechim | C75: Hospital | D75: Fundação Hospitalar Santa Terezinha | E75: 41160003 | F75: Saúde (Investimento - MAC) | G75: Investimento | H75: 260500 | I75: Emenda Individual | J75: Indicado | K75: Equipamento e material permanente para unidade de atenção especializada.
A76: 2020 | B76: Erechim | C76: Polícia Civil | D76: 11ª Delegacia de Polícia Regional – Erechim | E76: 41160010 | F76: Segurança pública | G76: Investimento | H76: 162142.85 | I76: Emenda individual | J76: Recurso empenhado. Inexigibilidade de licitação aceita pelo Ministério. Recurso pago em 25/04/2022. | K76: Aquisição de Ferramenta Forense para extração, processamento e apoio na análise de dados e informações a partir de plataformas eletrônicas portáteis para a estruturação da 11ª Delegacia de Polícia Regional – Erechim
A77: 2019 | B77: Erechim | C77: Escola Agrotécnica | D77: C.A.E. Ângelo Emílio Grando | E77: 71220005 | F77: Educação (escola estadual agrotécnica) | G77: Investimento | H77: 63000 | I77: Emenda de Bancada (processo seletivo) | J77: Recurso pago | K77: Recurso para a aquisição de implementos agrícolas | L77: Implementos agrícolas entregues a partir de abril de 2021.
A78: 2020 | B78: Erechim | C78: Hospital | D78: Fundação Hospitalar Santa Terezinha | E78: 41160005 | F78: Saúde (Custeio - MAC) | G78: Custeio | H78: 100000 | I78: Emenda Individual (processo seletivo) | J78: Recurso pago | K78: Recurso para custeio dos serviços de saúde (Média e Alta Complexidade) | L78: Aquisição de Luvas de Procedimento, conforme Nota Fiscal 104855 da Stock Med no valor de 99.258,00 e Nota Fiscal 337852 da Cooperativa Central de Cooperativas UNIMED RS no valor de 2.760,00
A79: 2020 | B79: Estância Velha | C79: Corpo de Bombeiros | D79: Corpo de Bombeiros de Estância Velha | E79: 41160012 | F79: Segurança pública | G79: Investimento | H79: 162125 | I79: Emenda individual | J79: Recurso empenhado. Em licitação. | K79: Desencarcerador hidráulico
A80: 2020 | B80: Estância Velha | C80: Hospital | D80: Hospital Municipal Getúlio Vargas | E80: 7122 0006 | F80: Saúde (Custeio - MAC) | G80: Custeio | H80: 60000 | I80: Emenda de Bancada | J80: Recurso pago | K80: Recursos para custeio do combate à COVID-19 (Média e Alta Complexidade)
A81: 2021 | B81: Estância Velha | C81: Hospital | D81: Hospital Municipal Getúlio Vargas | E81: 41160003 | F81: Saúde (Custeio - MAC) | G81: Custeio | H81: 210000 | I81: Emenda individual (processo seletivo) | J81: Recurso indicado via Fundo Estadual de Saúde. Emenda paga, faltando o Fundo transferir os recursos para os hospitais. | K81: Aquisição de um raio-X para o hospital.
A82: 2020 | B82: Esteio | C82: Município | D82: Prefeitura Municipal | E82: 41160001 | F82: Saúde (Custeio - PAB) | G82: Custeio | H82: 100000 | I82: Emenda Individual (processo seletivo) | J82: Recurso pago | K82: Recurso para custeio dos serviços de saúde (Piso de Atenção Básica)
A83: 2020 | B83: Esteio | C83: Município | D83: Prefeitura Municipal | E83: 41160004 | F83: Empreendedorismo, educação e inovação | G83: Misto (custeio e investimento) | H83: 300000 | I83: Emenda Individual (processo seletivo) | J83: Recurso empenhado | K83: Investimento em laboratório de produção criativa (ESPAÇO 4.0), inspirado nos FabLabs do MIT | L83: Processo licitatório da prefeitura encontra-se em análise no Ministério da Mulher.
A84: 2020 | B84: Farroupilha | C84: Hospital | D84: Hospital Beneficente São Carlos | E84: 41160005 | F84: Saúde (Custeio - MAC) | G84: Custeio | H84: 200000 | I84: Emenda Individual (processo seletivo) | J84: Recurso pago | K84: Recurso para custeio dos serviços de saúde (Média e Alta Complexidade) | L84: O recurso foi utilizado para a complementação de pagamento de Serviços de Terceiros - Pessoa Jurídica , especialmente para honorários médicos. O plano de trabalho foi apresentado e aprovado pelo Conselho Municipal de Saúde de Farroupilha, fez parte através de termo Aditivo ao Contrato de Prestação de Serviços 01/2020 que este Hospital mantém com o Município que é Gestão Plena na saúde, e após a aplicação foi realizada a devida prestação de contas, de acordo com as normas estabelecidas pelo Gestor Local de Saúde.
A85: 2022 | B85: Farroupilha | C85: Hospital | D85: Hospital São Carlos | E85: 7120004 | F85: Saúde (Custeio - MAC) | G85: Custeio | H85: 250000 | I85: Emenda de bancada (processo seletivo) | J85: Recurso indicado via Fundo Municipal de Saúde de Farroupilha. | K85: Custeio para o hospital.
A86: 2020 | B86: Feliz | C86: Município | D86: Prefeitura Municipal | E86: 41160009 | F86: Saúde (Custeio - MAC) | G86: Custeio | H86: 100000 | I86: Emenda Individual (processo seletivo) | J86: Recurso pago | K86: Recurso para custeio dos serviços de saúde (Média e Alta Complexidade) | L86: Conforme definido no projeto beneficiado, o recurso foi utilizado junto ao Contrato de Gestão mantido com a Associação de Saúde e Feliz para a manutenção de plantão médico presencial 24 horas no Hospital Schlatter para atendimentos de urgência e emergência, bem como ambulatoriais nos horários em que as Unidades Básicas de Saúde estão fechadas. De tal forma foi custeado a permanência de segundo plantonista médico (presencial) aos finais de semana e feriados, qualificando e agilizando os atendimentos.
A87: 2021 | B87: Feliz | C87: Município | D87: Prefeitura Municipal | E87: 41160004 | F87: Infraestrutura Turística | G87: Investimento | H87: 250000 | I87: Emenda Individual (processo seletivo) | J87: Empenhado | K87: Revitalização da Orla do Rio Caí
A88: 2021 | B88: Flores da Cunha | C88: Corpo de Bombeiros | D88: Corpo de Bombeiros de Flores da Cunha | E88: 41160001 | F88: Segurança pública | G88: Investimento | H88: 333333 | I88: Emenda individual | K88: Ambulância/Resgate tipo C Furgão teto alto
B89: Frederico Westphalen | C89: Brigada Militar | H89: 384370.17 | K89: PICK UP 4X4
A90: 2020 | B90: Garibaldi | C90: Município | D90: Prefeitura Municipal | E90: 41160009 | F90: Saúde (Custeio - MAC) | G90: Custeio | H90: 150000 | I90: Emenda Individual (processo seletivo) | J90: Recurso pago | K90: Recurso para custeio dos serviços de saúde (Média e Alta Complexidade)
A91: 2021 | B91: Giruá | C91: Corpo de Bombeiros | D91: Corpo de Bombeiros de Giruá | E91: 41160001 | F91: Segurança pública | G91: Investimento | H91: 333333 | I91: Emenda individual | K91: Ambulância/Resgate tipo C Furgão teto alto
A92: 2022 | B92: Gramado | C92: Município | D92: Prefeitura Municipal | E92: 41160007 | F92: Ministério do Desenvolvimento Regional | G92: Investimento | H92: 500000 | I92: Emenda Individual | J92: Indicado
A93: 2020 | B93: Gramado | C93: Hospital | D93: Hospital Arcanjo São Miguel | E93: 7122 0006 | F93: Saúde (Custeio - MAC) | G93: Custeio | H93: 50000 | I93: Emenda de Bancada | J93: Recurso pago | K93: Recursos para custeio do combate à COVID-19 (Média e Alta Complexidade)
B94: Gravataí | C94: Polícia Civil | H94: 234954.25 | K94: SUV 118CV
A95: 2020 | B95: Guaíba | C95: Município | D95: Prefeitura Municipal | E95: 41160009 | F95: Saúde (Custeio - PAB) | G95: Custeio | H95: 150000 | I95: Emenda Individual (processo seletivo) | J95: Recurso pago | K95: Recurso para custeio dos serviços de saúde (Piso de Atenção Básica)
A96: 2019 | B96: Guaporé | C96: Escola Agrotécnica | D96: Escola Estadual Técnica Agrícola Guaporé | E96: 71220005 | F96: Educação (escola estadual agrotécnica) | G96: Investimento | H96: 50000 | I96: Emenda de Bancada (processo seletivo) | J96: Recurso pago | K96: Recurso para a aquisição de implementos agrícolas | L96: Implementos agrícolas entregues a partir de abril de 2021.
A97: 2019 | B97: Guarani das Missões | C97: Escola Agrotécnica | D97: E.E.T. Guaramano | E97: 71220005 | F97: Educação (escola estadual agrotécnica) | G97: Investimento | H97: 78705.88 | I97: Emenda de Bancada (processo seletivo) | J97: Recurso pago | K97: Recurso para a aquisição de implementos agrícolas | L97: Implementos agrícolas entregues a partir de abril de 2021.
A98: 2020 | B98: Harmonia | C98: Município | D98: Prefeitura Municipal | E98: 41160001 | F98: Saúde (Custeio - PAB) | G98: Custeio | H98: 100000 | I98: Emenda Individual (processo seletivo) | J98: Recurso pago | K98: Recurso para custeio dos serviços de saúde (Piso de Atenção Básica) | L98: O recurso será aplicado em 2021, tendo em virtude de possuir alguma parte neste ano de 2019. Assim, de forma mais justa e uniforme, a administração municipal entendeu da melhor aplicação no próximo ano.
A99: 2019 | B99: Igrejinha | C99: Hospital | D99: Hospital Bom Pastor | E99: 71220009 | F99: Saúde (Custeio - MAC) | G99: Custeio | H99: 250000 | I99: Emenda de Bancada | J99: Recurso pago | K99: Recurso para custeio dos serviços de saúde (Média e Alta Complexidade) | L99: A Associação Beneficente de Igrejinha (CNPJ 87.369.799/0001-76) está utilizando parte do recurso recebido em procedimentos odontológicos para pacientes especiais, que conforme plano de trabalho, o valor total é de 172.834,00 (100 procedimentos) e o valor já utilizado está em 133.082,18, restando apenas 23 procedimentos para conclusão. O restante do valor da emenda foi utilizado para complementar folha de pagamento ( 77.166,00). Em anexo colocamos o relatório de procedimentos odontológicos até então realizados e demonstrativo de folha de pagamento no mês de dezembro de 2019.
A100: 2020 | B100: Igrejinha | C100: Hospital | D100: Hospital Bom Pastor | E100: 7122 0006 | F100: Saúde (Custeio - MAC) | G100: Custeio | H100: 50000 | I100: Emenda de Bancada | J100: Recurso pago | K100: Recursos para custeio do combate à COVID-19 (Média e Alta Complexidade)
...

Sheet Região Lorentz
B1: Município | C1: Beneficiário | D1: Instituição | E1: Nº da Emenda | F1: Área de alocação | G1: Modalidade | H1: Valores destinados | I1: Tipo da emenda | J1: Situação | K1: Informações adicionais | L1: Endereço | M1: Como foi executado | N1: Arquivos | O1: Código
A2: 2021 | B2: Dois Irmãos | C2: Município | E2: 41160006 | H2: 2693000 | I2: Emenda Individual
A3: 2022 | F3: SAÚDE | H3: 2250000 | I3: Emenda de bancada | J3: Indicado
A4: 2022 | D4: Posto de Saúde na Vila Mário Quintana (com Lasier Martins) | H4: 250000 | I4: Emenda de bancada | J4: Indicado
A5: 2022 | D5: RS-211 até RS-324 (Campinas do Sul e Ronda Alta) | H5: 500000 | I5: Emenda de bancada | J5: Indicado
A6: 2022 | B6: Tramandaí | D6: Ponte de Tramandaí-RS | H6: 500000 | I6: Emenda de bancada | J6: Indicado
A7: 2022 | D7: BR 448 | H7: 1000000 | I7: Emenda de bancada | J7: Indicado | K7: adiamento por conta da covid. dia 25 cadastro no ministério
A8: 2022 | D8: PRF | H8: 500000 | I8: Emenda de bancada | J8: Indicado
A9: 2022 | B9: A definir | C9: Secretaria de Segurança Pública | D9: Brigada Militar | E9: 41160001 | F9: Segurança Pública | H9: 1238648.8 | I9: Emenda Individual | J9: Indicado | K9: Compra de duas SUV 118 CV (preço: 234.954,25/un) e duas PICK UP 4x4 ( 384.370,17/un)
A10: 2022 | B10: A definir | C10: Secretaria de Segurança Pública | D10: Polícia Civil | E10: 41160001 | F10: Segurança Pública | H10: 1238648.8 | I10: Emenda Individual | J10: Indicado | K10: Compra de duas SUV 118 CV (preço: 234.954,25/un) e duas PICK UP 4x4 ( 384.370,17/un)
A11: 2022 | B11: A definir | C11: Secretaria de Segurança Pública | D11: Corpo de Bombeiros | E11: 41160001 | F11: Segurança Pública | H11: 1089232.9 | I11: Emenda Individual | J11: Indicado | K11: Compra de três SUV 118 CV (preço: 234.954,25/un) e uma PICK UP 4x4 ( 384.370,17/un)
A12: 2022 | B12: Bagé | D12: Fundação Universidade Federal do Pampa | E12: 41160004 | H12: 350000 | I12: Emenda Individual | J12: Indicado
A13: 2022 | B13: Porto Alegre | D13: Universidade Federal do Rio Grande Do Sul | E13: 41160006 | H13: 350000 | I13: Emenda Individual | J13: Indicado
A14: 2022 | B14: Rio Grande | D14: Comando da Marinha Rio Grande | E14: 41160010 | H14: 350000 | I14: Emenda Individual | J14: Indicado
A15: 2022 | B15: Porto Alegre | D15: Comando do Exército | E15: 41160009 | H15: 300000 | I15: Emenda Individual | J15: Indicado
A16: 2022 | B16: Santa Maria | D16: Comando da Aeronáutica Brasília | E16: 41160008 | H16: 300000 | I16: Emenda Individual | J16: Indicado
A17: 2022 | B17: Ivoti | C17: Município | D17: Prefeitura Municipal | E17: 41160007 | F17: Ministério do Desenvolvimento Regional | H17: 1139365 | I17: Emenda Individual | J17: Indicado
A18: 2022 | B18: Gramado | C18: Município | D18: Prefeitura Municipal | E18: 41160007 | F18: Ministério do Desenvolvimento Regional | H18: 500000 | I18: Emenda Individual | J18: Indicado
A19: 2022 | B19: Nova Hartz | C19: Município | D19: Prefeitura Municipal | E19: 41160007 | F19: Ministério do Desenvolvimento Regional | H19: 500000 | I19: Emenda Individual | J19: Indicado
A20: 2022 | B20: Passo Fundo | D20: Fundação Hospitalar Oftalmológica Universitária Lions | E20: 41160003 | F20: Saúde (Investimento - MAC) | G20: Investimento | H20: 720000 | I20: Emenda Individual | J20: Indicado
A21: 2022 | B21: Rodeio Bonito | D21: Associação Hospitalar São Jose. | E21: 41160003 | F21: Saúde (Investimento - MAC) | G21: Investimento | H21: 250000 | I21: Emenda Individual | J21: Indicado
A22: 2022 | B22: Sapiranga | D22: Fundo Municipal de Saúde | E22: 41160003 | F22: Saúde (Investimento - MAC) | G22: Investimento | H22: 650000 | I22: Emenda Individual | J22: Indicado
A23: 2022 | B23: Campo Bom | D23: Fundo Municipal de Saúde | E23: 41160003 | F23: Saúde (Investimento - MAC) | G23: Investimento | H23: 250000 | I23: Emenda Individual | J23: Indicado
A24: 2022 | B24: Canoas | D24: Fundo Municipal de Saúde | E24: 41160003 | F24: Saúde (Investimento - MAC) | G24: Investimento | H24: 610000 | I24: Emenda Individual | J24: Indicado
A25: 2022 | B25: Novo Hamburgo | D25: Fundo Municipal de Saúde | E25: 41160003 | F25: Saúde (Investimento - MAC) | G25: Investimento | H25: 1000000 | I25: Emenda Individual | J25: Indicado
A26: 2022 | B26: Passo Fundo | D26: Fundo Municipal de Saúde Passo | E26: 41160003 | F26: Saúde (Investimento - MAC) | G26: Investimento | H26: 135000 | I26: Emenda Individual | J26: Indicado
A27: 2022 | B27: Porto Alegre | D27: Sociedade Sulina Divina Providencia | E27: 41160003 | F27: Saúde (Investimento - MAC) | G27: Investimento | H27: 569347 | I27: Emenda Individual | J27: Indicado
A28: 2022 | B28: Marau | D28: Associação Hospitalar Beneficente de Marau | E28: 41160003 | F28: Saúde (Investimento - MAC) | G28: Investimento | H28: 210000 | I28: Emenda Individual | J28: Indicado
A29: 2022 | B29: Porto Alegre | C29: Hospital | D29: Hospital São Lucas da PUCRS | E29: 41160003 | F29: Saúde (Investimento - MAC) | G29: Investimento | H29: 776319 | I29: Emenda Individual | J29: Indicado
A30: 2022 | B30: Pejuçara | C30: Hospital | D30: Associação Hospitalar Rio Branco De Pejuçara | E30: 41160003 | F30: Saúde (Investimento - MAC) | G30: Investimento | H30: 187000 | I30: Emenda Individual | J30: Indicado
A31: 2022 | B31: Erechim | C31: Hospital | D31: Fundação Hospitalar Santa Terezinha | E31: 41160003 | F31: Saúde (Investimento - MAC) | G31: Investimento | H31: 260500 | I31: Emenda Individual | J31: Indicado
A32: 2022 | B32: Serafina Corrêa | C32: Hospital | D32: Hospital Nossa Senhora do Rosário | E32: 41160003 | F32: Saúde (Investimento - MAC) | G32: Investimento | H32: 300000 | I32: Emenda Individual | J32: Indicado
A33: 2022 | B33: Três Coroas | C33: Hospital | D33: Fundação Hospitalar Dr Oswaldo Diesel | E33: 41160003 | F33: Saúde (Investimento - MAC) | G33: Investimento | H33: 367500 | I33: Emenda Individual | J33: Indicado
A34: 2022 | B34: Morro Redondo | C34: Hospital | D34: Hospital Dr Ernesto Mauricio Arndt | E34: 41160003 | F34: Saúde (Investimento - MAC) | G34: Investimento | H34: 100000 | I34: Emenda Individual | J34: Indicado
A35: 2022 | B35: Pelotas | C35: Hospital | D35: Santa Casa De Misericórdia de Pelotas | E35: 41160003 | F35: Saúde (Investimento - MAC) | G35: Investimento | H35: 150000 | I35: Emenda Individual | J35: Indicado
A36: 2022 | B36: Porto Alegre | C36: Hospital | D36: Irmandade da Santa Casa de Misericórdia de Porto Alegre | E36: 41160003 | F36: Saúde (Investimento - MAC) | G36: Investimento | H36: 500000 | I36: Emenda Individual | J36: Indicado
A37: 2022 | B37: Quaraí | C37: Hospital | D37: Fundação Hospital de Caridade de Quarai | E37: 41160003 | F37: Saúde (Investimento - MAC) | G37: Investimento | H37: 117000 | I37: Emenda Individual | J37: Indicado
A38: 2022 | B38: Rio Grande | C38: Hospital | D38: Associação de Caridade Santa Casa de Rio Grande | E38: 41160003 | F38: Saúde (Investimento - MAC) | G38: Investimento | H38: 300000 | I38: Emenda Individual | J38: Indicado
A39: 2022 | B39: Santa Bárbara do Sul | C39: Hospital | D39: Hospital Santa Barbara Beneficente | E39: 41160003 | F39: Saúde (Investimento - MAC) | G39: Investimento | H39: 200000 | I39: Emenda Individual | J39: Indicado
A40: 2022 | B40: Sinimbu | C40: Hospital | D40: Hospital Beneficente Sinimbu | E40: 41160003 | F40: Saúde (Investimento - MAC) | G40: Investimento | H40: 100000 | I40: Emenda Individual | J40: Indicado
... A50: 2022 | B50: Terra de Areia | C50: Município | D50: Prefeitura Municipal | E50: 41160002 | F50: Saúde (Custeio - PAB) | G50: Custeio | H50: 100139 | I50: Emenda Individual | J50: Indicado
A51: 2022 | B51: Agudo | C51: Município | D51: Prefeitura Municipal | E51: 41160005 | F51: Infraestrutura Turística | G51: Investimento | H51: 250000 | I51: Emenda Individual (processo seletivo) | J51: Indicado | K51: Volkslager como centro de comercialização de produtos gastronômicos turísticos | N51: https://drive.google.com/open?id=1zq7P9qIDTVlJyDRaaBBAHabc1oyfsMBz
A52: 2022 | B52: Candelária | C52: Município | D52: Prefeitura Municipal | E52: 41160005 | F52: Infraestrutura Turística | G52: Investimento | H52: 250000 | I52: Emenda Individual (processo seletivo) | J52: Indicado | K52: Colocação de escada no Morro Botucaraí e construção de dois sanitários aos pés do Morro. | N52: https://drive.google.com/open?id=1gyEtnodEnV2Yubp0aaJGVKTmxzIALV6x
A53: 2022 | B53: São Sebastião do Caí | C53: Município | D53: Prefeitura Municipal | E53: 41160005 | F53: Infraestrutura Turística | G53: Investimento | H53: 250000 | I53: Emenda Individual (processo seletivo) | J53: Indicado | K53: Revitalização do Cais do Porto (paisagismo, sinalização turística, execução de calçadas, instalação de bancos, mesas, pergolados, construção de mirante). | N53: https://drive.google.com/open?id=1wq_x6tt3VKDwkhAVPvKnZkZdbhOMulk5
A54: 2022 | B54: Maratá | C54: Município | D54: Prefeitura Municipal | E54: 41160005 | F54: Infraestrutura Turística | G54: Investimento | H54: 250000 | I54: Emenda Individual (processo seletivo) | J54: Indicado | K54: Execução de faixa compartilhada destinada à circulação de pedestres e ciclistas, com acessibilidade e iluminação (530 metros de extensão que liga o centro da cidade até a Cachoeira Maratá). | N54: https://drive.google.com/open?id=1mwHnDPfOMAIzQmPg6HKfHInY9zAZrV2V
A55: 2022 | B55: Derrubadas | C55: Município | D55: Prefeitura Municipal | E55: 41160005 | F55: Infraestrutura Turística | G55: Investimento | H55: 250000 | I55: Emenda Individual (processo seletivo) | J55: Indicado | K55: Instalação de pontos de apoio e centro regional de atendimento ao turista (rotas de cicloturismo e caminhada). | N55: https://drive.google.com/open?id=1wq_x6tt3VKDwkhAVPvKnZkZdbhOMulk5
A56: 2022 | B56: Morro Reuter | C56: Município | D56: Prefeitura Municipal | E56: 41160005 | F56: Infraestrutura Turística | G56: Investimento | H56: 250000 | I56: Emenda Individual (processo seletivo) | J56: Indicado | K56: Revitalização da Rua Independência (365m de extensão) - substituição dos bloquetos por pedras regulares, bem como a substituição do passeio público. | N56: https://drive.google.com/open?id=1Y2owD1GGe7xGZfQ1c5OB0f5XRp9En0Nt
A57: 2021 | B57: A definir | C57: Polícia Civil | D57: Polícia Civil | E57: 71220009 | F57: Segurança Pública | G57: Investimento | H57: 700000 | I57: Emenda de Bancada | K57: 2 viaturas pick up ostensiva com cela | N57: Aquisição de 2 viaturas pick up ostensiva com cela. O valor total da emenda é de 1.650.930,54 que inclui 05 viaturas discretas tipo Sedan. Com contrapartida de 33.692,46. Proposta 028239: https://drive.google.com/file/d/13UJPbFK0izb7oc7oPflF1d60qA_i3jsW/view?usp=sharing
A58: 2021 | B58: Rio Pardo | C58: Corpo de Bombeiros | D58: Corpo de Bombeiros | E58: 71220009 | F58: Segurança Pública | G58: Investimento | H58: 330000 | I58: Emenda de Bancada | K58: 01 ambulância/resgate tipo C furgão teto alto. | N58: Aquisição de 01 viatura de resgate e salvamento. Com contrapartida 33.966,66. Valor total 353.966,66. Proposta - 028534: https://drive.google.com/file/d/1z0Sm5HAnkqAcRLsVO6CusjDhOGmRDcIF/view?usp=sharing
A59: 2021 | B59: A definir | C59: Brigada Militar | D59: Brigada Militar | E59: 71220009 | F59: Segurança Pública | G59: Investimento | H59: 358785 | I59: Emenda de Bancada | K59: 09 motocicletas caracterizadas | N59: Viatura caracterizada tipo motocicleta. Valor total (17 motocicletas) 665.691,61. Proposta - 028449: https://drive.google.com/file/d/1WlGh1kHSwuugd7ZkBZBGgSXTxeI_v28C/view?usp=sharing
A60: 2021 | B60: A definir | C60: Brigada Militar | D60: Brigada Militar | E60: 71220009 | F60: Segurança Pública | G60: Investimento | H60: 296745.33 | I60: Emenda de Bancada | K60: 04 Viatura ostensiva tipo pick up | N60: Aquisição 04 viatura caracterizada tipo PickUp. Valor total 1.280.468,00. Proposta 028449 : https://drive.google.com/file/d/1WlGh1kHSwuugd7ZkBZBGgSXTxeI_v28C/view?usp=sharing
A61: 2021 | B61: Ajuricaba | C61: Hospital | D61: Associação Hospitalar Beneficente Ajuricaba | E61: 41160002 | F61: Saúde (Investimento - MAC) | G61: Investimento | H61: 100000 | I61: Emenda individual (processo seletivo) | J61: Recurso empenhado. | K61: Grupo-gerador movido a diesel, com potência mínima de 100 KVA, para manter em funcionamento ininterrupto os equipamentos essenciais ao suporte de pacientes do Hospital. Assegura-se, assim, o abastecimento de energia em momentos de desabastecimento, mantendo a qualidade e segurança dos atendimentos. | L61: R. Vitório Sechinato, 50, Ajuricaba, RS, 98750-000 | N61: Proposta 033437/2021 - https://drive.google.com/file/d/1anFh9yryznLscxrEOzRV_Db5y8Px7OY8/view?usp=sharing | O61: 9
A62: 2021 | B62: Arambaré | C62: Município | D62: Prefeitura Municipal | E62: 41160004 | F62: Infraestrutura Turística | G62: Investimento | H62: 250000 | I62: Emenda Individual (processo seletivo) | J62: Empenhado | K62: Iluminação da orla da praia da Costa Doce | L62: Costa Doce Arambaré - RS | M62: Proposta Aceita. Plano de Trabalho em Análise. | N62: Resultado do processo seletivo: http://marcelvanhattem.com.br/2020/wp-content/uploads/2021/09/EMENDA-TURISMO-2021.pdf | O62: 116
A63: 2020 | B63: Araricá | C63: Município/hospital mais próximo | D63: Prefeitura/Hospital Sapiranga | E63: 7122 0006 | F63: Saúde (Custeio - MAC) | G63: Custeio | H63: 50000 | I63: Emenda de bancada | J63: Recurso pago | K63: Recursos para custeio do combate à COVID-19 (Média e Alta Complexidade). Como o município não possuía hospital para atender pacientes de COVID-19, e como o recurso era destinado a hospitais, a emenda foi alocada no hospital de referência do município. Prefeitos e hospitais foram comunicados. | L63: Av. José Antônio de Oliveira Neto, 355 - Centro, Araricá - RS, 93880-000 | O63: 104
A64: 2020 | B64: Arroio do Meio | C64: Município | D64: Prefeitura Municipal | E64: 41160001 | F64: Saúde (Custeio - PAB) | G64: Custeio | H64: 100000 | I64: Emenda Individual (processo seletivo) | J64: Recurso pago | K64: Recurso para custeio dos serviços de saúde (Piso de Atenção Básica) | L64: R. Dr. João Carlos Machado, 665 - Centro, Arroio do Meio - RS, 95940-000 | O64: 103
A65: 2020 | B65: Bagé | C65: Hospital | D65: Santa Casa de Caridade de Bagé | E65: 41160005 | F65: Saúde (Custeio - MAC) | G65: Custeio | H65: 100000 | I65: Emenda Individual (processo seletivo) | J65: Recurso pago | K65: Recurso para custeio dos serviços de saúde (Média e Alta Complexidade) | L65: R. Carlos Mangabeira, 307 - Centro, Bagé - RS, 96400-490 | N65: https://drive.google.com/file/d/16Ol1p7pGgiKY7zt4K0eY4MmtR6ITvWXw/view?usp=sharing | O65: 24
A66: 2020 | B66: Bagé | C66: Polícia Civil | D66: 9ª Delegacia de Polícia Regional – Bagé | E66: 41160010 | F66: Segurança pública | G66: Investimento | H66: 12142.85 | I66: Emenda individual | J66: Recurso empenhado. Inexigibilidade de licitação aceita pelo Ministério. Recurso pago em 25/04/2022 | K66: Aquisição de Ferramenta Forense para extração, processamento e apoio na análise de dados e informações a partir de plataformas eletrônicas portáteis para estruturar a 9ª Delegacia de Polícia Regional do Interior - Bagé. | L66: R. Gen. Flores da Cunha, 56 - Popular, Bagé - RS, 96400-350 | N66: Na aquisição de 01 ferramenta de extração de dados o deputado Marcel contibuiu com 12.142,85. Outro parlamentar (emenda 20980007) com 150.000,00. Proposta 2045/2020 - https://drive.google.com/file/d/1dA-xI-LIxcR9fUfK2Teoul4ATJp55IX9/view?usp=sharing | O66: 125
A67: 2020 | B67: Barão | C67: Município | D67: Prefeitura Municipal | E67: 41160001 | F67: Saúde (Custeio - PAB) | G67: Custeio | H67: 100000 | I67: Emenda Individual (processo seletivo) | J67: Recurso pago | K67: Recurso para custeio dos serviços de saúde (Piso de Atenção Básica) | L67: R. da Estação, 1085 - Operário, Barão - RS, 95730-000 | M67: . | N67: . | O67: 82
A68: 2021 | B68: Barros Cassal | C68: Município | D68: Prefeitura Municipal | E68: 41160002 | F68: Saúde (Investimento - MAC) | G68: Investimento | H68: 245000 | I68: Emenda individual (processo seletivo) | J68: Proposta aprovada para pagamento. | K68: Van para implantar o transporte sanitário eletivo, beneficiando a população de baixa renda que necessita deslocar-se a hospitais da região para atendimentos com médicos especializados e realização de procedimentos de maior complexidade. Recurso enviado via Fundo Municipal de Saúde de Barros Cassal. | L68: Av. Maurício Cardoso, 1177, Barros Cassal - RS, 99360-000 | N68: Propostas no Fundo Nacional de Saúde - https://drive.google.com/file/d/1lTmWUQJKG5rGSM0vQkXaZuJ4dXAvvvgM/view?usp=sharing e https://drive.google.com/file/d/1n91ehuvh0UbH3XWnALEDOEGLtv6QBzdg/view?usp=sharing
A69: 2020 | B69: Bento Gonçalves | C69: Hospital | D69: Hospital Tacchini | E69: 41160005 | F69: Saúde (Custeio - MAC) | G69: Custeio | H69: 100000 | I69: Emenda Individual (processo seletivo) | J69: Recurso pago | K69: Recurso para custeio dos serviços de saúde (Média e Alta Complexidade) | L69: R. Dr. José Mário Mônaco, 358 - Centro, Bento Gonçalves - RS, 95700-068 | M69: Em atenção ao Of. n. 135/2020, de 26/11/2020, e com base no Projeto apresentado através do e-mail datado de 27/07/2020 (leitura realizada em 28/07/2020), com o valor de 100.000,00 recebido através de Emenda Parlamentar - Portaria GM/MS nº 679/2020, de autoria do Deputado Federal Marcel Van Hattem, foi possível reduzir o indicador percentual de tempo de espera cirúrgica acima de 60 dias, de 54,00% para 30,33% , ao mesmo tempo em que, foi possível ampliar o atendimento e beneficiar na realização de tratamento cirúrgico em oncologia de 26 novos pacientes oncológicos, que ingressaram na UNACON do Hospital Tacchini (Bento Gonçalves - RS), período de agosto, setembro e outubro de 2020, conforme as seguintes AIH's: Agosto/2020 - 4320104280140; 4320105042715; 4320105069049; 4320105808865; 4320103526959; 4320103526937; 4320103527400 / Setembro/2020 - 4320104281537; 4320104281548; 4320104281890; 4320104283891; 4320104281603; 4320104277907; 4320104281559 / Outubro/2020 - 4320104284353; 4320106584453; 4320106586796; 4320107313566; 4320107346115; 4320105048699; 4320105048534; 4320105809900; 4320105048370; 4320105822087; 4320104286069; 4320105050635. | N69: https://drive.google.com/file/d/1W01r2obXUbZWJNeB6SXTmd1kmFOVsBhl/view?usp=sharing | O69: 25
A70: 2021 | B70: Bento Gonçalves | C70: Hospital | D70: Associação Dr. Bartholomeu Tacchini - Hospital Tacchini | E70: 41160002 | F70: Saúde (Investimento - MAC) | G70: Investimento | H70: 140000 | I70: Emenda individual (processo seletivo) | J70: Recurso empenhado. | K70: Aquisição e instalação de duas novas máquinas de hemodiálise para o tratamento de pacientes nefrológicos crônicos e agudos através do SUS. O hospital atende pacientes de oito municípios da Serra Gaúcha. | L70: R. Gen. Osório, 265 - Centro, Bento Gonçalves - RS, 95700-000 | N70: Proposta 037034/2021 - https://drive.google.com/file/d/1c32Eq75I5Pz5TeSqoui-K2Zi3_Qtpllr/view?usp=sharing | O70: 4
A71: 2021 | B71: Bento Gonçalves | C71: Hospital Municipal | D71: Complexo Hospitalar de Bento Gonçalves | E71: 41160003 | F71: Saúde (Custeio - MAC) | G71: Custeio | H71: 1000000 | I71: Emenda individual (processo seletivo) | J71: Recurso pago. | K71: Instalação de energia fotovoltaica no Complexo de Saúde do Trabalhador, que compreende laboratório, centro de imagens, UPA 24 horas, farmácia e 40 leitos. O Complexo gastou, em 2020, 400.000,00 com energia elétrica. A usina de energia solar fotovoltaica, com a instalação de 811 placas de 330W, pretende reduzir em 70% o valor do gasto com energia, uma economia de 26.000,00 mensais. O valor economizado será revertido para a ampliação do atendimento da população que procura o complexo público de saúde. Recurso enviado via Fundo Municipal de Saúde de Bento Gonçalves. | L71: R. Sen. Alberto Pasqualine, 186, Bento Gonçalves - RS, 95700-000 | N71: Proposta no Fundo Nacional de Saúde 36000357013202100
A72: 2020 | B72: Bom Princípio | C72: Município | D72: Prefeitura Municipal | E72: 41160001 | F72: Saúde (Custeio - PAB) | G72: Custeio | H72: 100000 | I72: Emenda Individual (processo seletivo) | J72: Recurso pago | K72: Recurso para custeio dos serviços de saúde (Piso de Atenção Básica) | L72: Av. Guilherme Winter, 65 - Centro, Bom Princípio - RS, 95765-000 | O72: 76
A73: 2019 | B73: Bom Progresso | C73: Escola Agrotécnica | D73: E.T.E. Celeiro | E73: 71220005 | F73: Educação (escola estadual agrotécnica) | G73: Investimento | H73: 63000 | I73: Emenda de Bancada (processo seletivo) | J73: Recurso pago | K73: Recurso para a aquisição de implementos agrícolas | L73: Br 468 - Km 87.9, Bom Progresso - RS, 98575-000 | M73: Implementos agrícolas entregues a partir de abril de 2021. | O73: 4
A74: 2020 | B74: Boqueirão do Leão | C74: Município | D74: Prefeitura Municipal | E74: 41160001 | F74: Saúde (Custeio - PAB) | G74: Custeio | H74: 67500 | I74: Emenda Individual (processo seletivo) | J74: Recurso pago | K74: Recurso para custeio dos serviços de saúde (Piso de Atenção Básica) | L74: R. Sinimbú, 644 - Centro, Boqueirão do Leão - RS, 95920-000 | O74: 77
A75: 2020 | B75: Brochier | C75: Município | D75: Prefeitura Municipal | E75: 41160001 | F75: Saúde (Custeio - PAB) | G75: Custeio | H75: 100000 | I75: Emenda Individual (processo seletivo) | J75: Recurso pago | K75: Recurso para custeio dos serviços de saúde (Piso de Atenção Básica) | L75: R. Guilherme Hartman, 260, Brochier - RS, 95790-000 | M75: 1) Pagamento de parte das despesas com Serviços Médicos e profissionais de saúde, através do Consórcio dos Municípios do Vale do Caí - CIS/CAI conforme empenhos a seguir relacionados: - 3818/2020 - no valor de 20.993,50; - 3494/2020 - no valor de 20.553,00; - 3218/2020 - no valor de 9.344,00; - 3216/2020 - no valor de 6.230,00; - 2928/2020 - no valor de 13.333,00; - 2926/2020 - no valor de 9.065,00; - 2587/2020 - no valor de 6.722,00; - 2580/2020 - no valor de 6.610,00; - 2579/2020 - no valor de 41.552,00; - 2237/2020 - no valor de 42.754,00; Trata esta prestação de contas de informação complementar à prestação de contas enviada na data de ontem, no intuito de esclarecer que os recursos aplicados serviram para ampliar o horário de atendimento no posto de saúde da sede do Município, que ocorre então das 7h da manhã até às 21h ininterruptamente. Com pode ser observado os recursos servem para custear parte da contratação de pessoal necessário para possibilitar o atendimento estendido no posto de saúde. | N75: https://drive.google.com/file/d/1W01r2obXUbZWJNeB6SXTmd1kmFOVsBhl/view?usp=sharing | O75: 78
A76: 2020 | B76: Camaquã | C76: Brigada Militar | D76: Brigada Militar de Camaquã | F76: Segurança pública | G76: Investimento | H76: 81280 | I76: Emenda de Bancada | J76: Em licitação | K76: Coletes balísticos e pistolas para o contingente da Brigada Militar | L76: R. Maj. Lúcio Meireles, 788 - Olaria, Camaquã - RS, 96180-000 | M76: Material em processo licitatório pela Secretaria de Segurança Pública do Rio Grande do Sul | O76: 113
A77: 2020 | B77: Cambará do Sul | C77: Hospital | D77: Fundação Hospitalar São José de Cambará do Sul | E77: 7122 0006 | F77: Saúde (Custeio - MAC) | G77: Custeio | H77: 174741 | I77: Emenda de Bancada | J77: Recurso pago | K77: Recursos para custeio do combate à COVID-19 (Média e Alta Complexidade) | L77: R. Padre João Paza, 315 - Centro, Cambará do Sul - RS, 95480-000 | O77: 72
A78: 2020 | B78: Campo Bom | C78: Hospital | D78: Hospital de Campo Bom Dr. Lauro Reus | E78: 7122 0006 | F78: Saúde (Custeio - MAC) | G78: Custeio | H78: 100000 | I78: Emenda de Bancada | J78: Recurso pago | K78: Recursos para custeio do combate à COVID-19 (Média e Alta Complexidade) | L78: R. Osvaldo Cruz, 116 - E, Campo Bom - RS, 93700-000 | O78: 73
A79: 2020 | B79: Canela | C79: Hospital | D79: Hospital de Caridade de Canela | E79: 7122 0006 | F79: Saúde (Custeio - MAC) | G79: Custeio | H79: 50000 | I79: Emenda de Bancada | J79: Recurso pago | K79: Recursos para custeio do combate à COVID-19 (Média e Alta Complexidade) | L79: R. Visc. de Mauá, 143 - Centro, Canela - RS, 95680-000 | O79: 74
A80: 2020 | B80: Canela | C80: Município | D80: Prefeitura Municipal | E80: 41160001 | F80: Saúde (Custeio - PAB) | G80: Custeio | H80: 67500 | I80: Emenda Individual (processo seletivo) | J80: Recurso pago | K80: Recurso para custeio dos serviços de saúde (Piso de Atenção Básica) | L80: Rua Dona Carlinda, 455 - Centro, Canela - RS, 95680-000 | O80: 83
A81: 2020 | B81: Canoas | C81: Hospital | D81: Hospital Universitário de Canoas | E81: 41160005 | F81: Saúde (Custeio - MAC) | G81: Custeio | H81: 150.000,00 / 200.000,00 | I81: Emenda Individual | J81: Recurso pago | K81: Recurso para Implemento Mac | L81: Av. Farroupilha, 8001 - São José, Canoas - RS | M81: Por se tratar de recursos para INCREMENTO MAC, os mesmos foram repassados para os CNES que foram cadastrados no sistema do FNS(Hospital Universitário e Hospital Nossa Senhora da Graças). | O81: 29
A82: 2020 | B82: Canoas | C82: Hospital | D82: Hospital Nossa Senhora das Graças | E82: 41160005 | F82: Saúde (Custeio - MAC) | G82: Custeio | H82: 50000 | I82: Emenda Individual | J82: Recurso pago | K82: Recurso para Implemento Mac | L82: Av. Santos Ferreira, 1864 - Mal. Rondon, Canoas - RS, 92030-000 | M82: Após cumprimentá-lo, vimos através desta, em resposta ao ofício de n. 137/2020, prestar informações atualizadas sobre o recurso financeiro destinado ao HNSG, em razão de emenda parlamentar impositiva individual de nº 41160005, na área da saúde (custeio) no Orçamento Geral da União 2020, no valor de 50.000,00 (cinqüenta mil reais). Primeiramente, insta apontar que o recurso em questão restou aplicado no Fundo Municipal de Saúde do Município de Canoas/RS, porém, com o não atingimento das metas do Plano Operativo do ano corrente, tais verbas não foram repassadas ao Hospital. A instituição destinatária da emenda parlamentar esteve, durante todo o ano de 2020, em estado crítico financeiro e assistencial, de forma tão grave que desencadeou a declaração de Requisição Administrativa pela Prefeitura Municipal de Canoas, através do Decreto nº 263, de 23 de outubro de 2020, como forma de tentativa de reversão deste quadro. Por isso, apesar de não ter observado o Plano Operativo de 2020 em sua integralidade, tem chances reais e concretas de fazê-lo em 2021, em razão do advento da nova diretoria nomeada pelo Poder Público Municipal, bem como por conta da ampliação de previsão de procedimentos e serviços à população Canoense no novo Plano Operativo. Com isso, haverá, então, o repasse dos recursos financeiros do Fundo Municipal da Saúde ao nosocômio, e a efetiva aplicação destes, possibilitando a prestação de contas requerida. | N82: https://drive.google.com/file/d/1SM5ISknl3pfK9h0Sa2isnorQbK9F32Td/view?usp=sharing | O82: 30
A83: 2020 | B83: Capão Bonito do Sul | C83: Município/hospital mais próximo | D83: Prefeitura/Hospital São Paulo de Lagoa Vermelha | E83: 7122 0006 | F83: Saúde (Custeio - MAC) | G83: Custeio | H83: 50000 | I83: Emenda de bancada OGU 2020 | J83: Recurso pago | K83: Recursos para custeio do combate à COVID-19 (Média e Alta Complexidade). Como o município não possuía hospital para atender pacientes de COVID-19, e como o recurso era destinado a hospitais, a emenda foi alocada no hospital de referência do município. Prefeitos e hospitais foram comunicados. | L83: R. Arthur Feijó, 375 - Centro, Capão Bonito do Sul - RS, 95308-000 | O83: 111
A84: 2019 | B84: Carazinho | C84: Escola Agrotécnica | D84: E.E.E.P. de Carazinho | E84: 71220005 | F84: Educação (escola estadual agrotécnica) | G84: Investimento | H84: 59000 | I84: Emenda de Bancada (processo seletivo) | J84: Recurso pago | K84: Recurso para a aquisição de implementos agrícolas | L84: BR-285, 210, Carazinho - RS, 99500-000 | M84: Implementos agrícolas entregues a partir de abril de 2021. | O84: 5
A85: 2020 | B85: Carazinho | C85: Hospital | D85: Hospital Comunitário de Carazinho | E85: 7122 0006 | F85: Saúde (Custeio - MAC) | G85: Custeio | H85: 50000 | I85: Emenda de Bancada | J85: Recurso pago | K85: Recursos para custeio do combate à COVID-19 (Média e Alta Complexidade) | L85: R. Gen. Câmara, 70 - Centro, Carazinho - RS, 99500-000 | O85: 75
A86: 2020 | B86: Carlos Barbosa | C86: Município | D86: Prefeitura Municipal | E86: 41160001 | F86: Saúde (Custeio - PAB) | G86: Custeio | H86: 100000 | I86: Emenda Individual (processo seletivo) | J86: Recurso pago | K86: Recurso para custeio dos serviços de saúde (Piso de Atenção Básica) | L86: R. Assis Brasil, 11 - Centro, Carlos Barbosa - RS, 95185-000 | O86: 84
A87: 2021 | B87: Carlos Barbosa | C87: Hospital | D87: Hospital São Roque | E87: 41160003 | F87: Saúde (Custeio - MAC) | G87: Custeio | H87: 400000 | I87: Emenda individual (processo seletivo) | J87: Recurso pago. | K87: Instalação de um gerador fotovoltaico com capacidade de 10.800 kW/mês. O hospital gastou, em 2020, 260.000,00 com energia elétrica. O projeto irá reduzir em 40% a energia consumida, produzindo uma economia, no longo prazo (em 20 anos e considerando uma inflação de 5% na energia ao ano) de 4.405.336,21. A redução desse custo permitirá investimentos em equipamentos, ampliação do hospital e capacitação dos funcionários. Recurso enviado via Fundo Municipal de Saúde de Carlos Barbosa. | L87: Av. Pres. Kennedy, 343, Aurora, Carlos Barbosa - RS, 95185-000 | N87: Proposta no Fundo Nacional de Saúde 36000358504202100
A88: 2021 | B88: Casca | C88: Hospital | D88: Hospital Beneficente Santa Lucia | E88: 41160002 | F88: Saúde (Investimento - MAC) | G88: Investimento | H88: 250000 | I88: Emenda individual (processo seletivo) | K88: Aparelho de endoscopia e colonoscopia para qualificar o atendimento SUS e possibilitar que o hospital torne-se referência regional de média complexidade na especialidade de proctologia, beneficiando 32 municípios da região e atendendo demanda reprimida. | L88: R. Vitorino Monteiro, 755 - Casca, RS, 99260-000 | N88: Proposta no Fundo Nacional de Saúde 98859021002 em Análise Técnico-Econômica
A89: 2020 | B89: Caxias do sul | C89: Hospital | D89: Hospital Virvi Ramos | E89: 41160005 | F89: Saúde (Custeio - MAC) | G89: Custeio | H89: 300000 | I89: Emenda Individual (processo seletivo) | J89: Recurso pago | K89: Recurso para custeio dos serviços de saúde (Média e Alta Complexidade) | L89: R. Castro Alves, 454 - Madureira, Caxias do Sul - RS, 95041-520 | M89: Foi elaborado um Termo de Fomento com a Prefeitura Municipal de Caxias do Sul juntamente com outras Emendas Parlamentares. O valor será utilizado para aquisição de medicamentos , pagamento aos fornecedores de gases medicinais, Energia Elétrica, Água e prestadores de serviços de manutenção de equipamentos e descarte de resíduos. Termo de Fomento nº 2020/716. | N89: https://drive.google.com/file/d/1WQh8NHgMNEN0CVi-6Y9RIBEuR0LX7ILs/view?usp=sharing | O89: 26
